Workbook

Sheet Instructions
A1: BrokerVerse RAID Log
A2: One shared log of risks, assumptions, issues and dependencies, kept by the iorta TechNXT project manager and reviewed in every weekly status meeting. Items rated High go to the steering committee. The risks and dependencies pre-filled from the Implementation Approach and Plan are typical of a BrokerVerse implementation: keep, change or close them at mobilisation.
A4: Item | B4: Guidance
A5: ID | B5: R-nnn, A-nnn, I-nnn or D-nnn with a running number. Never reuse an ID.
A6: Probability (risks) | B6: 1 Rare (under 10%), 2 Unlikely (10 to 30%), 3 Possible (30 to 50%), 4 Likely (50 to 80%), 5 Almost certain (over 80%).
A7: Impact (risks and issues) | B7: 1 Negligible, 2 Minor (a task slips), 3 Moderate (a milestone slips up to one week), 4 Major (go-live or budget at risk), 5 Severe (go-live missed, compliance or data loss).
A8: Score and rating | B8: Score = probability x impact. High: 15 to 25. Medium: 8 to 14. Low: 1 to 7. Calculated on the sheet; do not type over the formula.
A9: Issue priority | B9: An issue has happened. Priority follows impact: 4 or 5 High, 3 Medium, 1 or 2 Low.
A10: Assumptions | B10: Each assumption has a date by which it must be validated; an assumption found false becomes an issue or a risk.
A11: Dependencies | B11: What the project needs from someone outside the team (the broker, an insurer, a bank, the hosting provider), by when, and its state.
A12: Status | B12: Open, In progress, Closed. Fill the closure date and keep closed items on the sheet.
A13: Summary | B13: The Summary sheet counts open items by type and rating for the status report and the steering committee.

Sheet Summary
A1: RAID summary (open and in progress items)
A3: Type | B3: High | C3: Medium | D3: Low | E3: Open total
A4: Risks | B4: =COUNTIFS(Risks!$J$2:$J$201,"High",Risks!$M$2:$M$201,"<>Closed") | C4: =COUNTIFS(Risks!$J$2:$J$201,"Medium",Risks!$M$2:$M$201,"<>Closed") | D4: =COUNTIFS(Risks!$J$2:$J$201,"Low",Risks!$M$2:$M$201,"<>Closed") | E4: =COUNTIFS(Risks!$A$2:$A$201,"<>",Risks!$M$2:$M$201,"<>Closed")
A5: Issues | B5: =COUNTIFS(Issues!$G$2:$G$201,"High",Issues!$J$2:$J$201,"<>Closed") | C5: =COUNTIFS(Issues!$G$2:$G$201,"Medium",Issues!$J$2:$J$201,"<>Closed") | D5: =COUNTIFS(Issues!$G$2:$G$201,"Low",Issues!$J$2:$J$201,"<>Closed") | E5: =COUNTIFS(Issues!$A$2:$A$201,"<>",Issues!$J$2:$J$201,"<>Closed")
A6: Assumptions | E6: =COUNTIFS(Assumptions!$A$2:$A$201,"<>",Assumptions!$H$2:$H$201,"<>Closed")
A7: Dependencies late or at risk | E7: =COUNTIFS(Dependencies!$G$2:$G$201,"Late")+COUNTIFS(Dependencies!$G$2:$G$201,"At risk")
A10: Risk matrix: open risks by probability (rows) and impact (columns)
A11: Probability \ Impact | B11: 1 | C11: 2 | D11: 3 | E11: 4 | F11: 5
A12: 5 | B12: =COUNTIFS(Risks!$G$2:$G$201,5,Risks!$H$2:$H$201,1,Risks!$M$2:$M$201,"<>Closed") | C12: =COUNTIFS(Risks!$G$2:$G$201,5,Risks!$H$2:$H$201,2,Risks!$M$2:$M$201,"<>Closed") | D12: =COUNTIFS(Risks!$G$2:$G$201,5,Risks!$H$2:$H$201,3,Risks!$M$2:$M$201,"<>Closed") | E12: =COUNTIFS(Risks!$G$2:$G$201,5,Risks!$H$2:$H$201,4,Risks!$M$2:$M$201,"<>Closed") | F12: =COUNTIFS(Risks!$G$2:$G$201,5,Risks!$H$2:$H$201,5,Risks!$M$2:$M$201,"<>Closed")
A13: 4 | B13: =COUNTIFS(Risks!$G$2:$G$201,4,Risks!$H$2:$H$201,1,Risks!$M$2:$M$201,"<>Closed") | C13: =COUNTIFS(Risks!$G$2:$G$201,4,Risks!$H$2:$H$201,2,Risks!$M$2:$M$201,"<>Closed") | D13: =COUNTIFS(Risks!$G$2:$G$201,4,Risks!$H$2:$H$201,3,Risks!$M$2:$M$201,"<>Closed") | E13: =COUNTIFS(Risks!$G$2:$G$201,4,Risks!$H$2:$H$201,4,Risks!$M$2:$M$201,"<>Closed") | F13: =COUNTIFS(Risks!$G$2:$G$201,4,Risks!$H$2:$H$201,5,Risks!$M$2:$M$201,"<>Closed")
A14: 3 | B14: =COUNTIFS(Risks!$G$2:$G$201,3,Risks!$H$2:$H$201,1,Risks!$M$2:$M$201,"<>Closed") | C14: =COUNTIFS(Risks!$G$2:$G$201,3,Risks!$H$2:$H$201,2,Risks!$M$2:$M$201,"<>Closed") | D14: =COUNTIFS(Risks!$G$2:$G$201,3,Risks!$H$2:$H$201,3,Risks!$M$2:$M$201,"<>Closed") | E14: =COUNTIFS(Risks!$G$2:$G$201,3,Risks!$H$2:$H$201,4,Risks!$M$2:$M$201,"<>Closed") | F14: =COUNTIFS(Risks!$G$2:$G$201,3,Risks!$H$2:$H$201,5,Risks!$M$2:$M$201,"<>Closed")
A15: 2 | B15: =COUNTIFS(Risks!$G$2:$G$201,2,Risks!$H$2:$H$201,1,Risks!$M$2:$M$201,"<>Closed") | C15: =COUNTIFS(Risks!$G$2:$G$201,2,Risks!$H$2:$H$201,2,Risks!$M$2:$M$201,"<>Closed") | D15: =COUNTIFS(Risks!$G$2:$G$201,2,Risks!$H$2:$H$201,3,Risks!$M$2:$M$201,"<>Closed") | E15: =COUNTIFS(Risks!$G$2:$G$201,2,Risks!$H$2:$H$201,4,Risks!$M$2:$M$201,"<>Closed") | F15: =COUNTIFS(Risks!$G$2:$G$201,2,Risks!$H$2:$H$201,5,Risks!$M$2:$M$201,"<>Closed")
A16: 1 | B16: =COUNTIFS(Risks!$G$2:$G$201,1,Risks!$H$2:$H$201,1,Risks!$M$2:$M$201,"<>Closed") | C16: =COUNTIFS(Risks!$G$2:$G$201,1,Risks!$H$2:$H$201,2,Risks!$M$2:$M$201,"<>Closed") | D16: =COUNTIFS(Risks!$G$2:$G$201,1,Risks!$H$2:$H$201,3,Risks!$M$2:$M$201,"<>Closed") | E16: =COUNTIFS(Risks!$G$2:$G$201,1,Risks!$H$2:$H$201,4,Risks!$M$2:$M$201,"<>Closed") | F16: =COUNTIFS(Risks!$G$2:$G$201,1,Risks!$H$2:$H$201,5,Risks!$M$2:$M$201,"<>Closed")

Sheet Risks
A1: ID | B1: Risk | C1: Cause | D1: Effect | E1: Category | F1: Owner | G1: Probability | H1: Impact | I1: Score | J1: Rating | K1: Mitigation | L1: Due date | M1: Status | N1: Raised on | O1: Closed on
A2: R-001 | B2: Data arrives late or incomplete | C2: Extracts from the old system not ready | D2: Mock loads slip; go-live moves | E2: Data | F2: [owner] | G2: 4 | H2: 4 | I2: =IF(OR(G2="",H2=""),"",G2*H2) | J2: =IF(OR(G2="",H2=""),"",IF(G2*H2>=15,"High",IF(G2*H2>=8,"Medium","Low"))) | K2: Data requests in week 1; templates handed out at kick-off; data readiness tracked weekly; steering committee escalation after one week of delay | M2: Open
A3: R-002 | B3: Poor data quality in the old system | C3: Duplicates, missing fields, old balances | D3: Rejected rows; receivables or balances do not reconcile | E3: Data | F3: [owner] | G3: 3 | H3: 4 | I3: =IF(OR(G3="",H3=""),"",G3*H3) | J3: =IF(OR(G3="",H3=""),"",IF(G3*H3>=15,"High",IF(G3*H3>=8,"Medium","Low"))) | K3: Two to four mock loads with reconciliation; the broker cleanses at source; rejected-row reports from each upload | M3: Open
A4: R-003 | B4: Requests for customisation | C4: Old system habits; new wishes | D4: Scope and timeline grow | E4: Scope | F4: [owner] | G4: 3 | H4: 4 | I4: =IF(OR(G4="",H4=""),"",G4*H4) | J4: =IF(OR(G4="",H4=""),"",IF(G4*H4>=15,"High",IF(G4*H4>=8,"Medium","Low"))) | K4: Configure-first principle; fit-gap classes; change request process with steering committee approval | M4: Open
A5: R-004 | B5: Key users unavailable | C5: Business as usual takes priority | D5: Decisions late; weak UAT and training | E5: People | F5: [owner] | G5: 3 | H5: 3 | I5: =IF(OR(G5="",H5=""),"",G5*H5) | J5: =IF(OR(G5="",H5=""),"",IF(G5*H5>=15,"High",IF(G5*H5>=8,"Medium","Low"))) | K5: Named key users with committed time; backups named; workshops scheduled at kick-off | M5: Open
A6: R-005 | B6: Opening balances and open items do not agree | C6: Cut-off differences | D6: Ledger wrong from day one | E6: Data | F6: [owner] | G6: 2 | H6: 5 | I6: =IF(OR(G6="",H6=""),"",G6*H6) | J6: =IF(OR(G6="",H6=""),"",IF(G6*H6>=15,"High",IF(G6*H6>=8,"Medium","Low"))) | K6: Premiums Receivable balance equals the open item total; Due to Insurers reconciled to insurer statements; Accounting Manager signs off | M6: Open
A7: R-006 | B7: Tax rates or ATC not confirmed | C7: Tax adviser not engaged in time | D7: Wrong VAT or withholding | E7: Compliance | F7: [owner] | G7: 2 | H7: 4 | I7: =IF(OR(G7="",H7=""),"",G7*H7) | J7: =IF(OR(G7="",H7=""),"",IF(G7*H7>=15,"High",IF(G7*H7>=8,"Medium","Low"))) | K7: Tax adviser review in the configuration phase; VAT Summary checked in UAT | M7: Open
A8: R-007 | B8: Official receipt numbering out of line with the Authority to Print | C8: Last numbers not supplied | D8: Compliance exposure | E8: Compliance | F8: [owner] | G8: 2 | H8: 4 | I8: =IF(OR(G8="",H8=""),"",G8*H8) | J8: =IF(OR(G8="",H8=""),"",IF(G8*H8>=15,"High",IF(G8*H8>=8,"Medium","Low"))) | K8: Numbering set from the last number used; checked in UAT | M8: Open
A9: R-008 | B9: E-mail or payment gateway credentials late | C9: Provider onboarding | D9: Approval links, receipts by e-mail, password resets and online payments not working | E9: Integration | F9: [owner] | G9: 3 | H9: 3 | I9: =IF(OR(G9="",H9=""),"",G9*H9) | J9: =IF(OR(G9="",H9=""),"",IF(G9*H9>=15,"High",IF(G9*H9>=8,"Medium","Low"))) | K9: Requested in mobilisation; the system works without the gateway; sandbox first | M9: Open
A10: R-009 | B10: Users not ready at go-live | C10: Training too early or skipped | D10: Errors and slow work | E10: People | F10: [owner] | G10: 2 | H10: 3 | I10: =IF(OR(G10="",H10=""),"",G10*H10) | J10: =IF(OR(G10="",H10=""),"",IF(G10*H10>=15,"High",IF(G10*H10>=8,"Medium","Low"))) | K10: Role-based training, assessment, floor walkers in the first week | M10: Open
A11: R-010 | B11: First month-end close outside hypercare | C11: Go-live late in the month | D11: Close issues found late | E11: Schedule | F11: [owner] | G11: 2 | H11: 3 | I11: =IF(OR(G11="",H11=""),"",G11*H11) | J11: =IF(OR(G11="",H11=""),"",IF(G11*H11>=15,"High",IF(G11*H11>=8,"Medium","Low"))) | K11: Hypercare extends to the first close | M11: Open
I12: =IF(OR(G12="",H12=""),"",G12*H12) | J12: =IF(OR(G12="",H12=""),"",IF(G12*H12>=15,"High",IF(G12*H12>=8,"Medium","Low")))
I13: =IF(OR(G13="",H13=""),"",G13*H13) | J13: =IF(OR(G13="",H13=""),"",IF(G13*H13>=15,"High",IF(G13*H13>=8,"Medium","Low")))
I14: =IF(OR(G14="",H14=""),"",G14*H14) | J14: =IF(OR(G14="",H14=""),"",IF(G14*H14>=15,"High",IF(G14*H14>=8,"Medium","Low")))
I15: =IF(OR(G15="",H15=""),"",G15*H15) | J15: =IF(OR(G15="",H15=""),"",IF(G15*H15>=15,"High",IF(G15*H15>=8,"Medium","Low")))
I16: =IF(OR(G16="",H16=""),"",G16*H16) | J16: =IF(OR(G16="",H16=""),"",IF(G16*H16>=15,"High",IF(G16*H16>=8,"Medium","Low")))
I17: =IF(OR(G17="",H17=""),"",G17*H17) | J17: =IF(OR(G17="",H17=""),"",IF(G17*H17>=15,"High",IF(G17*H17>=8,"Medium","Low")))
I18: =IF(OR(G18="",H18=""),"",G18*H18) | J18: =IF(OR(G18="",H18=""),"",IF(G18*H18>=15,"High",IF(G18*H18>=8,"Medium","Low")))
I19: =IF(OR(G19="",H19=""),"",G19*H19) | J19: =IF(OR(G19="",H19=""),"",IF(G19*H19>=15,"High",IF(G19*H19>=8,"Medium","Low")))
I20: =IF(OR(G20="",H20=""),"",G20*H20) | J20: =IF(OR(G20="",H20=""),"",IF(G20*H20>=15,"High",IF(G20*H20>=8,"Medium","Low")))
I21: =IF(OR(G21="",H21=""),"",G21*H21) | J21: =IF(OR(G21="",H21=""),"",IF(G21*H21>=15,"High",IF(G21*H21>=8,"Medium","Low")))
I22: =IF(OR(G22="",H22=""),"",G22*H22) | J22: =IF(OR(G22="",H22=""),"",IF(G22*H22>=15,"High",IF(G22*H22>=8,"Medium","Low")))
I23: =IF(OR(G23="",H23=""),"",G23*H23) | J23: =IF(OR(G23="",H23=""),"",IF(G23*H23>=15,"High",IF(G23*H23>=8,"Medium","Low")))
... I201: =IF(OR(G201="",H201=""),"",G201*H201) | J201: =IF(OR(G201="",H201=""),"",IF(G201*H201>=15,"High",IF(G201*H201>=8,"Medium","Low")))

Sheet Assumptions
A1: ID | B1: Assumption | C1: Basis | D1: Effect if false | E1: Owner | F1: Validate by | G1: Validated | H1: Status | I1: Remarks
A2: A-001 | B2: The size of the implementation (Small, Medium or Large) agreed at mobilisation stays valid once the data volumes are known. | C2: Implementation Approach and Plan, sizing | D2: Plan and price re-baselined | E2: [PM] | H2: Open
A3: A-002 | B3: The broker provides its SMTP mailbox before the integrations phase. | C3: Dependencies on the broker | D3: E-mails stay queued in the outbox | E3: [IT head] | H3: Open
A4: A-003 | B4: The delivered chart of accounts is used with the accountant's mapping, not replaced. | C4: Configure-first principle | D4: Posting rules and account determination redone | E4: [Accounting Manager] | H4: Open

Sheet Issues
A1: ID | B1: Issue | C1: Effect | D1: Category | E1: Owner | F1: Impact | G1: Priority | H1: Action | I1: Due date | J1: Status | K1: Raised on | L1: Closed on | M1: From risk
A2: I-001 | B2: [Example: bank statement export of one bank does not match the delivered formats] | C2: [Bank reconciliation not testable in SIT] | D2: Integration | E2: [owner] | F2: 3 | G2: =IF(F2="","",IF(F2>=4,"High",IF(F2=3,"Medium","Low"))) | H2: [Add an insurer or bank statement format in Master > Finance] | J2: Open
G3: =IF(F3="","",IF(F3>=4,"High",IF(F3=3,"Medium","Low")))
G4: =IF(F4="","",IF(F4>=4,"High",IF(F4=3,"Medium","Low")))
G5: =IF(F5="","",IF(F5>=4,"High",IF(F5=3,"Medium","Low")))
G6: =IF(F6="","",IF(F6>=4,"High",IF(F6=3,"Medium","Low")))
G7: =IF(F7="","",IF(F7>=4,"High",IF(F7=3,"Medium","Low")))
G8: =IF(F8="","",IF(F8>=4,"High",IF(F8=3,"Medium","Low")))
G9: =IF(F9="","",IF(F9>=4,"High",IF(F9=3,"Medium","Low")))
G10: =IF(F10="","",IF(F10>=4,"High",IF(F10=3,"Medium","Low")))
G11: =IF(F11="","",IF(F11>=4,"High",IF(F11=3,"Medium","Low")))
G12: =IF(F12="","",IF(F12>=4,"High",IF(F12=3,"Medium","Low")))
G13: =IF(F13="","",IF(F13>=4,"High",IF(F13=3,"Medium","Low")))
G14: =IF(F14="","",IF(F14>=4,"High",IF(F14=3,"Medium","Low")))
... G201: =IF(F201="","",IF(F201>=4,"High",IF(F201=3,"Medium","Low")))

Sheet Dependencies
A1: ID | B1: Dependency | C1: Provided by | D1: Needed for | E1: Needed by | F1: Owner | G1: State | H1: Remarks
A2: D-001 | B2: Named project manager, key users and Accounting Manager | C2: Broker | D2: Mobilisation | E2: Week 1 | F2: [owner] | G2: On track
A3: D-002 | B3: Insurer list and agreements, commission and referrer rates, product list | C3: Broker | D3: Configuration | E3: End of discovery | F3: [owner] | G3: On track
A4: D-003 | B4: Chart of accounts and the accountant's mapping decisions | C4: Broker | D4: Ledger configuration | E4: Start of configuration | F4: [owner] | G4: On track
A5: D-004 | B5: BIR Authority to Print or registered series; last numbers used | C5: Broker | D5: Document numbering | E5: Configuration | F5: [owner] | G5: On track
A6: D-005 | B6: SMTP mailbox and credentials; payment gateway merchant account | C6: Broker | D6: Integrations | E6: Integrations phase | F6: [owner] | G6: On track
A7: D-006 | B7: One recent statement export per bank account | C7: Broker | D7: Bank reconciliation formats | E7: Integrations phase | F7: [owner] | G7: On track
A8: D-007 | B8: In-force policy, open receivable and trial balance extracts in the templates | C8: Broker | D8: Mock loads and cutover | E8: Each mock load | F8: [owner] | G8: On track
A9: D-008 | B9: User list with roles and e-mail addresses | C9: Broker | D9: Training and go-live | E9: Two weeks before training | F9: [owner] | G9: On track
A10: D-009 | B10: UAT testers and sign-off authority | C10: Broker | D10: UAT | E10: UAT phase | F10: [owner] | G10: On track
A11: D-010 | B11: Production environment provisioned and backups tested | C11: Hosting provider | D11: Go-live | E11: Before mock load 2 | F11: [owner] | G11: On track

Sheet Lists
A1: Status | B1: Score | C1: Category | D1: Priority | E1: Dependency state
A2: Open | B2: 1 | C2: Scope | D2: High | E2: On track
A3: In progress | B3: 2 | C3: Schedule | D3: Medium | E3: At risk
A4: Closed | B4: 3 | C4: Data | D4: Low | E4: Late
B5: 4 | C5: People | E5: Delivered
B6: 5 | C6: Technical
C7: Integration
C8: Compliance
C9: Commercial
C10: Hosting
