Workbook
Name FX: Inputs!$B$6
Name FX_Date: Inputs!$B$7
Name VAT: Inputs!$B$8
Name AMC_Rate: Inputs!$B$9
Name Esc: Inputs!$B$10
Name AMC_Start: Inputs!$B$11
Name Onboard_Pct: Inputs!$B$12
Name Infra_Margin: Inputs!$B$13
Name Infra_Esc: Inputs!$B$14
Name Days_per_LOB: Inputs!$B$15
Name Round_To: Inputs!$B$16
Name IT_Low: Inputs!$B$17
Name IT_High: Inputs!$B$18
Name Validity: Inputs!$B$19
Name Calc_Users: Inputs!$B$23
Name Calc_LOBs: Inputs!$B$24
Name Rate_BA: Inputs!$B$36
Name Rate_Dev: Inputs!$B$37
Name Rate_QA: Inputs!$B$38
Name Rate_PM: Inputs!$B$39
Name Blended: Inputs!$B$40
Name Rate_Trainer: Inputs!$B$41
Name Rate_Onsite: Inputs!$B$42
Name CR_BA: Inputs!$B$46
Name CR_QA: Inputs!$B$47
Name CR_PM: Inputs!$B$48
Name CR_Cont: Inputs!$B$49
Name CR_Small_Max: Inputs!$B$50
Name CR_Med_Max: Inputs!$B$51
Name CR_Large_Max: Inputs!$B$52
Name CR_Dev_Days: Inputs!$B$53
Name Env_Setup_Days: Inputs!$B$57
Name Mig_Days_Source: Inputs!$B$58
Name Int_Std_Days: Inputs!$B$59
Name Int_Cx_Days: Inputs!$B$60
Name Report_Days: Inputs!$B$61
Name Conn_Golive_Days: Inputs!$B$62
Name AML_Act_Days: Inputs!$B$63
Name IC_Act_Days: Inputs!$B$64
Name BIR_Act_Days: Inputs!$B$65
Name Dealer_Prog_Days: Inputs!$B$66
Name Brand_Pack_Days: Inputs!$B$67
Name AMLC_Val_Days: Inputs!$B$68
Name IC_Form_Days: Inputs!$B$69
Name EOPT_Rev_Days: Inputs!$B$70
Name CAS_Reg_Days: Inputs!$B$71
Name EIS_Enrol_Days: Inputs!$B$72
Name CTPL_Cert_Days: Inputs!$B$73
Name Insurer_Onb_Days: Inputs!$B$74
Name Bank_Cert_Days: Inputs!$B$75
Name SMS_Act_Days: Inputs!$B$76
Name Screen_Prov_Days: Inputs!$B$77
Name NP_Small_USD: Inputs!$B$91
Name NP_Med_USD: Inputs!$B$92
Name PreProd_Factor: Inputs!$B$93
Name PreProd_GoLive_Months: Inputs!$B$94
Name PreProd_Rel_Months: Inputs!$B$95
Name Major_Rel_Year: Inputs!$B$96
Name Azure_Factor: Inputs!$B$104
Name Local_Factor: Inputs!$B$105

Sheet Read Me
A1: BrokerVerse OOTB: commercials and pricing workbook
A2: iorta TechNXT. Prepared 03 October 2026, revised 04 October 2026 (optional modules and partner services confirmed). Prices in PHP, exclusive of 12% VAT. For discussion with prospective broker customers.
A4: Topic | B4: Notes
A5: Purpose | B5: Sets the commercial model for BrokerVerse OOTB (the out-of-the-box, as-is version) for Philippine non-life insurance brokers: Model A perpetual licence with Annual Maintenance Contract (AMC), Model B monthly subscription (SaaS), optional infrastructure, change request (CR) rates and optional services, with three worked quotes and the market evidence behind the price points.
A6: How to use | B6: 1. Change drivers only on the Inputs sheet (yellow cells, blue text). Every other sheet is formula driven. 2. To price a prospect, enter its user count and number of lines of business in Inputs (Calculator section). The calculators on Perpetual Model and Subscription Model update, with the break-even year. 3. To change the three worked examples, edit the Sample quote scenarios table in Inputs. 4. Infrastructure is optional and separate. Pick AWS, Azure or Local partner per scenario; the customer may host itself at no fee. Hosting is priced per environment set (Infrastructure sheet). 5. Recalculate (F9) if your spreadsheet tool does not recalculate on open.
A7: Size tiers and user slabs | B7: Small 1 to 25 users, Medium 26 to 100, Large 101 to 300, Enterprise above 300. User prices are graduated: the first 25 users are charged at the Small slab rate, users 26 to 100 at the Medium rate, and so on. This avoids a price drop when a broker crosses a tier boundary. The tier of the customer (by total users) sets the implementation effort, the minimum billable users for subscription, the included training days and the infrastructure size.
A8: Users | B8: A user is a named person with a BrokerVerse sign-in (one role per user, as set up in Master > Generals > User Management > User). Inactive users are not counted. Read-only or customer-portal access is outside this price list.
A9: Model A: perpetual | B9: One-time implementation fee by size and lines of business; one-time perpetual licence fee by user slab, payable on go-live; AMC at 22% of the licence fee from the AMC start year (default Year 2, after a 12-month warranty), increasing 5% a year. AMC covers corrections, product updates of the OOTB version, regulatory form updates released for all customers and standard support.
A10: Model B: subscription | B10: Monthly price per user by slab, billed monthly in advance, increasing 5% at each contract anniversary. Minimum billable users apply per tier. The onboarding fee equals the implementation fee times the onboarding percentage in Inputs (default 100%). Subscription includes the licence right for the term, updates and standard support. Hosting is not included and is quoted separately.
A11: Implementation effort | B11: Implementation = (base man-days for the tier + extra man-days for each line of business above the number included) x blended day rate, rounded to PHP 10,000. Each line of business needs product and cover set-up in the product configurator, rating and tax lines (documentary stamp tax, VAT or premium tax, local government tax, fire service tax where relevant), policy and endorsement document templates, insurer commission rates and UAT test cases. That is why the count of lines of business changes the effort.
A12: Taxes | B12: All prices exclude 12% VAT, which is added on the invoice (Philippine VAT on services and on the sale or licensing of software). Customers who are withholding agents deduct creditable withholding tax as their status and the payment type require, commonly 2% for services and 1% to 2% on software or subscription fees under RR 2-98 as amended, and issue BIR Form 2307 to iorta TechNXT. Withholding does not reduce the invoice price. The rates are to be confirmed by the customer's and iorta TechNXT's tax advisers.
A13: Exchange rate | B13: USD columns are for reference only and use the PHP per USD rate in Inputs (BSP reference rate 62.75 on 25 September 2026). The contract currency is PHP.
A14: Estimates and assumptions | B14: Rows and cells shaded light orange, and figures marked "Estimate" or "Assumption", are not published facts. They are the basis stated beside them and must be confirmed before a binding quotation. Competitor prices in Market Benchmark are mostly third-party estimates because the vendors do not publish list prices.
A15: Environments and hosting | B15: Small and Medium brokers: Dev, UAT and Production. Large and Enterprise: Dev, SIT, UAT and Production with high availability. Pre-Prod is temporary for every size, created from a production backup for the go-live rehearsal and for each major release, then removed; it is billed per month of use. Each environment is priced on its own line (Inputs and Infrastructure). Hosting fees do not increase yearly: provider price changes are passed through at cost.
... A18: Sheets | B18: Inputs, Size Tiers, Perpetual Model, Subscription Model, Infrastructure, Change Requests, Optional Services, Sample Quotes, Market Benchmark, Sources.

Sheet Inputs
A1: Inputs: all editable drivers
A2: Change yellow cells only. Light orange notes mark estimates or assumptions.
A4: General drivers
A5: Driver | B5: Value | C5: Unit | D5: Basis
A6: Exchange rate | B6: 62.75 | C6: PHP per USD | D6: BSP reference rate, 25 September 2026 (source S14). Reference only.
A7: Exchange rate date | B7: 25 Sep 2026 | C7: date | D7: Update with the rate on the quotation date.
A8: VAT rate | B8: 0.12 | C8: % | D8: Philippine VAT, added to all prices (prices exclusive of VAT).
A9: AMC rate (of perpetual licence fee) | B9: 0.22 | C9: % | D9: Business owner instruction.
A10: Annual escalation (AMC, subscription, support) | B10: 0.05 | C10: % | D10: Business owner instruction. Applied at each anniversary.
A11: AMC starts in contract year | B11: 2 | C11: year | D11: Assumption: Year 1 after go-live is covered by a 12-month warranty. Set to 1 to bill AMC from go-live.
A12: Subscription onboarding fee as % of implementation fee | B12: 1 | C12: % | D12: Assumption: same set-up work in both models.
A13: Infrastructure margin on cloud cost | B13: 0.2 | C13: % | D13: Assumption: covers FX movement, monitoring, patching and backup checks.
A14: Infrastructure annual change | B14: 0 | C14: % | D14: Hosting fees do not escalate yearly: provider price changes are passed through at cost under the Hosting Agreement. Keep at 0%.
A15: Extra implementation man-days per line of business above the included count | B15: 6 | C15: man-days | D15: Estimate: product and cover set-up, rating and tax lines, 2 to 3 document templates, insurer commission rates, UAT cases.
A16: Round implementation and service fees to | B16: 10000 | C16: PHP | D16: Presentation.
A17: IT budget benchmark, low (share of revenue) | B17: 0.03 | C17: % | D17: Gartner insurance IT spend 3.1% of revenue (2010); later benchmarks 4% to 7% (sources S10, S11).
A18: IT budget benchmark, high (share of revenue) | B18: 0.07 | C18: % | D18: As above.
A19: Quotation validity | B19: 90 | C19: days | D19: Commercial policy.
A21: Calculator (used by the calculators on Perpetual Model and Subscription Model)
A22: Driver | B22: Value | C22: Unit | D22: Basis
A23: Number of named users | B23: 40 | C23: users | D23: Enter the prospect figures.
A24: Number of lines of business to configure | B24: 6 | C24: lines | D24: Enter the prospect figures.
A26: Size tiers, user slabs and tier parameters
A27: Tier | B27: From users | C27: To users | D27: Perpetual licence per user (PHP, slab) | E27: Subscription per user per month (PHP, slab) | F27: Minimum billable users (subscription) | G27: Implementation base man-days | H27: Lines of business included | I27: Training days included | J27: Reference users (5-year view) | K27: Reference lines of business | L27: 24x7 Severity 1 support, annual (PHP) | M27: Indicative annual commission income (PHP, estimate) | N27: Basis
A28: Small | B28: 1 | C28: 25 | D28: 90000 | E28: 3200 | F28: 10 | G28: 70 | H28: 5 | I28: 4 | J28: 15 | K28: 5 | L28: 240000 | M28: 25000000 | N28: Commission income estimate: IC 2024 ranks 30 and below (rank 30 earned PHP 55.2 million). Price slab: see Market Benchmark.
A29: Medium | B29: 26 | C29: 100 | D29: 78000 | E29: 2800 | F29: 26 | G29: 130 | H29: 8 | I29: 6 | J29: 60 | K29: 8 | L29: 480000 | M29: 120000000 | N29: IC 2024 ranks about 10 to 30 (rank 20 earned PHP 98.0 million).
A30: Large | B30: 101 | C30: 300 | D30: 66000 | E30: 2400 | F30: 101 | G30: 230 | H30: 12 | I30: 10 | J30: 180 | K30: 12 | L30: 900000 | M30: 500000000 | N30: IC 2024 ranks 4 to 10 (Lockton PHP 712 million, PhilPacific PHP 598 million).
A31: Enterprise | B31: 301 | C31: 100000 | D31: 54000 | E31: 2000 | F31: 301 | G31: 360 | H31: 16 | I31: 15 | J31: 400 | K31: 16 | L31: 1500000 | M31: 1500000000 | N31: IC 2024 top 3 earned PHP 2.0 to 2.4 billion each (BDO, Marsh, Aon).
A32: Implementation base man-days, lines of business and training days are estimates for the OOTB version (configuration, data load with the standard templates, UAT support, training, go-live and hypercare). Commission income is an estimate used only for the affordability check.
A34: Day rates (PHP per man-day of 8 hours)
A35: Role | B35: Day rate (PHP) | C35: Mix for blended rate | D35: USD per day | E35: Basis
A36: Business analyst | B36: 18000 | C36: 0.25 | D36: =B36/FX | E36: Estimate. PH senior BA salary about PHP 70,500 a month (S17); vendor rate covers benefits, overhead, bench and margin.
A37: Developer | B37: 16000 | C37: 0.4 | D37: =B37/FX | E37: Estimate. PH outsourcing market USD 30 to 50 an hour mid-level, 50 to 75 senior (S15, S16); PHP 16,000 = USD 255 a day.
A38: QA engineer | B38: 12000 | C38: 0.25 | D38: =B38/FX | E38: Estimate. PH senior QA salary about PHP 65,000 a month (S18).
A39: Project manager | B39: 22000 | C39: 0.1 | D39: =B39/FX | E39: Estimate. PH IT project manager salary PHP 60,000 to 123,000 a month (S19).
A40: Blended day rate (weighted by mix) | B40: =ROUND(SUMPRODUCT(B36:B39,C36:C39)/SUM(C36:C39),-2) | C40: =SUM(C36:C39) | D40: =B40/FX
A41: Trainer day rate (end-user or train-the-trainer) | B41: 30000 | D41: =B41/FX | E41: Assumption: one trainer, up to 15 participants, preparation included.
A42: On-site consultant day rate (Metro Manila) | B42: 20000 | D42: =B42/FX | E42: Assumption: travel, lodging and meals outside Metro Manila billed at cost.
A44: Change request estimation ratios
A45: Driver | B45: Value | C45: Unit | D45: Basis
A46: Business analysis effort as % of development | B46: 0.3 | C46: % | D46: Assumption: requirement note, impact analysis, UAT support.
A47: Testing effort as % of development | B47: 0.4 | C47: % | D47: Assumption: test cases, regression of affected screens and reports.
A48: Project management as % of BA + development + testing | B48: 0.1 | C48: % | D48: Assumption.
A49: Contingency | B49: 0.1 | C49: % | D49: Assumption: unknowns found during analysis.
A50: Small CR band: total man-days up to | B50: 5 | C50: man-days | D50: Commercial policy.
A51: Medium CR band: total man-days up to | B51: 20 | C51: man-days | D51: Commercial policy.
A52: Large CR band: total man-days up to (above this, a separate project) | B52: 60 | C52: man-days | D52: Commercial policy.
A53: CR calculator: development man-days estimated | B53: 8 | C53: man-days | D53: Enter the developer estimate for the change.
A55: Optional services drivers
A56: Driver | B56: Value | C56: Unit | D56: Basis
A57: Additional environment: set-up man-days | B57: 6 | C57: man-days | D57: Estimate: provisioning, deployment, configuration copy, smoke test.
A58: Data migration beyond templates: man-days per additional legacy source | B58: 15 | C58: man-days | D58: Estimate: mapping, extraction scripts, 2 trial loads, reconciliation.
A59: Additional integration, standard (documented API or file) | B59: 20 | C59: man-days | D59: Estimate: a new kind of interface not covered by the delivered connectors, e.g. a payment gateway variant or an accounting package feed.
A60: Additional integration, complex (no API, two-way, or batch reconciliation) | B60: 45 | C60: man-days | D60: Estimate.
A61: New report or document template (typical) | B61: 4 | C61: man-days | D61: Estimate: falls in the Small CR band.
A62: Go-live of a delivered connector with one partner | B62: 5 | C62: man-days | D62: Estimate: SMS gateway, CTPL provider, one insurer API mapping, one bank file layout or the BIR EIS: configuration, credentials check, live test, support of the partner acceptance. Optional service confirmed by management on 04 October 2026.
A63: Activation of the AML/CFT toolkit | B63: 8 | C63: man-days | D63: Estimate: risk factors and rules workshop with the compliance officer, settings, first list loads, provider set-up, AMLC test file. Optional service confirmed by management on 04 October 2026.
A64: Activation of the IC compliance registers | B64: 6 | C64: man-days | D64: Estimate: licence and fit and proper register load, insurer certificates, complaints and breach settings, IC statement account mapping to the broker chart. Optional service confirmed by management on 04 October 2026.
A65: Activation of the BIR pack | B65: 8 | C65: man-days | D65: Estimate: BIR and EOPT invoice settings with the tax adviser, ATC mapping, DAT file dry run, CAS books pack. Optional service confirmed by management on 04 October 2026.
A66: Set-up of one dealer programme | B66: 3 | C66: man-days | D66: Estimate: channels, rates, subsidy, bank letter and the first upload. Optional service confirmed by management on 04 October 2026.
A67: Client brand pack | B67: 2 | C67: man-days | D67: Estimate: theme, sign-in picture, document and e-mail branding, e-signature mapping, exported pack. Optional service confirmed by management on 04 October 2026.
A68: AMLC reporting file validation and portal test | B68: 3 | C68: man-days | D68: Estimate: CTR and STR layout, institution and transaction codes confirmed with the AMLC, test file accepted in the AMLC portal. Optional service confirmed by management on 04 October 2026.
... A77: Screening list provider onboarding | B77: 2 | C77: man-days | D77: Estimate: provider contract data, API key, adapter test and first screening run. Optional service confirmed by management on 04 October 2026.
A79: Infrastructure: AWS reference cost per month of the Production environment (USD)
A80: Component | B80: Small | C80: Medium | D80: Large | E80: Enterprise | F80: Basis
A81: Application containers (API, web, scheduler) | B81: 90 | C81: 135 | D81: 180 | E81: 360 | F81: Estimate: 2/3/4/8 containers of 1 vCPU, 2 GB (Fargate, Singapore).
A82: Managed PostgreSQL 16 (instance and storage) | B82: 85 | C82: 320 | D82: 640 | E82: 1280 | F82: Estimate: db.t4g.medium single-AZ / db.m7g.large Multi-AZ / m7g.xlarge Multi-AZ / m7g.2xlarge Multi-AZ (S20). Large and Enterprise: high availability.
A83: Object storage and backups (documents, snapshots) | B83: 20 | C83: 40 | D83: 90 | E83: 180 | F83: Estimate: S3 and snapshot storage, growing with policies and uploads.
A84: Network (load balancer, CDN, data transfer) | B84: 45 | C84: 70 | D84: 120 | E84: 220 | F84: Estimate.
A85: Security and monitoring (WAF, logs, alarms, secrets, keys) | B85: 35 | C85: 60 | D85: 110 | E85: 200 | F85: Estimate.
A86: Disaster recovery copy (cross-region backups) | B86: 0 | C86: 0 | D86: 0 | E86: 400 | F86: Estimate: Enterprise only; optional for others. Not part of Pre-Prod.
A87: Production reference cost per month (USD) | B87: =SUM(B81:B86) | C87: =SUM(C81:C86) | D87: =SUM(D81:D86) | E87: =SUM(E81:E86)
A89: Infrastructure: non-production environment sizes and Pre-Prod use
A90: Driver | B90: Value | C90: Unit | D90: Basis
A91: Non-production environment, small: cloud cost per month | B91: 150 | C91: USD | D91: Estimate: 1 container of 1 vCPU, 2 GB; PostgreSQL db.t4g.medium single-AZ, 50 GB; file store; backups 7 to 14 days. Dev in every tier; UAT of Small and Medium brokers.
A92: Non-production environment, medium: cloud cost per month | B92: 300 | C92: USD | D92: Estimate: 2 containers of 1 vCPU, 2 GB (the second for the UAT performance test); db.t4g.large single-AZ, 100 GB; file store; load balancer. SIT and UAT of Large and Enterprise brokers.
A93: Pre-Prod cloud cost relative to Production (without the DR copy) | B93: 1 | C93: % | D93: Assumption: Pre-Prod is restored from a production backup and runs at production topology and size, so the rehearsal measures real timings.
A94: Pre-Prod months of use around go-live | B94: 2 | C94: months | D94: Assumption: created before the cutover rehearsal and removed after hypercare (1 to 2 months). Billed per month of use.
A95: Pre-Prod months of use per major release | B95: 1 | C95: months | D95: Assumption: created from a production backup for the release rehearsal and removed after the release.
A96: Major releases per year (yearly hosting view only) | B96: 1 | C96: releases | D96: Assumption for budgeting. Major releases are announced at least 6 months ahead (Release Notes and Roadmap); the invoice follows the actual months of use.
A98: Infrastructure: environment set by tier, AWS reference cost per month (USD)
A99: Tier | B99: Dev | C99: SIT | D99: UAT | E99: Production | F99: Standing environments | G99: Pre-Prod per month of use | H99: Environment set and basis
A100: =A28 | B100: =NP_Small_USD | C100: 0 | D100: =NP_Small_USD | E100: =B87 | F100: =SUM(B100:E100) | G100: =SUM(B81:B85)*PreProd_Factor | H100: Dev, UAT, Production, temporary Pre-Prod. Integration and SIT in Dev, then promoted to UAT for testing.
A101: =A29 | B101: =NP_Small_USD | C101: 0 | D101: =NP_Small_USD | E101: =C87 | F101: =SUM(B101:E101) | G101: =SUM(C81:C85)*PreProd_Factor | H101: Dev, UAT, Production, temporary Pre-Prod. As Small.
A102: =A30 | B102: =NP_Small_USD | C102: =NP_Med_USD | D102: =NP_Med_USD | E102: =D87 | F102: =SUM(B102:E102) | G102: =SUM(D81:D85)*PreProd_Factor | H102: Dev, SIT, UAT, Production with high availability, temporary Pre-Prod. SIT and UAT are separate.
A103: =A31 | B103: =NP_Small_USD | C103: =NP_Med_USD | D103: =NP_Med_USD | E103: =E87 | F103: =SUM(B103:E103) | G103: =SUM(E81:E85)*PreProd_Factor | H103: As Large, with the cross-region DR copy in Production.
A104: Azure cost relative to AWS | B104: 1.05 | F104: Assumption: comparable list prices in Southeast Asia (D4s v5 Linux about USD 158 a month, S21); +5% for managed PostgreSQL and WAF differences.
A105: Local partner cloud cost relative to AWS | B105: 0.95 | F105: Assumption: Philippine data-centre or partner cloud priced in PHP; lower compute and bandwidth, database run as managed VM. Confirm with a partner quotation.
A107: Sample quote scenarios (used by Sample Quotes)
A108: Driver | B108: Example 1 | C108: Example 2 | D108: Example 3 | F108: Notes
A109: Broker profile | B109: Small broker | C109: Medium broker | D109: Large broker | F109: Label only.
A110: Named users | B110: 15 | C110: 60 | D110: 180 | F110: Tier follows from the user count.
A111: Lines of business | B111: 5 | C111: 8 | D111: 12 | F111: Motor, fire, marine, casualty, engineering, bonds and so on.
A112: Infrastructure provider (AWS, Azure, Local partner, Customer) | B112: AWS | C112: Azure | D112: Local partner | F112: "Customer" means the broker hosts itself: no infrastructure fee.
A113: 24x7 Severity 1 support (Yes/No) | B113: No | C113: Yes | D113: Yes | F113: Optional.
A114: Extra training days | B114: 0 | C114: 2 | D114: 4 | F114: Beyond the days included for the tier.
A115: Extra legacy data sources to migrate | B115: 0 | C115: 1 | D115: 2 | F115: Beyond the standard templates.
A116: Additional standard integrations | B116: 0 | C116: 1 | D116: 2 | F116: One-time.

Sheet Size Tiers
A1: Size tiers and user slabs
A2: Tier definitions come from Inputs. Profile columns are estimates from the Insurance Commission broker ranking (2024) and market practice.
A4: Tier | B4: From users | C4: To users | D4: Typical broker profile (estimate) | E4: IC 2024 commission ranking position (evidence) | F4: Perpetual licence per user, slab (PHP) | G4: Subscription per user per month, slab (PHP) | H4: Minimum billable users | I4: Lines of business included | J4: Training days included
A5: =Inputs!A28 | B5: =Inputs!B28 | C5: =IF(Inputs!C28>=100000,"and above",Inputs!C28) | D5: Single office or 2 to 3 branches; 10 to 40 staff; SME, motor and fire focus; owner-managed finance. | E5: Rank 30 to 67: commission up to about PHP 55 million (rank 30, Moneyhero, PHP 55.2 million). | F5: =Inputs!D28 | G5: =Inputs!E28 | H5: =Inputs!F28 | I5: =Inputs!H28 | J5: =Inputs!I28
A6: =Inputs!A29 | B6: =Inputs!B29 | C6: =IF(Inputs!C29>=100000,"and above",Inputs!C29) | D6: Several branches; 40 to 150 staff; corporate and affinity accounts; in-house accounting team. | E6: Rank 10 to 30: PHP 55 to 250 million (rank 20, East West, PHP 98.0 million). | F6: =Inputs!D29 | G6: =Inputs!E29 | H6: =Inputs!F29 | I6: =Inputs!H29 | J6: =Inputs!I29
A7: =Inputs!A30 | B7: =Inputs!B30 | C7: =IF(Inputs!C30>=100000,"and above",Inputs!C30) | D7: National branch network or multinational; 150 to 400 staff; large corporate and reinsurance placements. | E7: Rank 4 to 10: PHP 250 to 800 million (Lockton PHP 712 million; PhilPacific PHP 598 million). | F7: =Inputs!D30 | G7: =Inputs!E30 | H7: =Inputs!F30 | I7: =Inputs!H30 | J7: =Inputs!I30
A8: =Inputs!A31 | B8: =Inputs!B31 | C8: =IF(Inputs!C31>=100000,"and above",Inputs!C31) | D8: Bank-affiliated or global broker; over 400 staff; high transaction volumes and bancassurance. | E8: Top 3: PHP 2.0 to 2.4 billion (BDO PHP 2,434 million; Marsh PHP 2,075 million; Aon PHP 2,047 million). | F8: =Inputs!D31 | G8: =Inputs!E31 | H8: =Inputs!F31 | I8: =Inputs!H31 | J8: =Inputs!I31
A10: How the graduated slabs work
A11: Each user is priced at the rate of the slab it falls in. Example: 40 users = 25 users at the Small rate + 15 users at the Medium rate. The broker tier (by total users) sets implementation effort, minimum billable users, included training and infrastructure size.
A13: Affordability check against IT budget norms (reference users per tier, Year 1 prices)
A14: Tier | B14: Reference users | C14: Commission income (PHP, estimate) | D14: IT budget at low benchmark (PHP) | E14: IT budget at high benchmark (PHP) | F14: Subscription Year 1 (PHP) | G14: Subscription as % of income | H14: Perpetual 5-year average per year incl. implementation (PHP) | I14: Perpetual average as % of income | J14: Within IT budget?
A15: =Inputs!A28 | B15: =Inputs!J28 | C15: =Inputs!M28 | D15: =C15*IT_Low | E15: =C15*IT_High | F15: ='Subscription Model'!C8 | G15: =F15/C15 | H15: ='Perpetual Model'!H9/5 | I15: =H15/C15 | J15: =IF(MAX(G15,I15)<=IT_High,"Yes","Review")
A16: =Inputs!A29 | B16: =Inputs!J29 | C16: =Inputs!M29 | D16: =C16*IT_Low | E16: =C16*IT_High | F16: ='Subscription Model'!C16 | G16: =F16/C16 | H16: ='Perpetual Model'!H17/5 | I16: =H16/C16 | J16: =IF(MAX(G16,I16)<=IT_High,"Yes","Review")
A17: =Inputs!A30 | B17: =Inputs!J30 | C17: =Inputs!M30 | D17: =C17*IT_Low | E17: =C17*IT_High | F17: ='Subscription Model'!C24 | G17: =F17/C17 | H17: ='Perpetual Model'!H25/5 | I17: =H17/C17 | J17: =IF(MAX(G17,I17)<=IT_High,"Yes","Review")
A18: =Inputs!A31 | B18: =Inputs!J31 | C18: =Inputs!M31 | D18: =C18*IT_Low | E18: =C18*IT_High | F18: ='Subscription Model'!C32 | G18: =F18/C18 | H18: ='Perpetual Model'!H33/5 | I18: =H18/C18 | J18: =IF(MAX(G18,I18)<=IT_High,"Yes","Review")
A20: Note: the IT budget also pays for hardware, network, office systems and staff. BrokerVerse should take well under the full budget; the check shows the software cost against the benchmark band, not a recommendation of spend.

Sheet Perpetual Model
A1: Model A: perpetual licence with AMC
A2: Implementation and licence in Year 1; AMC at 22% of the licence fee from the AMC start year, +5% a year. PHP, exclusive of VAT unless stated.
A4: Tier / item | B4: Basis | C4: Year 1 | D4: Year 2 | E4: Year 3 | F4: Year 4 | G4: Year 5 | H4: 5-year total (PHP) | I4: 5-year total (USD)
A5: =Inputs!A28&" (reference)" | B5: Users / lines of business | C5: =Inputs!J28 | D5: =Inputs!K28
A6: Implementation fee | B6: Base + extra lines x blended rate | C6: =ROUND((INDEX(Inputs!$G$28:$G$31,MATCH($C$5,Inputs!$B$28:$B$31,1))+MAX(0,$D$5-INDEX(Inputs!$H$28:$H$31,MATCH($C$5,Inputs!$B$28:$B$31,1)))*Days_per_LOB)*Blended/Round_To,0)*Round_To | D6: 0 | E6: 0 | F6: 0 | G6: 0 | H6: =SUM(C6:G6) | I6: =H6/FX
A7: Perpetual licence fee | B7: Graduated user slabs | C7: =MAX(0,MIN($C$5,Inputs!$C$28)-Inputs!$B$28+1)*Inputs!$D$28+MAX(0,MIN($C$5,Inputs!$C$29)-Inputs!$B$29+1)*Inputs!$D$29+MAX(0,MIN($C$5,Inputs!$C$30)-Inputs!$B$30+1)*Inputs!$D$30+MAX(0,MIN($C$5,Inputs!$C$31)-Inputs!$B$31+1)*Inputs!$D$31 | D7: 0 | E7: 0 | F7: 0 | G7: 0 | H7: =SUM(C7:G7) | I7: =H7/FX
A8: AMC | B8: 22% of licence, +5% a year | C8: =IF(1>=AMC_Start,$C$7*AMC_Rate*(1+Esc)^(1-AMC_Start),0) | D8: =IF(2>=AMC_Start,$C$7*AMC_Rate*(1+Esc)^(2-AMC_Start),0) | E8: =IF(3>=AMC_Start,$C$7*AMC_Rate*(1+Esc)^(3-AMC_Start),0) | F8: =IF(4>=AMC_Start,$C$7*AMC_Rate*(1+Esc)^(4-AMC_Start),0) | G8: =IF(5>=AMC_Start,$C$7*AMC_Rate*(1+Esc)^(5-AMC_Start),0) | H8: =SUM(C8:G8) | I8: =H8/FX
A9: Total excl. VAT | C9: =SUM(C6:C8) | D9: =SUM(D6:D8) | E9: =SUM(E6:E8) | F9: =SUM(F6:F8) | G9: =SUM(G6:G8) | H9: =SUM(H6:H8) | I9: =H9/FX
A10: VAT | B10: =TEXT(VAT,"0%") | C10: =C9*VAT | D10: =D9*VAT | E10: =E9*VAT | F10: =F9*VAT | G10: =G9*VAT | H10: =H9*VAT | I10: =H10/FX
A11: Total incl. VAT | C11: =C9+C10 | D11: =D9+D10 | E11: =E9+E10 | F11: =F9+F10 | G11: =G9+G10 | H11: =H9+H10 | I11: =H11/FX
A13: =Inputs!A29&" (reference)" | B13: Users / lines of business | C13: =Inputs!J29 | D13: =Inputs!K29
A14: Implementation fee | B14: Base + extra lines x blended rate | C14: =ROUND((INDEX(Inputs!$G$28:$G$31,MATCH($C$13,Inputs!$B$28:$B$31,1))+MAX(0,$D$13-INDEX(Inputs!$H$28:$H$31,MATCH($C$13,Inputs!$B$28:$B$31,1)))*Days_per_LOB)*Blended/Round_To,0)*Round_To | D14: 0 | E14: 0 | F14: 0 | G14: 0 | H14: =SUM(C14:G14) | I14: =H14/FX
A15: Perpetual licence fee | B15: Graduated user slabs | C15: =MAX(0,MIN($C$13,Inputs!$C$28)-Inputs!$B$28+1)*Inputs!$D$28+MAX(0,MIN($C$13,Inputs!$C$29)-Inputs!$B$29+1)*Inputs!$D$29+MAX(0,MIN($C$13,Inputs!$C$30)-Inputs!$B$30+1)*Inputs!$D$30+MAX(0,MIN($C$13,Inputs!$C$31)-Inputs!$B$31+1)*Inputs!$D$31 | D15: 0 | E15: 0 | F15: 0 | G15: 0 | H15: =SUM(C15:G15) | I15: =H15/FX
A16: AMC | B16: 22% of licence, +5% a year | C16: =IF(1>=AMC_Start,$C$15*AMC_Rate*(1+Esc)^(1-AMC_Start),0) | D16: =IF(2>=AMC_Start,$C$15*AMC_Rate*(1+Esc)^(2-AMC_Start),0) | E16: =IF(3>=AMC_Start,$C$15*AMC_Rate*(1+Esc)^(3-AMC_Start),0) | F16: =IF(4>=AMC_Start,$C$15*AMC_Rate*(1+Esc)^(4-AMC_Start),0) | G16: =IF(5>=AMC_Start,$C$15*AMC_Rate*(1+Esc)^(5-AMC_Start),0) | H16: =SUM(C16:G16) | I16: =H16/FX
A17: Total excl. VAT | C17: =SUM(C14:C16) | D17: =SUM(D14:D16) | E17: =SUM(E14:E16) | F17: =SUM(F14:F16) | G17: =SUM(G14:G16) | H17: =SUM(H14:H16) | I17: =H17/FX
A18: VAT | B18: =TEXT(VAT,"0%") | C18: =C17*VAT | D18: =D17*VAT | E18: =E17*VAT | F18: =F17*VAT | G18: =G17*VAT | H18: =H17*VAT | I18: =H18/FX
A19: Total incl. VAT | C19: =C17+C18 | D19: =D17+D18 | E19: =E17+E18 | F19: =F17+F18 | G19: =G17+G18 | H19: =H17+H18 | I19: =H19/FX
A21: =Inputs!A30&" (reference)" | B21: Users / lines of business | C21: =Inputs!J30 | D21: =Inputs!K30
A22: Implementation fee | B22: Base + extra lines x blended rate | C22: =ROUND((INDEX(Inputs!$G$28:$G$31,MATCH($C$21,Inputs!$B$28:$B$31,1))+MAX(0,$D$21-INDEX(Inputs!$H$28:$H$31,MATCH($C$21,Inputs!$B$28:$B$31,1)))*Days_per_LOB)*Blended/Round_To,0)*Round_To | D22: 0 | E22: 0 | F22: 0 | G22: 0 | H22: =SUM(C22:G22) | I22: =H22/FX
A23: Perpetual licence fee | B23: Graduated user slabs | C23: =MAX(0,MIN($C$21,Inputs!$C$28)-Inputs!$B$28+1)*Inputs!$D$28+MAX(0,MIN($C$21,Inputs!$C$29)-Inputs!$B$29+1)*Inputs!$D$29+MAX(0,MIN($C$21,Inputs!$C$30)-Inputs!$B$30+1)*Inputs!$D$30+MAX(0,MIN($C$21,Inputs!$C$31)-Inputs!$B$31+1)*Inputs!$D$31 | D23: 0 | E23: 0 | F23: 0 | G23: 0 | H23: =SUM(C23:G23) | I23: =H23/FX
A24: AMC | B24: 22% of licence, +5% a year | C24: =IF(1>=AMC_Start,$C$23*AMC_Rate*(1+Esc)^(1-AMC_Start),0) | D24: =IF(2>=AMC_Start,$C$23*AMC_Rate*(1+Esc)^(2-AMC_Start),0) | E24: =IF(3>=AMC_Start,$C$23*AMC_Rate*(1+Esc)^(3-AMC_Start),0) | F24: =IF(4>=AMC_Start,$C$23*AMC_Rate*(1+Esc)^(4-AMC_Start),0) | G24: =IF(5>=AMC_Start,$C$23*AMC_Rate*(1+Esc)^(5-AMC_Start),0) | H24: =SUM(C24:G24) | I24: =H24/FX
A25: Total excl. VAT | C25: =SUM(C22:C24) | D25: =SUM(D22:D24) | E25: =SUM(E22:E24) | F25: =SUM(F22:F24) | G25: =SUM(G22:G24) | H25: =SUM(H22:H24) | I25: =H25/FX
A26: VAT | B26: =TEXT(VAT,"0%") | C26: =C25*VAT | D26: =D25*VAT | E26: =E25*VAT | F26: =F25*VAT | G26: =G25*VAT | H26: =H25*VAT | I26: =H26/FX
A27: Total incl. VAT | C27: =C25+C26 | D27: =D25+D26 | E27: =E25+E26 | F27: =F25+F26 | G27: =G25+G26 | H27: =H25+H26 | I27: =H27/FX
A29: =Inputs!A31&" (reference)" | B29: Users / lines of business | C29: =Inputs!J31 | D29: =Inputs!K31
A30: Implementation fee | B30: Base + extra lines x blended rate | C30: =ROUND((INDEX(Inputs!$G$28:$G$31,MATCH($C$29,Inputs!$B$28:$B$31,1))+MAX(0,$D$29-INDEX(Inputs!$H$28:$H$31,MATCH($C$29,Inputs!$B$28:$B$31,1)))*Days_per_LOB)*Blended/Round_To,0)*Round_To | D30: 0 | E30: 0 | F30: 0 | G30: 0 | H30: =SUM(C30:G30) | I30: =H30/FX
A31: Perpetual licence fee | B31: Graduated user slabs | C31: =MAX(0,MIN($C$29,Inputs!$C$28)-Inputs!$B$28+1)*Inputs!$D$28+MAX(0,MIN($C$29,Inputs!$C$29)-Inputs!$B$29+1)*Inputs!$D$29+MAX(0,MIN($C$29,Inputs!$C$30)-Inputs!$B$30+1)*Inputs!$D$30+MAX(0,MIN($C$29,Inputs!$C$31)-Inputs!$B$31+1)*Inputs!$D$31 | D31: 0 | E31: 0 | F31: 0 | G31: 0 | H31: =SUM(C31:G31) | I31: =H31/FX
A32: AMC | B32: 22% of licence, +5% a year | C32: =IF(1>=AMC_Start,$C$31*AMC_Rate*(1+Esc)^(1-AMC_Start),0) | D32: =IF(2>=AMC_Start,$C$31*AMC_Rate*(1+Esc)^(2-AMC_Start),0) | E32: =IF(3>=AMC_Start,$C$31*AMC_Rate*(1+Esc)^(3-AMC_Start),0) | F32: =IF(4>=AMC_Start,$C$31*AMC_Rate*(1+Esc)^(4-AMC_Start),0) | G32: =IF(5>=AMC_Start,$C$31*AMC_Rate*(1+Esc)^(5-AMC_Start),0) | H32: =SUM(C32:G32) | I32: =H32/FX
A33: Total excl. VAT | C33: =SUM(C30:C32) | D33: =SUM(D30:D32) | E33: =SUM(E30:E32) | F33: =SUM(F30:F32) | G33: =SUM(G30:G32) | H33: =SUM(H30:H32) | I33: =H33/FX
A34: VAT | B34: =TEXT(VAT,"0%") | C34: =C33*VAT | D34: =D33*VAT | E34: =E33*VAT | F34: =F33*VAT | G34: =G33*VAT | H34: =H33*VAT | I34: =H34/FX
A35: Total incl. VAT | C35: =C33+C34 | D35: =D33+D34 | E35: =E33+E34 | F35: =F33+F34 | G35: =G33+G34 | H35: =H33+H34 | I35: =H35/FX
A38: Calculator for a chosen user count (change users and lines of business in Inputs, Calculator section)
A39: Named users | C39: =Calc_Users
A40: Lines of business | C40: =Calc_LOBs
A41: Tier | C41: =INDEX(Inputs!$A$28:$A$31,MATCH(C39,Inputs!$B$28:$B$31,1))
A43: Slab | B43: Users from - to | C43: Users in slab | D43: Price per user (PHP) | E43: Amount (PHP)
A44: =Inputs!A28 | B44: =Inputs!B28&" - "&IF(Inputs!C28>=100000,"above",Inputs!C28) | C44: =MAX(0,MIN($C$39,Inputs!C28)-Inputs!B28+1) | D44: =Inputs!D28 | E44: =C44*D44
A45: =Inputs!A29 | B45: =Inputs!B29&" - "&IF(Inputs!C29>=100000,"above",Inputs!C29) | C45: =MAX(0,MIN($C$39,Inputs!C29)-Inputs!B29+1) | D45: =Inputs!D29 | E45: =C45*D45
A46: =Inputs!A30 | B46: =Inputs!B30&" - "&IF(Inputs!C30>=100000,"above",Inputs!C30) | C46: =MAX(0,MIN($C$39,Inputs!C30)-Inputs!B30+1) | D46: =Inputs!D30 | E46: =C46*D46
A47: =Inputs!A31 | B47: =Inputs!B31&" - "&IF(Inputs!C31>=100000,"above",Inputs!C31) | C47: =MAX(0,MIN($C$39,Inputs!C31)-Inputs!B31+1) | D47: =Inputs!D31 | E47: =C47*D47
A48: Perpetual licence fee | E48: =SUM(E44:E47)
A49: Effective licence price per user | E49: =E48/$C$39
A50: Implementation fee | B50: Base man-days for tier + extra lines | E50: =ROUND((INDEX(Inputs!$G$28:$G$31,MATCH($C$39,Inputs!$B$28:$B$31,1))+MAX(0,$C$40-INDEX(Inputs!$H$28:$H$31,MATCH($C$39,Inputs!$B$28:$B$31,1)))*Days_per_LOB)*Blended/Round_To,0)*Round_To
A51: Implementation man-days (before rounding) | E51: =INDEX(Inputs!$G$28:$G$31,MATCH($C$39,Inputs!$B$28:$B$31,1))+MAX(0,$C$40-INDEX(Inputs!$H$28:$H$31,MATCH($C$39,Inputs!$B$28:$B$31,1)))*Days_per_LOB
A53: Item | B53: Basis | C53: Year 1 | D53: Year 2 | E53: Year 3 | F53: Year 4 | G53: Year 5 | H53: 5-year total (PHP) | I53: 5-year total (USD)
A54: Implementation fee | C54: =$E$50 | D54: 0 | E54: 0 | F54: 0 | G54: 0 | H54: =SUM(C54:G54) | I54: =H54/FX
A55: Perpetual licence fee | C55: =$E$48 | D55: 0 | E55: 0 | F55: 0 | G55: 0 | H55: =SUM(C55:G55) | I55: =H55/FX
A56: AMC | C56: =IF(1>=AMC_Start,$E$48*AMC_Rate*(1+Esc)^(1-AMC_Start),0) | D56: =IF(2>=AMC_Start,$E$48*AMC_Rate*(1+Esc)^(2-AMC_Start),0) | E56: =IF(3>=AMC_Start,$E$48*AMC_Rate*(1+Esc)^(3-AMC_Start),0) | F56: =IF(4>=AMC_Start,$E$48*AMC_Rate*(1+Esc)^(4-AMC_Start),0) | G56: =IF(5>=AMC_Start,$E$48*AMC_Rate*(1+Esc)^(5-AMC_Start),0) | H56: =SUM(C56:G56) | I56: =H56/FX
A57: Total excl. VAT | C57: =SUM(C54:C56) | D57: =SUM(D54:D56) | E57: =SUM(E54:E56) | F57: =SUM(F54:F56) | G57: =SUM(G54:G56) | H57: =SUM(H54:H56) | I57: =H57/FX
A58: VAT | C58: =C57*VAT | D58: =D57*VAT | E58: =E57*VAT | F58: =F57*VAT | G58: =G57*VAT | H58: =H57*VAT | I58: =H58/FX
A59: Total incl. VAT | C59: =C57+C58 | D59: =D57+D58 | E59: =E57+E58 | F59: =F57+F58 | G59: =G57+G58 | H59: =H57+H58 | I59: =H59/FX

Sheet Subscription Model
A1: Model B: subscription (SaaS, as-is version)
A2: Monthly per-user price by graduated slab, billed monthly in advance, +5% at each anniversary. Hosting quoted separately. PHP, exclusive of VAT unless stated.
A4: Tier / item | B4: Basis | C4: Year 1 | D4: Year 2 | E4: Year 3 | F4: Year 4 | G4: Year 5 | H4: 5-year total (PHP) | I4: 5-year total (USD)
A5: =Inputs!A28&" (reference)" | B5: Users / billable users | C5: =Inputs!J28 | D5: =MAX($C$5,INDEX(Inputs!$F$28:$F$31,MATCH($C$5,Inputs!$B$28:$B$31,1)))
A6: Monthly fee (Year 1 rates) | B6: Graduated slabs on billable users | C6: =MAX(0,MIN($D$5,Inputs!$C$28)-Inputs!$B$28+1)*Inputs!$E$28+MAX(0,MIN($D$5,Inputs!$C$29)-Inputs!$B$29+1)*Inputs!$E$29+MAX(0,MIN($D$5,Inputs!$C$30)-Inputs!$B$30+1)*Inputs!$E$30+MAX(0,MIN($D$5,Inputs!$C$31)-Inputs!$B$31+1)*Inputs!$E$31 | D6: per user: | E6: =C6/$D$5
A7: Onboarding fee | B7: Implementation x onboarding % | C7: ='Perpetual Model'!C6*Onboard_Pct | D7: 0 | E7: 0 | F7: 0 | G7: 0 | H7: =SUM(C7:G7) | I7: =H7/FX
A8: Subscription fees (12 months) | B8: Monthly fee x 12, +5% a year | C8: =$C$6*12*(1+Esc)^(1-1) | D8: =$C$6*12*(1+Esc)^(2-1) | E8: =$C$6*12*(1+Esc)^(3-1) | F8: =$C$6*12*(1+Esc)^(4-1) | G8: =$C$6*12*(1+Esc)^(5-1) | H8: =SUM(C8:G8) | I8: =H8/FX
A9: Total excl. VAT | C9: =C7+C8 | D9: =D7+D8 | E9: =E7+E8 | F9: =F7+F8 | G9: =G7+G8 | H9: =H7+H8 | I9: =H9/FX
A10: VAT | C10: =C9*VAT | D10: =D9*VAT | E10: =E9*VAT | F10: =F9*VAT | G10: =G9*VAT | H10: =H9*VAT | I10: =H10/FX
A11: Total incl. VAT | C11: =C9+C10 | D11: =D9+D10 | E11: =E9+E10 | F11: =F9+F10 | G11: =G9+G10 | H11: =H9+H10 | I11: =H11/FX
A13: =Inputs!A29&" (reference)" | B13: Users / billable users | C13: =Inputs!J29 | D13: =MAX($C$13,INDEX(Inputs!$F$28:$F$31,MATCH($C$13,Inputs!$B$28:$B$31,1)))
A14: Monthly fee (Year 1 rates) | B14: Graduated slabs on billable users | C14: =MAX(0,MIN($D$13,Inputs!$C$28)-Inputs!$B$28+1)*Inputs!$E$28+MAX(0,MIN($D$13,Inputs!$C$29)-Inputs!$B$29+1)*Inputs!$E$29+MAX(0,MIN($D$13,Inputs!$C$30)-Inputs!$B$30+1)*Inputs!$E$30+MAX(0,MIN($D$13,Inputs!$C$31)-Inputs!$B$31+1)*Inputs!$E$31 | D14: per user: | E14: =C14/$D$13
A15: Onboarding fee | B15: Implementation x onboarding % | C15: ='Perpetual Model'!C14*Onboard_Pct | D15: 0 | E15: 0 | F15: 0 | G15: 0 | H15: =SUM(C15:G15) | I15: =H15/FX
A16: Subscription fees (12 months) | B16: Monthly fee x 12, +5% a year | C16: =$C$14*12*(1+Esc)^(1-1) | D16: =$C$14*12*(1+Esc)^(2-1) | E16: =$C$14*12*(1+Esc)^(3-1) | F16: =$C$14*12*(1+Esc)^(4-1) | G16: =$C$14*12*(1+Esc)^(5-1) | H16: =SUM(C16:G16) | I16: =H16/FX
A17: Total excl. VAT | C17: =C15+C16 | D17: =D15+D16 | E17: =E15+E16 | F17: =F15+F16 | G17: =G15+G16 | H17: =H15+H16 | I17: =H17/FX
A18: VAT | C18: =C17*VAT | D18: =D17*VAT | E18: =E17*VAT | F18: =F17*VAT | G18: =G17*VAT | H18: =H17*VAT | I18: =H18/FX
A19: Total incl. VAT | C19: =C17+C18 | D19: =D17+D18 | E19: =E17+E18 | F19: =F17+F18 | G19: =G17+G18 | H19: =H17+H18 | I19: =H19/FX
A21: =Inputs!A30&" (reference)" | B21: Users / billable users | C21: =Inputs!J30 | D21: =MAX($C$21,INDEX(Inputs!$F$28:$F$31,MATCH($C$21,Inputs!$B$28:$B$31,1)))
A22: Monthly fee (Year 1 rates) | B22: Graduated slabs on billable users | C22: =MAX(0,MIN($D$21,Inputs!$C$28)-Inputs!$B$28+1)*Inputs!$E$28+MAX(0,MIN($D$21,Inputs!$C$29)-Inputs!$B$29+1)*Inputs!$E$29+MAX(0,MIN($D$21,Inputs!$C$30)-Inputs!$B$30+1)*Inputs!$E$30+MAX(0,MIN($D$21,Inputs!$C$31)-Inputs!$B$31+1)*Inputs!$E$31 | D22: per user: | E22: =C22/$D$21
A23: Onboarding fee | B23: Implementation x onboarding % | C23: ='Perpetual Model'!C22*Onboard_Pct | D23: 0 | E23: 0 | F23: 0 | G23: 0 | H23: =SUM(C23:G23) | I23: =H23/FX
A24: Subscription fees (12 months) | B24: Monthly fee x 12, +5% a year | C24: =$C$22*12*(1+Esc)^(1-1) | D24: =$C$22*12*(1+Esc)^(2-1) | E24: =$C$22*12*(1+Esc)^(3-1) | F24: =$C$22*12*(1+Esc)^(4-1) | G24: =$C$22*12*(1+Esc)^(5-1) | H24: =SUM(C24:G24) | I24: =H24/FX
A25: Total excl. VAT | C25: =C23+C24 | D25: =D23+D24 | E25: =E23+E24 | F25: =F23+F24 | G25: =G23+G24 | H25: =H23+H24 | I25: =H25/FX
A26: VAT | C26: =C25*VAT | D26: =D25*VAT | E26: =E25*VAT | F26: =F25*VAT | G26: =G25*VAT | H26: =H25*VAT | I26: =H26/FX
A27: Total incl. VAT | C27: =C25+C26 | D27: =D25+D26 | E27: =E25+E26 | F27: =F25+F26 | G27: =G25+G26 | H27: =H25+H26 | I27: =H27/FX
A29: =Inputs!A31&" (reference)" | B29: Users / billable users | C29: =Inputs!J31 | D29: =MAX($C$29,INDEX(Inputs!$F$28:$F$31,MATCH($C$29,Inputs!$B$28:$B$31,1)))
A30: Monthly fee (Year 1 rates) | B30: Graduated slabs on billable users | C30: =MAX(0,MIN($D$29,Inputs!$C$28)-Inputs!$B$28+1)*Inputs!$E$28+MAX(0,MIN($D$29,Inputs!$C$29)-Inputs!$B$29+1)*Inputs!$E$29+MAX(0,MIN($D$29,Inputs!$C$30)-Inputs!$B$30+1)*Inputs!$E$30+MAX(0,MIN($D$29,Inputs!$C$31)-Inputs!$B$31+1)*Inputs!$E$31 | D30: per user: | E30: =C30/$D$29
A31: Onboarding fee | B31: Implementation x onboarding % | C31: ='Perpetual Model'!C30*Onboard_Pct | D31: 0 | E31: 0 | F31: 0 | G31: 0 | H31: =SUM(C31:G31) | I31: =H31/FX
A32: Subscription fees (12 months) | B32: Monthly fee x 12, +5% a year | C32: =$C$30*12*(1+Esc)^(1-1) | D32: =$C$30*12*(1+Esc)^(2-1) | E32: =$C$30*12*(1+Esc)^(3-1) | F32: =$C$30*12*(1+Esc)^(4-1) | G32: =$C$30*12*(1+Esc)^(5-1) | H32: =SUM(C32:G32) | I32: =H32/FX
A33: Total excl. VAT | C33: =C31+C32 | D33: =D31+D32 | E33: =E31+E32 | F33: =F31+F32 | G33: =G31+G32 | H33: =H31+H32 | I33: =H33/FX
A34: VAT | C34: =C33*VAT | D34: =D33*VAT | E34: =E33*VAT | F34: =F33*VAT | G34: =G33*VAT | H34: =H33*VAT | I34: =H34/FX
A35: Total incl. VAT | C35: =C33+C34 | D35: =D33+D34 | E35: =E33+E34 | F35: =F33+F34 | G35: =G33+G34 | H35: =H33+H34 | I35: =H35/FX
A38: Break-even against the perpetual model (cumulative cost including implementation or onboarding, excl. VAT)
A39: Tier / item | C39: Year 1 | D39: Year 2 | E39: Year 3 | F39: Year 4 | G39: Year 5 | H39: Break-even | I39: Saving of perpetual over 5 years
A40: =Inputs!A28
A41: Perpetual, cumulative | C41: =SUM('Perpetual Model'!$C$9:C9) | D41: =SUM('Perpetual Model'!$C$9:D9) | E41: =SUM('Perpetual Model'!$C$9:E9) | F41: =SUM('Perpetual Model'!$C$9:F9) | G41: =SUM('Perpetual Model'!$C$9:G9) | H41: =IF(MIN(C43:G43)=99,"Beyond Year 5","Year "&MIN(C43:G43)) | I41: =G42-G41
A42: Subscription, cumulative | C42: =SUM($C$9:C9) | D42: =SUM($C$9:D9) | E42: =SUM($C$9:E9) | F42: =SUM($C$9:F9) | G42: =SUM($C$9:G9)
A43: Helper: year subscription reaches perpetual | C43: =IF(C42>=C41,1,99) | D43: =IF(D42>=D41,2,99) | E43: =IF(E42>=E41,3,99) | F43: =IF(F42>=F41,4,99) | G43: =IF(G42>=G41,5,99)
A45: =Inputs!A29
A46: Perpetual, cumulative | C46: =SUM('Perpetual Model'!$C$17:C17) | D46: =SUM('Perpetual Model'!$C$17:D17) | E46: =SUM('Perpetual Model'!$C$17:E17) | F46: =SUM('Perpetual Model'!$C$17:F17) | G46: =SUM('Perpetual Model'!$C$17:G17) | H46: =IF(MIN(C48:G48)=99,"Beyond Year 5","Year "&MIN(C48:G48)) | I46: =G47-G46
A47: Subscription, cumulative | C47: =SUM($C$17:C17) | D47: =SUM($C$17:D17) | E47: =SUM($C$17:E17) | F47: =SUM($C$17:F17) | G47: =SUM($C$17:G17)
A48: Helper: year subscription reaches perpetual | C48: =IF(C47>=C46,1,99) | D48: =IF(D47>=D46,2,99) | E48: =IF(E47>=E46,3,99) | F48: =IF(F47>=F46,4,99) | G48: =IF(G47>=G46,5,99)
A50: =Inputs!A30
A51: Perpetual, cumulative | C51: =SUM('Perpetual Model'!$C$25:C25) | D51: =SUM('Perpetual Model'!$C$25:D25) | E51: =SUM('Perpetual Model'!$C$25:E25) | F51: =SUM('Perpetual Model'!$C$25:F25) | G51: =SUM('Perpetual Model'!$C$25:G25) | H51: =IF(MIN(C53:G53)=99,"Beyond Year 5","Year "&MIN(C53:G53)) | I51: =G52-G51
A52: Subscription, cumulative | C52: =SUM($C$25:C25) | D52: =SUM($C$25:D25) | E52: =SUM($C$25:E25) | F52: =SUM($C$25:F25) | G52: =SUM($C$25:G25)
A53: Helper: year subscription reaches perpetual | C53: =IF(C52>=C51,1,99) | D53: =IF(D52>=D51,2,99) | E53: =IF(E52>=E51,3,99) | F53: =IF(F52>=F51,4,99) | G53: =IF(G52>=G51,5,99)
A55: =Inputs!A31
A56: Perpetual, cumulative | C56: =SUM('Perpetual Model'!$C$33:C33) | D56: =SUM('Perpetual Model'!$C$33:D33) | E56: =SUM('Perpetual Model'!$C$33:E33) | F56: =SUM('Perpetual Model'!$C$33:F33) | G56: =SUM('Perpetual Model'!$C$33:G33) | H56: =IF(MIN(C58:G58)=99,"Beyond Year 5","Year "&MIN(C58:G58)) | I56: =G57-G56
A57: Subscription, cumulative | C57: =SUM($C$33:C33) | D57: =SUM($C$33:D33) | E57: =SUM($C$33:E33) | F57: =SUM($C$33:F33) | G57: =SUM($C$33:G33)
A58: Helper: year subscription reaches perpetual | C58: =IF(C57>=C56,1,99) | D58: =IF(D57>=D56,2,99) | E58: =IF(E57>=E56,3,99) | F58: =IF(F57>=F56,4,99) | G58: =IF(G57>=G56,5,99)
A61: Calculator for a chosen user count (Inputs, Calculator section)
A62: Named users | C62: =Calc_Users
A63: Tier | C63: =INDEX(Inputs!$A$28:$A$31,MATCH(C62,Inputs!$B$28:$B$31,1))
A64: Billable users (minimum for tier applies) | C64: =MAX(C62,INDEX(Inputs!$F$28:$F$31,MATCH(C62,Inputs!$B$28:$B$31,1)))
A66: Slab | B66: Users from - to | C66: Users in slab | D66: Price per user per month (PHP) | E66: Monthly amount (PHP)
A67: =Inputs!A28 | B67: =Inputs!B28&" - "&IF(Inputs!C28>=100000,"above",Inputs!C28) | C67: =MAX(0,MIN($C$64,Inputs!C28)-Inputs!B28+1) | D67: =Inputs!E28 | E67: =C67*D67
A68: =Inputs!A29 | B68: =Inputs!B29&" - "&IF(Inputs!C29>=100000,"above",Inputs!C29) | C68: =MAX(0,MIN($C$64,Inputs!C29)-Inputs!B29+1) | D68: =Inputs!E29 | E68: =C68*D68
A69: =Inputs!A30 | B69: =Inputs!B30&" - "&IF(Inputs!C30>=100000,"above",Inputs!C30) | C69: =MAX(0,MIN($C$64,Inputs!C30)-Inputs!B30+1) | D69: =Inputs!E30 | E69: =C69*D69
A70: =Inputs!A31 | B70: =Inputs!B31&" - "&IF(Inputs!C31>=100000,"above",Inputs!C31) | C70: =MAX(0,MIN($C$64,Inputs!C31)-Inputs!B31+1) | D70: =Inputs!E31 | E70: =C70*D70
A71: Monthly subscription, Year 1 | E71: =SUM(E67:E70)
A72: Effective price per user per month | E72: =E71/$C$64
A73: Onboarding fee | E73: ='Perpetual Model'!$E$50*Onboard_Pct
A75: Item | B75: Basis | C75: Year 1 | D75: Year 2 | E75: Year 3 | F75: Year 4 | G75: Year 5 | H75: 5-year total (PHP) | I75: 5-year total (USD)
A76: Onboarding fee | C76: =$E$73 | D76: 0 | E76: 0 | F76: 0 | G76: 0 | H76: =SUM(C76:G76) | I76: =H76/FX
A77: Subscription fees (12 months) | C77: =$E$71*12*(1+Esc)^(1-1) | D77: =$E$71*12*(1+Esc)^(2-1) | E77: =$E$71*12*(1+Esc)^(3-1) | F77: =$E$71*12*(1+Esc)^(4-1) | G77: =$E$71*12*(1+Esc)^(5-1) | H77: =SUM(C77:G77) | I77: =H77/FX
A78: Total excl. VAT | C78: =C76+C77 | D78: =D76+D77 | E78: =E76+E77 | F78: =F76+F77 | G78: =G76+G77 | H78: =H76+H77 | I78: =H78/FX
A79: VAT | C79: =C78*VAT | D79: =D78*VAT | E79: =E78*VAT | F79: =F78*VAT | G79: =G78*VAT | H79: =H78*VAT | I79: =H79/FX
A80: Total incl. VAT | C80: =C78+C79 | D80: =D78+D79 | E80: =E78+E79 | F80: =F78+F79 | G80: =G78+G79 | H80: =H78+H79 | I80: =H80/FX
A82: Perpetual, cumulative (calculator) | C82: =SUM('Perpetual Model'!$C$57:C57) | D82: =SUM('Perpetual Model'!$C$57:D57) | E82: =SUM('Perpetual Model'!$C$57:E57) | F82: =SUM('Perpetual Model'!$C$57:F57) | G82: =SUM('Perpetual Model'!$C$57:G57) | H82: =IF(MIN(C84:G84)=99,"Beyond Year 5","Break-even Year "&MIN(C84:G84))
A83: Subscription, cumulative (calculator) | C83: =SUM($C$78:C78) | D83: =SUM($C$78:D78) | E83: =SUM($C$78:E78) | F83: =SUM($C$78:F78) | G83: =SUM($C$78:G78)
A84: Helper | C84: =IF(C83>=C82,1,99) | D84: =IF(D83>=D82,2,99) | E84: =IF(E83>=E82,3,99) | F84: =IF(F83>=F82,4,99) | G84: =IF(G83>=G82,5,99)

Sheet Infrastructure
A1: Infrastructure (optional and separate): hosting per environment set
A2: Price per month by provider, tier and environment, with margin. Standing environments run all the time; Pre-Prod is temporary and billed per month of use. The customer may host BrokerVerse itself at no fee.
A4: Provider | B4: Tier | C4: Environment set | D4: Dev per month (PHP) | E4: SIT per month (PHP) | F4: UAT per month (PHP) | G4: Production per month (PHP) | H4: Standing environments per month (PHP) | I4: Pre-Prod per month of use (PHP) | J4: Hosting Year 1 (PHP, incl. Pre-Prod at go-live) | K4: Hosting each later year (PHP, incl. Pre-Prod per major release) | L4: Standing per month (USD) | M4: Notes
A5: AWS | B5: =Inputs!A28 | C5: Dev, UAT, Production + Pre-Prod when used | D5: =ROUND(Inputs!B100*1*FX*(1+Infra_Margin),-3) | E5: =ROUND(Inputs!C100*1*FX*(1+Infra_Margin),-3) | F5: =ROUND(Inputs!D100*1*FX*(1+Infra_Margin),-3) | G5: =ROUND(Inputs!E100*1*FX*(1+Infra_Margin),-3) | H5: =SUM(D5:G5) | I5: =ROUND(Inputs!G100*1*FX*(1+Infra_Margin),-3) | J5: =H5*12+I5*PreProd_GoLive_Months | K5: =H5*12+I5*PreProd_Rel_Months*Major_Rel_Year | L5: =H5/FX | M5: Singapore region (ap-southeast-1); a Manila Local Zone exists for latency-sensitive parts (S22).
A6: AWS | B6: =Inputs!A29 | C6: Dev, UAT, Production + Pre-Prod when used | D6: =ROUND(Inputs!B101*1*FX*(1+Infra_Margin),-3) | E6: =ROUND(Inputs!C101*1*FX*(1+Infra_Margin),-3) | F6: =ROUND(Inputs!D101*1*FX*(1+Infra_Margin),-3) | G6: =ROUND(Inputs!E101*1*FX*(1+Infra_Margin),-3) | H6: =SUM(D6:G6) | I6: =ROUND(Inputs!G101*1*FX*(1+Infra_Margin),-3) | J6: =H6*12+I6*PreProd_GoLive_Months | K6: =H6*12+I6*PreProd_Rel_Months*Major_Rel_Year | L6: =H6/FX
A7: AWS | B7: =Inputs!A30 | C7: Dev, SIT, UAT, Production (HA) + Pre-Prod when used | D7: =ROUND(Inputs!B102*1*FX*(1+Infra_Margin),-3) | E7: =ROUND(Inputs!C102*1*FX*(1+Infra_Margin),-3) | F7: =ROUND(Inputs!D102*1*FX*(1+Infra_Margin),-3) | G7: =ROUND(Inputs!E102*1*FX*(1+Infra_Margin),-3) | H7: =SUM(D7:G7) | I7: =ROUND(Inputs!G102*1*FX*(1+Infra_Margin),-3) | J7: =H7*12+I7*PreProd_GoLive_Months | K7: =H7*12+I7*PreProd_Rel_Months*Major_Rel_Year | L7: =H7/FX
A8: AWS | B8: =Inputs!A31 | C8: Dev, SIT, UAT, Production (HA, DR copy) + Pre-Prod when used | D8: =ROUND(Inputs!B103*1*FX*(1+Infra_Margin),-3) | E8: =ROUND(Inputs!C103*1*FX*(1+Infra_Margin),-3) | F8: =ROUND(Inputs!D103*1*FX*(1+Infra_Margin),-3) | G8: =ROUND(Inputs!E103*1*FX*(1+Infra_Margin),-3) | H8: =SUM(D8:G8) | I8: =ROUND(Inputs!G103*1*FX*(1+Infra_Margin),-3) | J8: =H8*12+I8*PreProd_GoLive_Months | K8: =H8*12+I8*PreProd_Rel_Months*Major_Rel_Year | L8: =H8/FX
A9: Azure | B9: =Inputs!A28 | C9: Dev, UAT, Production + Pre-Prod when used | D9: =ROUND(Inputs!B100*Azure_Factor*FX*(1+Infra_Margin),-3) | E9: =ROUND(Inputs!C100*Azure_Factor*FX*(1+Infra_Margin),-3) | F9: =ROUND(Inputs!D100*Azure_Factor*FX*(1+Infra_Margin),-3) | G9: =ROUND(Inputs!E100*Azure_Factor*FX*(1+Infra_Margin),-3) | H9: =SUM(D9:G9) | I9: =ROUND(Inputs!G100*Azure_Factor*FX*(1+Infra_Margin),-3) | J9: =H9*12+I9*PreProd_GoLive_Months | K9: =H9*12+I9*PreProd_Rel_Months*Major_Rel_Year | L9: =H9/FX | M9: Southeast Asia region (Singapore).
A10: Azure | B10: =Inputs!A29 | C10: Dev, UAT, Production + Pre-Prod when used | D10: =ROUND(Inputs!B101*Azure_Factor*FX*(1+Infra_Margin),-3) | E10: =ROUND(Inputs!C101*Azure_Factor*FX*(1+Infra_Margin),-3) | F10: =ROUND(Inputs!D101*Azure_Factor*FX*(1+Infra_Margin),-3) | G10: =ROUND(Inputs!E101*Azure_Factor*FX*(1+Infra_Margin),-3) | H10: =SUM(D10:G10) | I10: =ROUND(Inputs!G101*Azure_Factor*FX*(1+Infra_Margin),-3) | J10: =H10*12+I10*PreProd_GoLive_Months | K10: =H10*12+I10*PreProd_Rel_Months*Major_Rel_Year | L10: =H10/FX
A11: Azure | B11: =Inputs!A30 | C11: Dev, SIT, UAT, Production (HA) + Pre-Prod when used | D11: =ROUND(Inputs!B102*Azure_Factor*FX*(1+Infra_Margin),-3) | E11: =ROUND(Inputs!C102*Azure_Factor*FX*(1+Infra_Margin),-3) | F11: =ROUND(Inputs!D102*Azure_Factor*FX*(1+Infra_Margin),-3) | G11: =ROUND(Inputs!E102*Azure_Factor*FX*(1+Infra_Margin),-3) | H11: =SUM(D11:G11) | I11: =ROUND(Inputs!G102*Azure_Factor*FX*(1+Infra_Margin),-3) | J11: =H11*12+I11*PreProd_GoLive_Months | K11: =H11*12+I11*PreProd_Rel_Months*Major_Rel_Year | L11: =H11/FX
A12: Azure | B12: =Inputs!A31 | C12: Dev, SIT, UAT, Production (HA, DR copy) + Pre-Prod when used | D12: =ROUND(Inputs!B103*Azure_Factor*FX*(1+Infra_Margin),-3) | E12: =ROUND(Inputs!C103*Azure_Factor*FX*(1+Infra_Margin),-3) | F12: =ROUND(Inputs!D103*Azure_Factor*FX*(1+Infra_Margin),-3) | G12: =ROUND(Inputs!E103*Azure_Factor*FX*(1+Infra_Margin),-3) | H12: =SUM(D12:G12) | I12: =ROUND(Inputs!G103*Azure_Factor*FX*(1+Infra_Margin),-3) | J12: =H12*12+I12*PreProd_GoLive_Months | K12: =H12*12+I12*PreProd_Rel_Months*Major_Rel_Year | L12: =H12/FX
A13: Local partner | B13: =Inputs!A28 | C13: Dev, UAT, Production + Pre-Prod when used | D13: =ROUND(Inputs!B100*Local_Factor*FX*(1+Infra_Margin),-3) | E13: =ROUND(Inputs!C100*Local_Factor*FX*(1+Infra_Margin),-3) | F13: =ROUND(Inputs!D100*Local_Factor*FX*(1+Infra_Margin),-3) | G13: =ROUND(Inputs!E100*Local_Factor*FX*(1+Infra_Margin),-3) | H13: =SUM(D13:G13) | I13: =ROUND(Inputs!G100*Local_Factor*FX*(1+Infra_Margin),-3) | J13: =H13*12+I13*PreProd_GoLive_Months | K13: =H13*12+I13*PreProd_Rel_Months*Major_Rel_Year | L13: =H13/FX | M13: Philippine data centre or partner cloud; data stays in the Philippines.
A14: Local partner | B14: =Inputs!A29 | C14: Dev, UAT, Production + Pre-Prod when used | D14: =ROUND(Inputs!B101*Local_Factor*FX*(1+Infra_Margin),-3) | E14: =ROUND(Inputs!C101*Local_Factor*FX*(1+Infra_Margin),-3) | F14: =ROUND(Inputs!D101*Local_Factor*FX*(1+Infra_Margin),-3) | G14: =ROUND(Inputs!E101*Local_Factor*FX*(1+Infra_Margin),-3) | H14: =SUM(D14:G14) | I14: =ROUND(Inputs!G101*Local_Factor*FX*(1+Infra_Margin),-3) | J14: =H14*12+I14*PreProd_GoLive_Months | K14: =H14*12+I14*PreProd_Rel_Months*Major_Rel_Year | L14: =H14/FX
A15: Local partner | B15: =Inputs!A30 | C15: Dev, SIT, UAT, Production (HA) + Pre-Prod when used | D15: =ROUND(Inputs!B102*Local_Factor*FX*(1+Infra_Margin),-3) | E15: =ROUND(Inputs!C102*Local_Factor*FX*(1+Infra_Margin),-3) | F15: =ROUND(Inputs!D102*Local_Factor*FX*(1+Infra_Margin),-3) | G15: =ROUND(Inputs!E102*Local_Factor*FX*(1+Infra_Margin),-3) | H15: =SUM(D15:G15) | I15: =ROUND(Inputs!G102*Local_Factor*FX*(1+Infra_Margin),-3) | J15: =H15*12+I15*PreProd_GoLive_Months | K15: =H15*12+I15*PreProd_Rel_Months*Major_Rel_Year | L15: =H15/FX
A16: Local partner | B16: =Inputs!A31 | C16: Dev, SIT, UAT, Production (HA, DR copy) + Pre-Prod when used | D16: =ROUND(Inputs!B103*Local_Factor*FX*(1+Infra_Margin),-3) | E16: =ROUND(Inputs!C103*Local_Factor*FX*(1+Infra_Margin),-3) | F16: =ROUND(Inputs!D103*Local_Factor*FX*(1+Infra_Margin),-3) | G16: =ROUND(Inputs!E103*Local_Factor*FX*(1+Infra_Margin),-3) | H16: =SUM(D16:G16) | I16: =ROUND(Inputs!G103*Local_Factor*FX*(1+Infra_Margin),-3) | J16: =H16*12+I16*PreProd_GoLive_Months | K16: =H16*12+I16*PreProd_Rel_Months*Major_Rel_Year | L16: =H16/FX
A17: Customer | B17: =Inputs!A28 | C17: Dev, UAT, Production + Pre-Prod when used | D17: 0 | E17: 0 | F17: 0 | G17: 0 | H17: 0 | I17: 0 | J17: 0 | K17: 0 | L17: 0 | M17: Broker hosts itself (cloud account or own data centre) with the same environment set. Deployment guide supplied; set-up support at day rates.
A18: Customer | B18: =Inputs!A29 | C18: Dev, UAT, Production + Pre-Prod when used | D18: 0 | E18: 0 | F18: 0 | G18: 0 | H18: 0 | I18: 0 | J18: 0 | K18: 0 | L18: 0
A19: Customer | B19: =Inputs!A30 | C19: Dev, SIT, UAT, Production (HA) + Pre-Prod when used | D19: 0 | E19: 0 | F19: 0 | G19: 0 | H19: 0 | I19: 0 | J19: 0 | K19: 0 | L19: 0
A20: Customer | B20: =Inputs!A31 | C20: Dev, SIT, UAT, Production (HA, DR copy) + Pre-Prod when used | D20: 0 | E20: 0 | F20: 0 | G20: 0 | H20: 0 | I20: 0 | J20: 0 | K20: 0 | L20: 0
A22: Environment model and what the price covers
A23: Environment model: Small and Medium brokers have Dev, UAT and Production. Integration and system testing are done in Dev and the release is promoted to UAT for testing, then to Production. Large and Enterprise brokers have Dev, SIT, UAT and Production, with SIT and UAT separate and Production highly available.
A24: Pre-Prod is temporary for every size: created from a production backup (masked when used by people without production access) for the go-live rehearsal and for each major release, then removed. It is billed per month of use at the Pre-Prod rate: by default 2 months around go-live and 1 month per major release (Inputs).
A25: Covers: cloud resources of each environment, daily backups, monitoring and alarms, operating system and database patching, TLS certificates.
A26: Reference sizing: the BrokerVerse capacity document sizes 200 named users (80 concurrent) at 2 API containers of 1 vCPU, 2 GB and Amazon RDS for PostgreSQL 16 db.m7g.large Multi-AZ, 100 GB gp3 storage.
A27: Excludes: e-mail sending service charges above normal volumes, SMS, payment gateway fees, domain names, extra environments such as a training environment (see Optional Services) and disaster-recovery copies for tiers other than Enterprise.
A28: All cloud figures are estimates from public on-demand list prices, rounded up. Confirm with the provider pricing calculator and a partner quotation before a binding offer. Reserved instances or savings plans can lower cost 20% to 40% for a 1 to 3 year commitment.
A29: Billing: monthly in advance in PHP from the handover of each environment; Pre-Prod monthly for each month or part month of use. Hosting fees do not increase yearly; provider price changes are passed through at cost (Hosting Agreement). The margin covers FX movement between USD cloud billing and PHP invoicing, and the operations effort.

Sheet Change Requests
A1: Change requests (CR)
A2: Man-day rates by role, blended rate, CR bands and the estimation method. PHP, exclusive of VAT.
A4: Role | B4: Day rate (PHP) | C4: Day rate (USD) | D4: Hourly equivalent (PHP) | E4: Mix in blended rate
A5: =Inputs!A36 | B5: =Inputs!B36 | C5: =B5/FX | D5: =B5/8 | E5: =Inputs!C36
A6: =Inputs!A37 | B6: =Inputs!B37 | C6: =B6/FX | D6: =B6/8 | E6: =Inputs!C37
A7: =Inputs!A38 | B7: =Inputs!B38 | C7: =B7/FX | D7: =B7/8 | E7: =Inputs!C38
A8: =Inputs!A39 | B8: =Inputs!B39 | C8: =B8/FX | D8: =B8/8 | E8: =Inputs!C39
A9: Blended rate | B9: =Blended | C9: =B9/FX | D9: =B9/8
A11: Estimation method
A12: 1. The broker raises the CR with the business need and examples. iorta TechNXT replies with an impact note within 5 business days (Small) or 10 (Medium, Large).
A13: 2. Developer man-days are estimated from the screens, APIs, reports, database changes and jobs affected.
A14: 3. Business analysis = development x BA %; testing = development x QA %; project management = (BA + development + testing) x PM %; contingency on the total. Days are rounded up to the half day.
A15: 4. Cost = days by role x role day rate. The band decides the approval route and the payment terms: Small, billed on delivery; Medium, 50% on approval and 50% on UAT sign-off; Large, 30% / 50% / 20% like a project.
A16: 5. CRs change the OOTB version for that customer only. The changed code is covered by AMC or subscription support only when merged into the product line; otherwise support of the change is billed at day rates.
A18: CR bands
A19: Band | B19: Total man-days from | C19: Total man-days to | D19: Indicative cost from (PHP, blended) | E19: Indicative cost to (PHP, blended) | F19: Approval | H19: Typical examples
A20: Small | B20: =0.5 | C20: =CR_Small_Max | D20: =B20*Blended | E20: =C20*Blended | F20: Broker IT or operations head | H20: New report column or filter; document template wording; new validation; new field on a screen.
A21: Medium | B21: =CR_Small_Max+0.5 | C21: =CR_Med_Max | D21: =B21*Blended | E21: =C21*Blended | F21: Broker sponsor | H21: New report; new letter or statement; change to a commission or tax computation; new upload template.
A22: Large | B22: =CR_Med_Max+0.5 | C22: =CR_Large_Max | D22: =B22*Blended | E22: =C22*Blended | F22: Steering committee | H22: New module screen set; new insurer or bank integration; new workflow with approvals.
A23: Above the Large band: treated as a separate project with its own statement of work.
A25: Worked examples and calculator
A26: Line | B26: Example Small | C26: Example Medium | D26: Example Large | E26: Calculator (Inputs) | H26: Notes
A27: Development man-days | B27: 2 | C27: 7 | D27: 20 | E27: =CR_Dev_Days | H27: Examples are illustrative; the calculator column reads CR_Dev_Days in Inputs.
A28: Business analysis man-days | B28: =ROUNDUP(B27*CR_BA*2,0)/2 | C28: =ROUNDUP(C27*CR_BA*2,0)/2 | D28: =ROUNDUP(D27*CR_BA*2,0)/2 | E28: =ROUNDUP(E27*CR_BA*2,0)/2
A29: Testing man-days | B29: =ROUNDUP(B27*CR_QA*2,0)/2 | C29: =ROUNDUP(C27*CR_QA*2,0)/2 | D29: =ROUNDUP(D27*CR_QA*2,0)/2 | E29: =ROUNDUP(E27*CR_QA*2,0)/2
A30: Project management man-days | B30: =ROUNDUP((B27+B28+B29)*CR_PM*2,0)/2 | C30: =ROUNDUP((C27+C28+C29)*CR_PM*2,0)/2 | D30: =ROUNDUP((D27+D28+D29)*CR_PM*2,0)/2 | E30: =ROUNDUP((E27+E28+E29)*CR_PM*2,0)/2
A31: Contingency man-days | B31: =ROUNDUP((B27+B28+B29+B30)*CR_Cont*2,0)/2 | C31: =ROUNDUP((C27+C28+C29+C30)*CR_Cont*2,0)/2 | D31: =ROUNDUP((D27+D28+D29+D30)*CR_Cont*2,0)/2 | E31: =ROUNDUP((E27+E28+E29+E30)*CR_Cont*2,0)/2
A32: Total man-days | B32: =SUM(B27:B31) | C32: =SUM(C27:C31) | D32: =SUM(D27:D31) | E32: =SUM(E27:E31)
A33: Band | B33: =IF(B32<=CR_Small_Max,"Small",IF(B32<=CR_Med_Max,"Medium",IF(B32<=CR_Large_Max,"Large","Project"))) | C33: =IF(C32<=CR_Small_Max,"Small",IF(C32<=CR_Med_Max,"Medium",IF(C32<=CR_Large_Max,"Large","Project"))) | D33: =IF(D32<=CR_Small_Max,"Small",IF(D32<=CR_Med_Max,"Medium",IF(D32<=CR_Large_Max,"Large","Project"))) | E33: =IF(E32<=CR_Small_Max,"Small",IF(E32<=CR_Med_Max,"Medium",IF(E32<=CR_Large_Max,"Large","Project")))
A34: Cost: business analyst | B34: =B28*Rate_BA | C34: =C28*Rate_BA | D34: =D28*Rate_BA | E34: =E28*Rate_BA
A35: Cost: developer | B35: =B27*Rate_Dev | C35: =C27*Rate_Dev | D35: =D27*Rate_Dev | E35: =E27*Rate_Dev
A36: Cost: QA engineer | B36: =B29*Rate_QA | C36: =C29*Rate_QA | D36: =D29*Rate_QA | E36: =E29*Rate_QA
A37: Cost: project manager | B37: =B30*Rate_PM | C37: =C30*Rate_PM | D37: =D30*Rate_PM | E37: =E30*Rate_PM
A38: Contingency cost (blended) | B38: =B31*Blended | C38: =C31*Blended | D38: =D31*Blended | E38: =E31*Blended
A39: CR price excl. VAT (PHP) | B39: =SUM(B34:B38) | C39: =SUM(C34:C38) | D39: =SUM(D34:D38) | E39: =SUM(E34:E38)
A40: CR price (USD) | B40: =B39/FX | C40: =C39/FX | D40: =D39/FX | E40: =E39/FX

Sheet Optional Services
A1: Optional services
A2: Priced on request in addition to either model. PHP, exclusive of VAT. 24x7 support escalates 5% a year; hosted environments do not.
A4: Item | B4: Unit | C4: Price (PHP) | D4: Price (USD) | E4: Man-days | F4: Basis and notes
A5: Additional environment (training, second UAT), set-up | B5: one-time | C5: =ROUND(Env_Setup_Days*Blended/Round_To,0)*Round_To | D5: =C5/FX | E5: =Env_Setup_Days | F5: Set-up man-days x blended rate.
A6: Additional environment hosted by iorta TechNXT | B6: per month | C6: =ROUND(NP_Small_USD*FX*(1+Infra_Margin),-3) | D6: =C6/FX | F6: Small non-production size (as Dev) on AWS, cloud cost plus infrastructure margin; no yearly increase. Customer-hosted: set-up fee only.
A7: Training beyond the included days | B7: per trainer day | C7: =Rate_Trainer | D7: =C7/FX | F7: Up to 15 participants per session; customer provides the room and PCs.
A8: Data migration beyond the standard templates | B8: per legacy source | C8: =ROUND(Mig_Days_Source*Blended/Round_To,0)*Round_To | D8: =C8/FX | E8: =Mig_Days_Source | F8: Standard: data loaded by the broker with the BrokerVerse upload templates (docs/package/05_Delivery/Upload_Templates), with guidance. This item covers extraction and transformation from a legacy system.
A9: Data migration, additional effort | B9: per man-day | C9: =Blended | D9: =C9/FX | F9: For volume or data-quality work beyond the estimate.
A10: Additional integration, standard | B10: per integration | C10: =ROUND(Int_Std_Days*Blended/Round_To,0)*Round_To | D10: =C10/FX | E10: =Int_Std_Days | F10: One documented API or file exchange, one direction.
A11: Additional integration, complex | B11: per integration | C11: =ROUND(Int_Cx_Days*Blended/Round_To,0)*Round_To | D11: =C11/FX | E11: =Int_Cx_Days | F11: Two-way, no API, or batch with reconciliation.
A12: Additional line of business after go-live | B12: per line | C12: =ROUND(Days_per_LOB*Blended/Round_To,0)*Round_To | D12: =C12/FX | E12: =Days_per_LOB | F12: Product set-up, rating and tax lines, templates, testing.
A13: New report or document template | B13: per item (typical) | C13: =ROUND(Report_Days*Blended/Round_To,0)*Round_To | D13: =C13/FX | E13: =Report_Days | F13: Small CR band; firm price after the impact note.
A14: On-site day (Metro Manila) | B14: per consultant day | C14: =Rate_Onsite | D14: =C14/FX | F14: Outside Metro Manila: travel, lodging and meals at cost.
A16: Optional modules and partner services (confirmed by management on 04 October 2026): man-days x blended rate, rounded to PHP 10,000; the regulator's or partner's own fees are not included
A17: Item | B17: Unit | C17: Price (PHP) | D17: Price (USD) | E17: Man-days | F17: Scope
A18: Connector go-live with a partner | B18: per connector | C18: =ROUND(Conn_Golive_Days*Blended/Round_To,0)*Round_To | D18: =C18/FX | E18: =Conn_Golive_Days | F18: A delivered connector (SMS gateway, CTPL provider, one insurer, one bank file layout, BIR EIS) taken live: configuration, credential check, live test, support of the partner acceptance; the partner certifies its own side.
A19: Activation of the AML/CFT toolkit | B19: one-time | C19: =ROUND(AML_Act_Days*Blended/Round_To,0)*Round_To | D19: =C19/FX | E19: =AML_Act_Days | F19: The toolkit is included in the software; this is the set-up effort: risk factors and rules workshop, settings, first list loads, provider set-up, AMLC test file. The compliance officer confirms the settings and loads the lists.
A20: Activation of the IC compliance registers | B20: one-time | C20: =ROUND(IC_Act_Days*Blended/Round_To,0)*Round_To | D20: =C20/FX | E20: =IC_Act_Days | F20: Registers included in the software; this is the set-up effort: licence and fit and proper register load, insurer certificates, complaints and breach settings, IC statement account mapping.
A21: Activation of the BIR pack | B21: one-time | C21: =ROUND(BIR_Act_Days*Blended/Round_To,0)*Round_To | D21: =C21/FX | E21: =BIR_Act_Days | F21: BIR forms, EOPT invoices, EIS and CAS pack included in the software; this is the set-up effort: BIR and EOPT invoice settings, ATC mapping, DAT file dry run, CAS books pack. The tax adviser confirms the treatment.
A22: Dealer programme set-up | B22: per programme | C22: =ROUND(Dealer_Prog_Days*Blended/Round_To,0)*Round_To | D22: =C22/FX | E22: =Dealer_Prog_Days | F22: Dealer programmes are included in the software; this is the set-up of one programme: channels, rates, subsidy, bank letter and the first upload.
A23: Client brand pack | B23: per pack | C23: =ROUND(Brand_Pack_Days*Blended/Round_To,0)*Round_To | D23: =C23/FX | E23: =Brand_Pack_Days | F23: Branding is included in the software; this is one pack: theme, sign-in picture, document and e-mail branding, e-signature mapping, exported pack. A pack carrying third-party marks needs the owner's written permission.
A24: AMLC reporting file validation and portal test | B24: one-time | C24: =ROUND(AMLC_Val_Days*Blended/Round_To,0)*Round_To | D24: =C24/FX | E24: =AMLC_Val_Days | F24: CTR and STR layout, institution and transaction codes confirmed with the AMLC, test file accepted in the AMLC portal.
A25: IC annual statement form alignment | B25: one-time | C25: =ROUND(IC_Form_Days*Blended/Round_To,0)*Round_To | D25: =C25/FX | E25: =IC_Form_Days | F25: The accountant working paper mapped to the IC form set in force for the year.
A26: EOPT invoicing review with the broker tax adviser | B26: one-time | C26: =ROUND(EOPT_Rev_Days*Blended/Round_To,0)*Round_To | D26: =C26/FX | E26: =EOPT_Rev_Days | F26: Registered invoice documents, supplementary wording, VAT treatment of each commission stream, ATP or CAS.
A27: BIR CAS registration support | B27: one-time | C27: =ROUND(CAS_Reg_Days*Blended/Round_To,0)*Round_To | D27: =C27/FX | E27: =CAS_Reg_Days | F27: Books, system description and the Permit to Use filing prepared with the broker; the broker files.
A28: BIR EIS enrolment and certification | B28: one-time | C28: =ROUND(EIS_Enrol_Days*Blended/Round_To,0)*Round_To | D28: =C28/FX | E28: =EIS_Enrol_Days | F28: EIS enrolment, signing certificate, final field list, production endpoint and certification of the connector.
A29: CTPL authentication and LTO interface certification | B29: one-time | C29: =ROUND(CTPL_Cert_Days*Blended/Round_To,0)*Round_To | D29: =C29/FX | E29: =CTPL_Cert_Days | F29: Acceptance of the live requests by the accredited provider, COC series, LTO interface where the provider does not transmit.
A30: Insurer API onboarding, per insurer | B30: per insurer | C30: =ROUND(Insurer_Onb_Days*Blended/Round_To,0)*Round_To | D30: =C30/FX | E30: =Insurer_Onb_Days | F30: Endpoint, credentials, field mapping and live test with one insurer.
A31: Bank payment file certification, per bank | B31: per bank | C31: =ROUND(Bank_Cert_Days*Blended/Round_To,0)*Round_To | D31: =C31/FX | E31: =Bank_Cert_Days | F31: Layout validated against the bank specification and a test file accepted by the bank.
A32: SMS or Viber gateway activation | B32: one-time | C32: =ROUND(SMS_Act_Days*Blended/Round_To,0)*Round_To | D32: =C32/FX | E32: =SMS_Act_Days | F32: Sender name or short code, live credentials, templates and consent check tested with the gateway.
A33: Screening list provider onboarding | B33: one-time | C33: =ROUND(Screen_Prov_Days*Blended/Round_To,0)*Round_To | D33: =C33/FX | E33: =Screen_Prov_Days | F33: Provider contract data, API key, adapter test and first screening run.
A35: 24x7 Severity 1 support
A36: ="24x7 Severity 1 support, "&Inputs!A28&" tier" | B36: per year, Year 1 | C36: =Inputs!L28 | D36: =C36/FX | F36: Standard support is business hours (Monday to Friday, 08:00 to 18:00 Philippine time, excluding holidays). This adds round-the-clock response to Severity 1 incidents (production down or a core process stopped for all users).
A37: ="24x7 Severity 1 support, "&Inputs!A29&" tier" | B37: per year, Year 1 | C37: =Inputs!L29 | D37: =C37/FX
A38: ="24x7 Severity 1 support, "&Inputs!A30&" tier" | B38: per year, Year 1 | C38: =Inputs!L30 | D38: =C38/FX
A39: ="24x7 Severity 1 support, "&Inputs!A31&" tier" | B39: per year, Year 1 | C39: =Inputs!L31 | D39: =C39/FX
A41: Included in the standard implementation (no extra charge)
A42: Configuration of the company, branches, users and roles, insurers, commission rates, chart of accounts, banks and the included lines of business.
A43: Data load using the standard upload templates (about 50 templates in docs/package/05_Delivery/Upload_Templates), with the broker supplying clean data.
A44: Training days included for the tier (train-the-trainer), UAT support, go-live support and 4 weeks of hypercare.
A45: Set-up of the environment set of the tier (Dev, UAT and Production; SIT as well for Large and Enterprise) and of Pre-Prod for the go-live rehearsal; hosting is billed separately. Deployment guidance when the broker hosts.
A46: Every module is included in the software price, including the AML/CFT toolkit, the IC compliance registers, the BIR pack, the integration framework with its connectors, dealer programmes and branding. Their activation, each connector go-live and the regulator and partner services are the optional modules and partner services above, confirmed by management on 04 October 2026 as add-on items; no package total changes.

Sheet Sample Quotes
A1: Sample quotes: three brokers, 5-year total cost of ownership
A2: Scenario drivers are in Inputs (Sample quote scenarios). PHP, exclusive of VAT unless stated. Optional items shown separately and added to both models.
A4: ="Example 1: "&Inputs!$B$109&", "&Inputs!$B$110&" users, "&Inputs!$B$111&" lines of business, tier "&INDEX(Inputs!$A$28:$A$31,MATCH(Inputs!$B$110,Inputs!$B$28:$B$31,1))&", hosting: "&Inputs!$B$112
A5: Item | B5: Year 1 | C5: Year 2 | D5: Year 3 | E5: Year 4 | F5: Year 5 | G5: 5-year total (PHP) | H5: 5-year total (USD)
A6: Model A: perpetual
A7: Implementation fee | B7: =ROUND((INDEX(Inputs!$G$28:$G$31,MATCH(Inputs!$B$110,Inputs!$B$28:$B$31,1))+MAX(0,Inputs!$B$111-INDEX(Inputs!$H$28:$H$31,MATCH(Inputs!$B$110,Inputs!$B$28:$B$31,1)))*Days_per_LOB)*Blended/Round_To,0)*Round_To | C7: 0 | D7: 0 | E7: 0 | F7: 0 | G7: =SUM(B7:F7) | H7: =G7/FX
A8: Perpetual licence fee | B8: =MAX(0,MIN(Inputs!$B$110,Inputs!$C$28)-Inputs!$B$28+1)*Inputs!$D$28+MAX(0,MIN(Inputs!$B$110,Inputs!$C$29)-Inputs!$B$29+1)*Inputs!$D$29+MAX(0,MIN(Inputs!$B$110,Inputs!$C$30)-Inputs!$B$30+1)*Inputs!$D$30+MAX(0,MIN(Inputs!$B$110,Inputs!$C$31)-Inputs!$B$31+1)*Inputs!$D$31 | C8: 0 | D8: 0 | E8: 0 | F8: 0 | G8: =SUM(B8:F8) | H8: =G8/FX
A9: AMC (22%, +5% a year) | B9: =IF(1>=AMC_Start,$B$8*AMC_Rate*(1+Esc)^(1-AMC_Start),0) | C9: =IF(2>=AMC_Start,$B$8*AMC_Rate*(1+Esc)^(2-AMC_Start),0) | D9: =IF(3>=AMC_Start,$B$8*AMC_Rate*(1+Esc)^(3-AMC_Start),0) | E9: =IF(4>=AMC_Start,$B$8*AMC_Rate*(1+Esc)^(4-AMC_Start),0) | F9: =IF(5>=AMC_Start,$B$8*AMC_Rate*(1+Esc)^(5-AMC_Start),0) | G9: =SUM(B9:F9) | H9: =G9/FX
A10: Software subtotal, perpetual | B10: =SUM(B7:B9) | C10: =SUM(C7:C9) | D10: =SUM(D7:D9) | E10: =SUM(E7:E9) | F10: =SUM(F7:F9) | G10: =SUM(B10:F10) | H10: =G10/FX
A11: Model B: subscription
A12: Onboarding fee | B12: =$B$7*Onboard_Pct | C12: 0 | D12: 0 | E12: 0 | F12: 0 | G12: =SUM(B12:F12) | H12: =G12/FX
A13: ="Subscription ("&MAX(Inputs!$B$110,INDEX(Inputs!$F$28:$F$31,MATCH(Inputs!$B$110,Inputs!$B$28:$B$31,1)))&" billable users)" | B13: =(MAX(0,MIN(MAX(Inputs!$B$110,INDEX(Inputs!$F$28:$F$31,MATCH(Inputs!$B$110,Inputs!$B$28:$B$31,1))),Inputs!$C$28)-Inputs!$B$28+1)*Inputs!$E$28+MAX(0,MIN(MAX(Inputs!$B$110,INDEX(Inputs!$F$28:$F$31,MATCH(Inputs!$B$110,Inputs!$B$28:$B$31,1))),Inputs!$C$29)-Inputs!$B$29+1)*Inputs!$E$29+MAX(0,MIN(MAX(Inputs!$B$110,INDEX(Inputs!$F$28:$F$31,MATCH(Inputs!$B$110,Inputs!$B$28:$B$31,1))),Inputs!$C$30)-Inputs!$B$30+1)*Inputs!$E$30+MAX(0,MIN(MAX(Inputs!$B$110,INDEX(Inputs!$F$28:$F$31,MATCH(Inputs!$B$110,Inputs!$B$28:$B$31,1))),Inputs!$C$31)-Inputs!$B$31+1)*Inputs!$E$31)*12*(1+Esc)^(1-1) | C13: =(MAX(0,MIN(MAX(Inputs!$B$110,INDEX(Inputs!$F$28:$F$31,MATCH(Inputs!$B$110,Inputs!$B$28:$B$31,1))),Inputs!$C$28)-Inputs!$B$28+1)*Inputs!$E$28+MAX(0,MIN(MAX(Inputs!$B$110,INDEX(Inputs!$F$28:$F$31,MATCH(Inputs!$B$110,Inputs!$B$28:$B$31,1))),Inputs!$C$29)-Inputs!$B$29+1)*Inputs!$E$29+MAX(0,MIN(MAX(Inputs!$B$110,INDEX(Inputs!$F$28:$F$31,MATCH(Inputs!$B$110,Inputs!$B$28:$B$31,1))),Inputs!$C$30)-Inputs!$B$30+1)*Inputs!$E$30+MAX(0,MIN(MAX(Inputs!$B$110,INDEX(Inputs!$F$28:$F$31,MATCH(Inputs!$B$110,Inputs!$B$28:$B$31,1))),Inputs!$C$31)-Inputs!$B$31+1)*Inputs!$E$31)*12*(1+Esc)^(2-1) | D13: =(MAX(0,MIN(MAX(Inputs!$B$110,INDEX(Inputs!$F$28:$F$31,MATCH(Inputs!$B$110,Inputs!$B$28:$B$31,1))),Inputs!$C$28)-Inputs!$B$28+1)*Inputs!$E$28+MAX(0,MIN(MAX(Inputs!$B$110,INDEX(Inputs!$F$28:$F$31,MATCH(Inputs!$B$110,Inputs!$B$28:$B$31,1))),Inputs!$C$29)-Inputs!$B$29+1)*Inputs!$E$29+MAX(0,MIN(MAX(Inputs!$B$110,INDEX(Inputs!$F$28:$F$31,MATCH(Inputs!$B$110,Inputs!$B$28:$B$31,1))),Inputs!$C$30)-Inputs!$B$30+1)*Inputs!$E$30+MAX(0,MIN(MAX(Inputs!$B$110,INDEX(Inputs!$F$28:$F$31,MATCH(Inputs!$B$110,Inputs!$B$28:$B$31,1))),Inputs!$C$31)-Inputs!$B$31+1)*Inputs!$E$31)*12*(1+Esc)^(3-1) | E13: =(MAX(0,MIN(MAX(Inputs!$B$110,INDEX(Inputs!$F$28:$F$31,MATCH(Inputs!$B$110,Inputs!$B$28:$B$31,1))),Inputs!$C$28)-Inputs!$B$28+1)*Inputs!$E$28+MAX(0,MIN(MAX(Inputs!$B$110,INDEX(Inputs!$F$28:$F$31,MATCH(Inputs!$B$110,Inputs!$B$28:$B$31,1))),Inputs!$C$29)-Inputs!$B$29+1)*Inputs!$E$29+MAX(0,MIN(MAX(Inputs!$B$110,INDEX(Inputs!$F$28:$F$31,MATCH(Inputs!$B$110,Inputs!$B$28:$B$31,1))),Inputs!$C$30)-Inputs!$B$30+1)*Inputs!$E$30+MAX(0,MIN(MAX(Inputs!$B$110,INDEX(Inputs!$F$28:$F$31,MATCH(Inputs!$B$110,Inputs!$B$28:$B$31,1))),Inputs!$C$31)-Inputs!$B$31+1)*Inputs!$E$31)*12*(1+Esc)^(4-1) | F13: =(MAX(0,MIN(MAX(Inputs!$B$110,INDEX(Inputs!$F$28:$F$31,MATCH(Inputs!$B$110,Inputs!$B$28:$B$31,1))),Inputs!$C$28)-Inputs!$B$28+1)*Inputs!$E$28+MAX(0,MIN(MAX(Inputs!$B$110,INDEX(Inputs!$F$28:$F$31,MATCH(Inputs!$B$110,Inputs!$B$28:$B$31,1))),Inputs!$C$29)-Inputs!$B$29+1)*Inputs!$E$29+MAX(0,MIN(MAX(Inputs!$B$110,INDEX(Inputs!$F$28:$F$31,MATCH(Inputs!$B$110,Inputs!$B$28:$B$31,1))),Inputs!$C$30)-Inputs!$B$30+1)*Inputs!$E$30+MAX(0,MIN(MAX(Inputs!$B$110,INDEX(Inputs!$F$28:$F$31,MATCH(Inputs!$B$110,Inputs!$B$28:$B$31,1))),Inputs!$C$31)-Inputs!$B$31+1)*Inputs!$E$31)*12*(1+Esc)^(5-1) | G13: =SUM(B13:F13) | H13: =G13/FX
A14: Software subtotal, subscription | B14: =B12+B13 | C14: =C12+C13 | D14: =D12+D13 | E14: =E12+E13 | F14: =F12+F13 | G14: =SUM(B14:F14) | H14: =G14/FX
A15: Optional items (same in both models)
A16: ="Hosting, environment set and Pre-Prod: "&Inputs!$B$112 | B16: =(SUMIFS(Infrastructure!$J$5:$J$20,Infrastructure!$A$5:$A$20,Inputs!$B$112,Infrastructure!$B$5:$B$20,INDEX(Inputs!$A$28:$A$31,MATCH(Inputs!$B$110,Inputs!$B$28:$B$31,1))))*(1+Infra_Esc)^(1-1) | C16: =(SUMIFS(Infrastructure!$K$5:$K$20,Infrastructure!$A$5:$A$20,Inputs!$B$112,Infrastructure!$B$5:$B$20,INDEX(Inputs!$A$28:$A$31,MATCH(Inputs!$B$110,Inputs!$B$28:$B$31,1))))*(1+Infra_Esc)^(2-1) | D16: =(SUMIFS(Infrastructure!$K$5:$K$20,Infrastructure!$A$5:$A$20,Inputs!$B$112,Infrastructure!$B$5:$B$20,INDEX(Inputs!$A$28:$A$31,MATCH(Inputs!$B$110,Inputs!$B$28:$B$31,1))))*(1+Infra_Esc)^(3-1) | E16: =(SUMIFS(Infrastructure!$K$5:$K$20,Infrastructure!$A$5:$A$20,Inputs!$B$112,Infrastructure!$B$5:$B$20,INDEX(Inputs!$A$28:$A$31,MATCH(Inputs!$B$110,Inputs!$B$28:$B$31,1))))*(1+Infra_Esc)^(4-1) | F16: =(SUMIFS(Infrastructure!$K$5:$K$20,Infrastructure!$A$5:$A$20,Inputs!$B$112,Infrastructure!$B$5:$B$20,INDEX(Inputs!$A$28:$A$31,MATCH(Inputs!$B$110,Inputs!$B$28:$B$31,1))))*(1+Infra_Esc)^(5-1) | G16: =SUM(B16:F16) | H16: =G16/FX
A17: 24x7 Severity 1 support | B17: =IF(Inputs!$B$113="Yes",INDEX(Inputs!$L$28:$L$31,MATCH(Inputs!$B$110,Inputs!$B$28:$B$31,1))*(1+Esc)^(1-1),0) | C17: =IF(Inputs!$B$113="Yes",INDEX(Inputs!$L$28:$L$31,MATCH(Inputs!$B$110,Inputs!$B$28:$B$31,1))*(1+Esc)^(2-1),0) | D17: =IF(Inputs!$B$113="Yes",INDEX(Inputs!$L$28:$L$31,MATCH(Inputs!$B$110,Inputs!$B$28:$B$31,1))*(1+Esc)^(3-1),0) | E17: =IF(Inputs!$B$113="Yes",INDEX(Inputs!$L$28:$L$31,MATCH(Inputs!$B$110,Inputs!$B$28:$B$31,1))*(1+Esc)^(4-1),0) | F17: =IF(Inputs!$B$113="Yes",INDEX(Inputs!$L$28:$L$31,MATCH(Inputs!$B$110,Inputs!$B$28:$B$31,1))*(1+Esc)^(5-1),0) | G17: =SUM(B17:F17) | H17: =G17/FX
A18: Extra training, migration and integrations (one-time) | B18: =Inputs!$B$114*Rate_Trainer+ROUND(Mig_Days_Source*Blended/Round_To,0)*Round_To*Inputs!$B$115+ROUND(Int_Std_Days*Blended/Round_To,0)*Round_To*Inputs!$B$116 | C18: 0 | D18: 0 | E18: 0 | F18: 0 | G18: =SUM(B18:F18) | H18: =G18/FX
A19: Optional subtotal | B19: =SUM(B16:B18) | C19: =SUM(C16:C18) | D19: =SUM(D16:D18) | E19: =SUM(E16:E18) | F19: =SUM(F16:F18) | G19: =SUM(B19:F19) | H19: =G19/FX
A20: Total cost of ownership
A21: Perpetual with options, excl. VAT | B21: =B10+B19 | C21: =C10+C19 | D21: =D10+D19 | E21: =E10+E19 | F21: =F10+F19 | G21: =SUM(B21:F21) | H21: =G21/FX
A22: Subscription with options, excl. VAT | B22: =B14+B19 | C22: =C14+C19 | D22: =D14+D19 | E22: =E14+E19 | F22: =F14+F19 | G22: =SUM(B22:F22) | H22: =G22/FX
A23: Perpetual with options, incl. VAT | B23: =B21*(1+VAT) | C23: =C21*(1+VAT) | D23: =D21*(1+VAT) | E23: =E21*(1+VAT) | F23: =F21*(1+VAT) | G23: =SUM(B23:F23) | H23: =G23/FX
A24: Subscription with options, incl. VAT | B24: =B22*(1+VAT) | C24: =C22*(1+VAT) | D24: =D22*(1+VAT) | E24: =E22*(1+VAT) | F24: =F22*(1+VAT) | G24: =SUM(B24:F24) | H24: =G24/FX
A25: Lower 5-year cost (excl. VAT) | B25: =IF(G21<G22,"Perpetual","Subscription") | C25: by (PHP) | D25: =ABS(G21-G22) | E25: Year 1 cash, perpetual vs subscription | G25: =B21 | H25: =B22
A27: ="Example 2: "&Inputs!$C$109&", "&Inputs!$C$110&" users, "&Inputs!$C$111&" lines of business, tier "&INDEX(Inputs!$A$28:$A$31,MATCH(Inputs!$C$110,Inputs!$B$28:$B$31,1))&", hosting: "&Inputs!$C$112
A28: Item | B28: Year 1 | C28: Year 2 | D28: Year 3 | E28: Year 4 | F28: Year 5 | G28: 5-year total (PHP) | H28: 5-year total (USD)
A29: Model A: perpetual
A30: Implementation fee | B30: =ROUND((INDEX(Inputs!$G$28:$G$31,MATCH(Inputs!$C$110,Inputs!$B$28:$B$31,1))+MAX(0,Inputs!$C$111-INDEX(Inputs!$H$28:$H$31,MATCH(Inputs!$C$110,Inputs!$B$28:$B$31,1)))*Days_per_LOB)*Blended/Round_To,0)*Round_To | C30: 0 | D30: 0 | E30: 0 | F30: 0 | G30: =SUM(B30:F30) | H30: =G30/FX
A31: Perpetual licence fee | B31: =MAX(0,MIN(Inputs!$C$110,Inputs!$C$28)-Inputs!$B$28+1)*Inputs!$D$28+MAX(0,MIN(Inputs!$C$110,Inputs!$C$29)-Inputs!$B$29+1)*Inputs!$D$29+MAX(0,MIN(Inputs!$C$110,Inputs!$C$30)-Inputs!$B$30+1)*Inputs!$D$30+MAX(0,MIN(Inputs!$C$110,Inputs!$C$31)-Inputs!$B$31+1)*Inputs!$D$31 | C31: 0 | D31: 0 | E31: 0 | F31: 0 | G31: =SUM(B31:F31) | H31: =G31/FX
A32: AMC (22%, +5% a year) | B32: =IF(1>=AMC_Start,$B$31*AMC_Rate*(1+Esc)^(1-AMC_Start),0) | C32: =IF(2>=AMC_Start,$B$31*AMC_Rate*(1+Esc)^(2-AMC_Start),0) | D32: =IF(3>=AMC_Start,$B$31*AMC_Rate*(1+Esc)^(3-AMC_Start),0) | E32: =IF(4>=AMC_Start,$B$31*AMC_Rate*(1+Esc)^(4-AMC_Start),0) | F32: =IF(5>=AMC_Start,$B$31*AMC_Rate*(1+Esc)^(5-AMC_Start),0) | G32: =SUM(B32:F32) | H32: =G32/FX
A33: Software subtotal, perpetual | B33: =SUM(B30:B32) | C33: =SUM(C30:C32) | D33: =SUM(D30:D32) | E33: =SUM(E30:E32) | F33: =SUM(F30:F32) | G33: =SUM(B33:F33) | H33: =G33/FX
A34: Model B: subscription
A35: Onboarding fee | B35: =$B$30*Onboard_Pct | C35: 0 | D35: 0 | E35: 0 | F35: 0 | G35: =SUM(B35:F35) | H35: =G35/FX
A36: ="Subscription ("&MAX(Inputs!$C$110,INDEX(Inputs!$F$28:$F$31,MATCH(Inputs!$C$110,Inputs!$B$28:$B$31,1)))&" billable users)" | B36: =(MAX(0,MIN(MAX(Inputs!$C$110,INDEX(Inputs!$F$28:$F$31,MATCH(Inputs!$C$110,Inputs!$B$28:$B$31,1))),Inputs!$C$28)-Inputs!$B$28+1)*Inputs!$E$28+MAX(0,MIN(MAX(Inputs!$C$110,INDEX(Inputs!$F$28:$F$31,MATCH(Inputs!$C$110,Inputs!$B$28:$B$31,1))),Inputs!$C$29)-Inputs!$B$29+1)*Inputs!$E$29+MAX(0,MIN(MAX(Inputs!$C$110,INDEX(Inputs!$F$28:$F$31,MATCH(Inputs!$C$110,Inputs!$B$28:$B$31,1))),Inputs!$C$30)-Inputs!$B$30+1)*Inputs!$E$30+MAX(0,MIN(MAX(Inputs!$C$110,INDEX(Inputs!$F$28:$F$31,MATCH(Inputs!$C$110,Inputs!$B$28:$B$31,1))),Inputs!$C$31)-Inputs!$B$31+1)*Inputs!$E$31)*12*(1+Esc)^(1-1) | C36: =(MAX(0,MIN(MAX(Inputs!$C$110,INDEX(Inputs!$F$28:$F$31,MATCH(Inputs!$C$110,Inputs!$B$28:$B$31,1))),Inputs!$C$28)-Inputs!$B$28+1)*Inputs!$E$28+MAX(0,MIN(MAX(Inputs!$C$110,INDEX(Inputs!$F$28:$F$31,MATCH(Inputs!$C$110,Inputs!$B$28:$B$31,1))),Inputs!$C$29)-Inputs!$B$29+1)*Inputs!$E$29+MAX(0,MIN(MAX(Inputs!$C$110,INDEX(Inputs!$F$28:$F$31,MATCH(Inputs!$C$110,Inputs!$B$28:$B$31,1))),Inputs!$C$30)-Inputs!$B$30+1)*Inputs!$E$30+MAX(0,MIN(MAX(Inputs!$C$110,INDEX(Inputs!$F$28:$F$31,MATCH(Inputs!$C$110,Inputs!$B$28:$B$31,1))),Inputs!$C$31)-Inputs!$B$31+1)*Inputs!$E$31)*12*(1+Esc)^(2-1) | D36: =(MAX(0,MIN(MAX(Inputs!$C$110,INDEX(Inputs!$F$28:$F$31,MATCH(Inputs!$C$110,Inputs!$B$28:$B$31,1))),Inputs!$C$28)-Inputs!$B$28+1)*Inputs!$E$28+MAX(0,MIN(MAX(Inputs!$C$110,INDEX(Inputs!$F$28:$F$31,MATCH(Inputs!$C$110,Inputs!$B$28:$B$31,1))),Inputs!$C$29)-Inputs!$B$29+1)*Inputs!$E$29+MAX(0,MIN(MAX(Inputs!$C$110,INDEX(Inputs!$F$28:$F$31,MATCH(Inputs!$C$110,Inputs!$B$28:$B$31,1))),Inputs!$C$30)-Inputs!$B$30+1)*Inputs!$E$30+MAX(0,MIN(MAX(Inputs!$C$110,INDEX(Inputs!$F$28:$F$31,MATCH(Inputs!$C$110,Inputs!$B$28:$B$31,1))),Inputs!$C$31)-Inputs!$B$31+1)*Inputs!$E$31)*12*(1+Esc)^(3-1) | E36: =(MAX(0,MIN(MAX(Inputs!$C$110,INDEX(Inputs!$F$28:$F$31,MATCH(Inputs!$C$110,Inputs!$B$28:$B$31,1))),Inputs!$C$28)-Inputs!$B$28+1)*Inputs!$E$28+MAX(0,MIN(MAX(Inputs!$C$110,INDEX(Inputs!$F$28:$F$31,MATCH(Inputs!$C$110,Inputs!$B$28:$B$31,1))),Inputs!$C$29)-Inputs!$B$29+1)*Inputs!$E$29+MAX(0,MIN(MAX(Inputs!$C$110,INDEX(Inputs!$F$28:$F$31,MATCH(Inputs!$C$110,Inputs!$B$28:$B$31,1))),Inputs!$C$30)-Inputs!$B$30+1)*Inputs!$E$30+MAX(0,MIN(MAX(Inputs!$C$110,INDEX(Inputs!$F$28:$F$31,MATCH(Inputs!$C$110,Inputs!$B$28:$B$31,1))),Inputs!$C$31)-Inputs!$B$31+1)*Inputs!$E$31)*12*(1+Esc)^(4-1) | F36: =(MAX(0,MIN(MAX(Inputs!$C$110,INDEX(Inputs!$F$28:$F$31,MATCH(Inputs!$C$110,Inputs!$B$28:$B$31,1))),Inputs!$C$28)-Inputs!$B$28+1)*Inputs!$E$28+MAX(0,MIN(MAX(Inputs!$C$110,INDEX(Inputs!$F$28:$F$31,MATCH(Inputs!$C$110,Inputs!$B$28:$B$31,1))),Inputs!$C$29)-Inputs!$B$29+1)*Inputs!$E$29+MAX(0,MIN(MAX(Inputs!$C$110,INDEX(Inputs!$F$28:$F$31,MATCH(Inputs!$C$110,Inputs!$B$28:$B$31,1))),Inputs!$C$30)-Inputs!$B$30+1)*Inputs!$E$30+MAX(0,MIN(MAX(Inputs!$C$110,INDEX(Inputs!$F$28:$F$31,MATCH(Inputs!$C$110,Inputs!$B$28:$B$31,1))),Inputs!$C$31)-Inputs!$B$31+1)*Inputs!$E$31)*12*(1+Esc)^(5-1) | G36: =SUM(B36:F36) | H36: =G36/FX
A37: Software subtotal, subscription | B37: =B35+B36 | C37: =C35+C36 | D37: =D35+D36 | E37: =E35+E36 | F37: =F35+F36 | G37: =SUM(B37:F37) | H37: =G37/FX
A38: Optional items (same in both models)
A39: ="Hosting, environment set and Pre-Prod: "&Inputs!$C$112 | B39: =(SUMIFS(Infrastructure!$J$5:$J$20,Infrastructure!$A$5:$A$20,Inputs!$C$112,Infrastructure!$B$5:$B$20,INDEX(Inputs!$A$28:$A$31,MATCH(Inputs!$C$110,Inputs!$B$28:$B$31,1))))*(1+Infra_Esc)^(1-1) | C39: =(SUMIFS(Infrastructure!$K$5:$K$20,Infrastructure!$A$5:$A$20,Inputs!$C$112,Infrastructure!$B$5:$B$20,INDEX(Inputs!$A$28:$A$31,MATCH(Inputs!$C$110,Inputs!$B$28:$B$31,1))))*(1+Infra_Esc)^(2-1) | D39: =(SUMIFS(Infrastructure!$K$5:$K$20,Infrastructure!$A$5:$A$20,Inputs!$C$112,Infrastructure!$B$5:$B$20,INDEX(Inputs!$A$28:$A$31,MATCH(Inputs!$C$110,Inputs!$B$28:$B$31,1))))*(1+Infra_Esc)^(3-1) | E39: =(SUMIFS(Infrastructure!$K$5:$K$20,Infrastructure!$A$5:$A$20,Inputs!$C$112,Infrastructure!$B$5:$B$20,INDEX(Inputs!$A$28:$A$31,MATCH(Inputs!$C$110,Inputs!$B$28:$B$31,1))))*(1+Infra_Esc)^(4-1) | F39: =(SUMIFS(Infrastructure!$K$5:$K$20,Infrastructure!$A$5:$A$20,Inputs!$C$112,Infrastructure!$B$5:$B$20,INDEX(Inputs!$A$28:$A$31,MATCH(Inputs!$C$110,Inputs!$B$28:$B$31,1))))*(1+Infra_Esc)^(5-1) | G39: =SUM(B39:F39) | H39: =G39/FX
A40: 24x7 Severity 1 support | B40: =IF(Inputs!$C$113="Yes",INDEX(Inputs!$L$28:$L$31,MATCH(Inputs!$C$110,Inputs!$B$28:$B$31,1))*(1+Esc)^(1-1),0) | C40: =IF(Inputs!$C$113="Yes",INDEX(Inputs!$L$28:$L$31,MATCH(Inputs!$C$110,Inputs!$B$28:$B$31,1))*(1+Esc)^(2-1),0) | D40: =IF(Inputs!$C$113="Yes",INDEX(Inputs!$L$28:$L$31,MATCH(Inputs!$C$110,Inputs!$B$28:$B$31,1))*(1+Esc)^(3-1),0) | E40: =IF(Inputs!$C$113="Yes",INDEX(Inputs!$L$28:$L$31,MATCH(Inputs!$C$110,Inputs!$B$28:$B$31,1))*(1+Esc)^(4-1),0) | F40: =IF(Inputs!$C$113="Yes",INDEX(Inputs!$L$28:$L$31,MATCH(Inputs!$C$110,Inputs!$B$28:$B$31,1))*(1+Esc)^(5-1),0) | G40: =SUM(B40:F40) | H40: =G40/FX
A41: Extra training, migration and integrations (one-time) | B41: =Inputs!$C$114*Rate_Trainer+ROUND(Mig_Days_Source*Blended/Round_To,0)*Round_To*Inputs!$C$115+ROUND(Int_Std_Days*Blended/Round_To,0)*Round_To*Inputs!$C$116 | C41: 0 | D41: 0 | E41: 0 | F41: 0 | G41: =SUM(B41:F41) | H41: =G41/FX
A42: Optional subtotal | B42: =SUM(B39:B41) | C42: =SUM(C39:C41) | D42: =SUM(D39:D41) | E42: =SUM(E39:E41) | F42: =SUM(F39:F41) | G42: =SUM(B42:F42) | H42: =G42/FX
A43: Total cost of ownership
A44: Perpetual with options, excl. VAT | B44: =B33+B42 | C44: =C33+C42 | D44: =D33+D42 | E44: =E33+E42 | F44: =F33+F42 | G44: =SUM(B44:F44) | H44: =G44/FX
A45: Subscription with options, excl. VAT | B45: =B37+B42 | C45: =C37+C42 | D45: =D37+D42 | E45: =E37+E42 | F45: =F37+F42 | G45: =SUM(B45:F45) | H45: =G45/FX
A46: Perpetual with options, incl. VAT | B46: =B44*(1+VAT) | C46: =C44*(1+VAT) | D46: =D44*(1+VAT) | E46: =E44*(1+VAT) | F46: =F44*(1+VAT) | G46: =SUM(B46:F46) | H46: =G46/FX
A47: Subscription with options, incl. VAT | B47: =B45*(1+VAT) | C47: =C45*(1+VAT) | D47: =D45*(1+VAT) | E47: =E45*(1+VAT) | F47: =F45*(1+VAT) | G47: =SUM(B47:F47) | H47: =G47/FX
A48: Lower 5-year cost (excl. VAT) | B48: =IF(G44<G45,"Perpetual","Subscription") | C48: by (PHP) | D48: =ABS(G44-G45) | E48: Year 1 cash, perpetual vs subscription | G48: =B44 | H48: =B45
A50: ="Example 3: "&Inputs!$D$109&", "&Inputs!$D$110&" users, "&Inputs!$D$111&" lines of business, tier "&INDEX(Inputs!$A$28:$A$31,MATCH(Inputs!$D$110,Inputs!$B$28:$B$31,1))&", hosting: "&Inputs!$D$112
A51: Item | B51: Year 1 | C51: Year 2 | D51: Year 3 | E51: Year 4 | F51: Year 5 | G51: 5-year total (PHP) | H51: 5-year total (USD)
A52: Model A: perpetual
A53: Implementation fee | B53: =ROUND((INDEX(Inputs!$G$28:$G$31,MATCH(Inputs!$D$110,Inputs!$B$28:$B$31,1))+MAX(0,Inputs!$D$111-INDEX(Inputs!$H$28:$H$31,MATCH(Inputs!$D$110,Inputs!$B$28:$B$31,1)))*Days_per_LOB)*Blended/Round_To,0)*Round_To | C53: 0 | D53: 0 | E53: 0 | F53: 0 | G53: =SUM(B53:F53) | H53: =G53/FX
A54: Perpetual licence fee | B54: =MAX(0,MIN(Inputs!$D$110,Inputs!$C$28)-Inputs!$B$28+1)*Inputs!$D$28+MAX(0,MIN(Inputs!$D$110,Inputs!$C$29)-Inputs!$B$29+1)*Inputs!$D$29+MAX(0,MIN(Inputs!$D$110,Inputs!$C$30)-Inputs!$B$30+1)*Inputs!$D$30+MAX(0,MIN(Inputs!$D$110,Inputs!$C$31)-Inputs!$B$31+1)*Inputs!$D$31 | C54: 0 | D54: 0 | E54: 0 | F54: 0 | G54: =SUM(B54:F54) | H54: =G54/FX
A55: AMC (22%, +5% a year) | B55: =IF(1>=AMC_Start,$B$54*AMC_Rate*(1+Esc)^(1-AMC_Start),0) | C55: =IF(2>=AMC_Start,$B$54*AMC_Rate*(1+Esc)^(2-AMC_Start),0) | D55: =IF(3>=AMC_Start,$B$54*AMC_Rate*(1+Esc)^(3-AMC_Start),0) | E55: =IF(4>=AMC_Start,$B$54*AMC_Rate*(1+Esc)^(4-AMC_Start),0) | F55: =IF(5>=AMC_Start,$B$54*AMC_Rate*(1+Esc)^(5-AMC_Start),0) | G55: =SUM(B55:F55) | H55: =G55/FX
A56: Software subtotal, perpetual | B56: =SUM(B53:B55) | C56: =SUM(C53:C55) | D56: =SUM(D53:D55) | E56: =SUM(E53:E55) | F56: =SUM(F53:F55) | G56: =SUM(B56:F56) | H56: =G56/FX
A57: Model B: subscription
A58: Onboarding fee | B58: =$B$53*Onboard_Pct | C58: 0 | D58: 0 | E58: 0 | F58: 0 | G58: =SUM(B58:F58) | H58: =G58/FX
A59: ="Subscription ("&MAX(Inputs!$D$110,INDEX(Inputs!$F$28:$F$31,MATCH(Inputs!$D$110,Inputs!$B$28:$B$31,1)))&" billable users)" | B59: =(MAX(0,MIN(MAX(Inputs!$D$110,INDEX(Inputs!$F$28:$F$31,MATCH(Inputs!$D$110,Inputs!$B$28:$B$31,1))),Inputs!$C$28)-Inputs!$B$28+1)*Inputs!$E$28+MAX(0,MIN(MAX(Inputs!$D$110,INDEX(Inputs!$F$28:$F$31,MATCH(Inputs!$D$110,Inputs!$B$28:$B$31,1))),Inputs!$C$29)-Inputs!$B$29+1)*Inputs!$E$29+MAX(0,MIN(MAX(Inputs!$D$110,INDEX(Inputs!$F$28:$F$31,MATCH(Inputs!$D$110,Inputs!$B$28:$B$31,1))),Inputs!$C$30)-Inputs!$B$30+1)*Inputs!$E$30+MAX(0,MIN(MAX(Inputs!$D$110,INDEX(Inputs!$F$28:$F$31,MATCH(Inputs!$D$110,Inputs!$B$28:$B$31,1))),Inputs!$C$31)-Inputs!$B$31+1)*Inputs!$E$31)*12*(1+Esc)^(1-1) | C59: =(MAX(0,MIN(MAX(Inputs!$D$110,INDEX(Inputs!$F$28:$F$31,MATCH(Inputs!$D$110,Inputs!$B$28:$B$31,1))),Inputs!$C$28)-Inputs!$B$28+1)*Inputs!$E$28+MAX(0,MIN(MAX(Inputs!$D$110,INDEX(Inputs!$F$28:$F$31,MATCH(Inputs!$D$110,Inputs!$B$28:$B$31,1))),Inputs!$C$29)-Inputs!$B$29+1)*Inputs!$E$29+MAX(0,MIN(MAX(Inputs!$D$110,INDEX(Inputs!$F$28:$F$31,MATCH(Inputs!$D$110,Inputs!$B$28:$B$31,1))),Inputs!$C$30)-Inputs!$B$30+1)*Inputs!$E$30+MAX(0,MIN(MAX(Inputs!$D$110,INDEX(Inputs!$F$28:$F$31,MATCH(Inputs!$D$110,Inputs!$B$28:$B$31,1))),Inputs!$C$31)-Inputs!$B$31+1)*Inputs!$E$31)*12*(1+Esc)^(2-1) | D59: =(MAX(0,MIN(MAX(Inputs!$D$110,INDEX(Inputs!$F$28:$F$31,MATCH(Inputs!$D$110,Inputs!$B$28:$B$31,1))),Inputs!$C$28)-Inputs!$B$28+1)*Inputs!$E$28+MAX(0,MIN(MAX(Inputs!$D$110,INDEX(Inputs!$F$28:$F$31,MATCH(Inputs!$D$110,Inputs!$B$28:$B$31,1))),Inputs!$C$29)-Inputs!$B$29+1)*Inputs!$E$29+MAX(0,MIN(MAX(Inputs!$D$110,INDEX(Inputs!$F$28:$F$31,MATCH(Inputs!$D$110,Inputs!$B$28:$B$31,1))),Inputs!$C$30)-Inputs!$B$30+1)*Inputs!$E$30+MAX(0,MIN(MAX(Inputs!$D$110,INDEX(Inputs!$F$28:$F$31,MATCH(Inputs!$D$110,Inputs!$B$28:$B$31,1))),Inputs!$C$31)-Inputs!$B$31+1)*Inputs!$E$31)*12*(1+Esc)^(3-1) | E59: =(MAX(0,MIN(MAX(Inputs!$D$110,INDEX(Inputs!$F$28:$F$31,MATCH(Inputs!$D$110,Inputs!$B$28:$B$31,1))),Inputs!$C$28)-Inputs!$B$28+1)*Inputs!$E$28+MAX(0,MIN(MAX(Inputs!$D$110,INDEX(Inputs!$F$28:$F$31,MATCH(Inputs!$D$110,Inputs!$B$28:$B$31,1))),Inputs!$C$29)-Inputs!$B$29+1)*Inputs!$E$29+MAX(0,MIN(MAX(Inputs!$D$110,INDEX(Inputs!$F$28:$F$31,MATCH(Inputs!$D$110,Inputs!$B$28:$B$31,1))),Inputs!$C$30)-Inputs!$B$30+1)*Inputs!$E$30+MAX(0,MIN(MAX(Inputs!$D$110,INDEX(Inputs!$F$28:$F$31,MATCH(Inputs!$D$110,Inputs!$B$28:$B$31,1))),Inputs!$C$31)-Inputs!$B$31+1)*Inputs!$E$31)*12*(1+Esc)^(4-1) | F59: =(MAX(0,MIN(MAX(Inputs!$D$110,INDEX(Inputs!$F$28:$F$31,MATCH(Inputs!$D$110,Inputs!$B$28:$B$31,1))),Inputs!$C$28)-Inputs!$B$28+1)*Inputs!$E$28+MAX(0,MIN(MAX(Inputs!$D$110,INDEX(Inputs!$F$28:$F$31,MATCH(Inputs!$D$110,Inputs!$B$28:$B$31,1))),Inputs!$C$29)-Inputs!$B$29+1)*Inputs!$E$29+MAX(0,MIN(MAX(Inputs!$D$110,INDEX(Inputs!$F$28:$F$31,MATCH(Inputs!$D$110,Inputs!$B$28:$B$31,1))),Inputs!$C$30)-Inputs!$B$30+1)*Inputs!$E$30+MAX(0,MIN(MAX(Inputs!$D$110,INDEX(Inputs!$F$28:$F$31,MATCH(Inputs!$D$110,Inputs!$B$28:$B$31,1))),Inputs!$C$31)-Inputs!$B$31+1)*Inputs!$E$31)*12*(1+Esc)^(5-1) | G59: =SUM(B59:F59) | H59: =G59/FX
A60: Software subtotal, subscription | B60: =B58+B59 | C60: =C58+C59 | D60: =D58+D59 | E60: =E58+E59 | F60: =F58+F59 | G60: =SUM(B60:F60) | H60: =G60/FX
A61: Optional items (same in both models)
A62: ="Hosting, environment set and Pre-Prod: "&Inputs!$D$112 | B62: =(SUMIFS(Infrastructure!$J$5:$J$20,Infrastructure!$A$5:$A$20,Inputs!$D$112,Infrastructure!$B$5:$B$20,INDEX(Inputs!$A$28:$A$31,MATCH(Inputs!$D$110,Inputs!$B$28:$B$31,1))))*(1+Infra_Esc)^(1-1) | C62: =(SUMIFS(Infrastructure!$K$5:$K$20,Infrastructure!$A$5:$A$20,Inputs!$D$112,Infrastructure!$B$5:$B$20,INDEX(Inputs!$A$28:$A$31,MATCH(Inputs!$D$110,Inputs!$B$28:$B$31,1))))*(1+Infra_Esc)^(2-1) | D62: =(SUMIFS(Infrastructure!$K$5:$K$20,Infrastructure!$A$5:$A$20,Inputs!$D$112,Infrastructure!$B$5:$B$20,INDEX(Inputs!$A$28:$A$31,MATCH(Inputs!$D$110,Inputs!$B$28:$B$31,1))))*(1+Infra_Esc)^(3-1) | E62: =(SUMIFS(Infrastructure!$K$5:$K$20,Infrastructure!$A$5:$A$20,Inputs!$D$112,Infrastructure!$B$5:$B$20,INDEX(Inputs!$A$28:$A$31,MATCH(Inputs!$D$110,Inputs!$B$28:$B$31,1))))*(1+Infra_Esc)^(4-1) | F62: =(SUMIFS(Infrastructure!$K$5:$K$20,Infrastructure!$A$5:$A$20,Inputs!$D$112,Infrastructure!$B$5:$B$20,INDEX(Inputs!$A$28:$A$31,MATCH(Inputs!$D$110,Inputs!$B$28:$B$31,1))))*(1+Infra_Esc)^(5-1) | G62: =SUM(B62:F62) | H62: =G62/FX
A63: 24x7 Severity 1 support | B63: =IF(Inputs!$D$113="Yes",INDEX(Inputs!$L$28:$L$31,MATCH(Inputs!$D$110,Inputs!$B$28:$B$31,1))*(1+Esc)^(1-1),0) | C63: =IF(Inputs!$D$113="Yes",INDEX(Inputs!$L$28:$L$31,MATCH(Inputs!$D$110,Inputs!$B$28:$B$31,1))*(1+Esc)^(2-1),0) | D63: =IF(Inputs!$D$113="Yes",INDEX(Inputs!$L$28:$L$31,MATCH(Inputs!$D$110,Inputs!$B$28:$B$31,1))*(1+Esc)^(3-1),0) | E63: =IF(Inputs!$D$113="Yes",INDEX(Inputs!$L$28:$L$31,MATCH(Inputs!$D$110,Inputs!$B$28:$B$31,1))*(1+Esc)^(4-1),0) | F63: =IF(Inputs!$D$113="Yes",INDEX(Inputs!$L$28:$L$31,MATCH(Inputs!$D$110,Inputs!$B$28:$B$31,1))*(1+Esc)^(5-1),0) | G63: =SUM(B63:F63) | H63: =G63/FX
A64: Extra training, migration and integrations (one-time) | B64: =Inputs!$D$114*Rate_Trainer+ROUND(Mig_Days_Source*Blended/Round_To,0)*Round_To*Inputs!$D$115+ROUND(Int_Std_Days*Blended/Round_To,0)*Round_To*Inputs!$D$116 | C64: 0 | D64: 0 | E64: 0 | F64: 0 | G64: =SUM(B64:F64) | H64: =G64/FX
A65: Optional subtotal | B65: =SUM(B62:B64) | C65: =SUM(C62:C64) | D65: =SUM(D62:D64) | E65: =SUM(E62:E64) | F65: =SUM(F62:F64) | G65: =SUM(B65:F65) | H65: =G65/FX
A66: Total cost of ownership
A67: Perpetual with options, excl. VAT | B67: =B56+B65 | C67: =C56+C65 | D67: =D56+D65 | E67: =E56+E65 | F67: =F56+F65 | G67: =SUM(B67:F67) | H67: =G67/FX
A68: Subscription with options, excl. VAT | B68: =B60+B65 | C68: =C60+C65 | D68: =D60+D65 | E68: =E60+E65 | F68: =F60+F65 | G68: =SUM(B68:F68) | H68: =G68/FX
A69: Perpetual with options, incl. VAT | B69: =B67*(1+VAT) | C69: =C67*(1+VAT) | D69: =D67*(1+VAT) | E69: =E67*(1+VAT) | F69: =F67*(1+VAT) | G69: =SUM(B69:F69) | H69: =G69/FX
A70: Subscription with options, incl. VAT | B70: =B68*(1+VAT) | C70: =C68*(1+VAT) | D70: =D68*(1+VAT) | E70: =E68*(1+VAT) | F70: =F68*(1+VAT) | G70: =SUM(B70:F70) | H70: =G70/FX
A71: Lower 5-year cost (excl. VAT) | B71: =IF(G67<G68,"Perpetual","Subscription") | C71: by (PHP) | D71: =ABS(G67-G68) | E71: Year 1 cash, perpetual vs subscription | G71: =B67 | H71: =B68
A73: Payment terms assumed: implementation 40% on signing, 40% on UAT sign-off, 20% on go-live; perpetual licence on go-live; AMC yearly in advance; subscription and hosting monthly in advance.

Sheet Market Benchmark
A1: Market benchmark: comparable systems and prices
A2: Published prices are rare in this market. "Third-party estimate" means a review or comparison site, not the vendor. Converted at the Inputs exchange rate.
A4: Vendor / product | B4: Origin / market | C4: Pricing model | D4: Price as found | E4: Low (USD per user per month) | F4: High (USD per user per month) | G4: Low (PHP per user per month) | H4: High (PHP per user per month) | I4: Source ID | J4: Type of evidence and notes
A5: Applied Epic | B5: USA, global | C5: Subscription per user, quote only | D5: USD 125 to 250 per user per month; set-up USD 10,000 to 25,000 | E5: 125 | F5: 250 | G5: =IF(E5="","",E5*FX) | H5: =IF(F5="","",F5*FX) | I5: S5 | J5: Third-party estimate. Large-agency system; not localised for Philippine taxes or IC reports.
A6: Applied Sagitta | B6: USA | C6: Enterprise, quote only | D6: USD 200 to 500 per user per month plus set-up | E6: 200 | F6: 500 | G6: =IF(E6="","",E6*FX) | H6: =IF(F6="","",F6*FX) | I6: S9 | J6: Third-party estimate.
A7: Vertafore AMS360 | B7: USA | C7: Subscription per user, quote only | D7: Listings from USD 99; agencies report USD 150 to 300 per user per month | E7: 150 | F7: 300 | G7: =IF(E7="","",E7*FX) | H7: =IF(F7="","",F7*FX) | I7: S6 | J7: Third-party estimate.
A8: Insly | B8: Estonia / EU, global | C8: Subscription per user, tiers | D8: USD 89 (Starter) to 199 (Professional) per user per month; EUR 149 basic | E8: 89 | F8: 199 | G8: =IF(E8="","",E8*FX) | H8: =IF(F8="","",F8*FX) | I8: S7 | J8: Third-party listings; Enterprise tier higher.
A9: Open GI | B9: UK | C9: Subscription per user | D9: From USD 70 per user per month | E9: 70 | F9: 70 | G9: =IF(E9="","",E9*FX) | H9: =IF(F9="","",F9*FX) | I9: S8 | J9: Third-party listing (starting price).
A10: Acturis | B10: UK, Europe | C10: Service fee by users and modules | D10: USD 2,000 to 25,000+ per month per firm; implementation USD 15,000 to 80,000 | G10: =IF(E10="","",E10*FX) | H10: =IF(F10="","",F10*FX) | I10: S8 | J10: Third-party estimate; per firm, not per user.
A11: Salesforce Financial Services Cloud | B11: USA, global | C11: Published per user, billed annually | D11: USD 325 to 350 per user per month | E11: 325 | F11: 350 | G11: =IF(E11="","",E11*FX) | H11: =IF(F11="","",F11*FX) | I11: S12 | J11: Published list price. CRM platform only: broking accounting, remittance and BIR reports must be built.
A12: Zoho CRM | B12: India, global | C12: Published per user | D12: USD 23 to 50 per user per month (Professional to Enterprise) | E12: 23 | F12: 50 | G12: =IF(E12="","",E12*FX) | H12: =IF(F12="","",F12*FX) | I12: S13 | J12: Published list price. Generic CRM floor price; no broking functions.
A13: Agiliux | B13: Singapore / Malaysia; live clients in the Philippines | C13: Modular; pay-as-you-sell for digital | D13: No public price | G13: =IF(E13="","",E13*FX) | H13: =IF(F13="","",F13*FX) | I13: S23 | J13: Main regional competitor. Price on request.
A14: Mzapp (Mindzen) | B14: India | C14: Quote only | D14: No public per-user price | G14: =IF(E14="","",E14*FX) | H14: =IF(F14="","",F14*FX) | I14: S24 | J14: Indian broker system; one listing shows a USD 200,000 starting price (basis unclear).
A15: Sibro | B15: India; markets to the Philippines | C15: Quote only | D15: No public price | G15: =IF(E15="","",E15*FX) | H15: =IF(F15="","",F15*FX) | I15: S25 | J15: Regional broker system.
A16: BrokerEdge (Damco) | B16: India / USA | C16: Quote only | D16: No public price | G16: =IF(E16="","",E16*FX) | H16: =IF(F16="","",F16*FX) | I16: S26 | J16: Feature-based pricing.
A17: Xceedance | B17: USA / India | C17: Services and platforms, quote only | D17: No public price | G17: =IF(E17="","",E17*FX) | H17: =IF(F17="","",F17*FX) | I17: S27 | J17: Builds agency and policy systems and offers operations services.
A18: ="BrokerVerse OOTB, "&Inputs!A28&" slab" | B18: Philippines | C18: Subscription per user, graduated slabs | D18: ="PHP "&TEXT(Inputs!E28,"#,##0")&" per user per month" | E18: =Inputs!E28/FX | F18: =Inputs!E28/FX | G18: =Inputs!E28 | H18: =Inputs!E28 | J18: Recommended price (this workbook).
A19: ="BrokerVerse OOTB, "&Inputs!A29&" slab" | B19: Philippines | C19: Subscription per user, graduated slabs | D19: ="PHP "&TEXT(Inputs!E29,"#,##0")&" per user per month" | E19: =Inputs!E29/FX | F19: =Inputs!E29/FX | G19: =Inputs!E29 | H19: =Inputs!E29 | J19: Recommended price (this workbook).
A20: ="BrokerVerse OOTB, "&Inputs!A30&" slab" | B20: Philippines | C20: Subscription per user, graduated slabs | D20: ="PHP "&TEXT(Inputs!E30,"#,##0")&" per user per month" | E20: =Inputs!E30/FX | F20: =Inputs!E30/FX | G20: =Inputs!E30 | H20: =Inputs!E30 | J20: Recommended price (this workbook).
A21: ="BrokerVerse OOTB, "&Inputs!A31&" slab" | B21: Philippines | C21: Subscription per user, graduated slabs | D21: ="PHP "&TEXT(Inputs!E31,"#,##0")&" per user per month" | E21: =Inputs!E31/FX | F21: =Inputs!E31/FX | G21: =Inputs!E31 | H21: =Inputs!E31 | J21: Recommended price (this workbook).
A23: Positioning summary
A24: Global broker systems (median of low/high, USD per user per month) | G24: =MEDIAN(E5:F7,E9:F9) | J24: Applied Epic, Sagitta, AMS360, Open GI (third-party estimates).
A25: BrokerVerse Small slab as % of that median | G25: =(Inputs!E28/FX)/G24
A26: BrokerVerse Small slab vs Zoho CRM Enterprise monthly (USD 50) | G26: =(Inputs!E28/FX)/50 | J26: A broking system with accounting and BIR reports sits above generic CRM and below global broker systems.
A28: Philippine IT services rates (basis for day rates)
A29: Item | B29: Market | C29: Unit | D29: Range as found | E29: Low (USD) | F29: High (USD) | G29: Low (PHP) | H29: High (PHP) | I29: Source ID | J29: Notes
A30: Mid-level developer | B30: Philippines | C30: per hour | D30: USD 30 to 50 | E30: 30 | F30: 50 | G30: =IF(E30="","",E30*FX) | H30: =IF(F30="","",F30*FX) | I30: S15 | J30: Outsourcing market rates; day = 8 hours.
A31: Senior developer | B31: Philippines | C31: per hour | D31: USD 50 to 75 | E31: 50 | F31: 75 | G31: =IF(E31="","",E31*FX) | H31: =IF(F31="","",F31*FX) | I31: S15
A32: IT consulting | B32: Philippines | C32: per hour | D32: USD 30 to 70; premium firms 70 to 150 | E32: 30 | F32: 70 | G32: =IF(E32="","",E32*FX) | H32: =IF(F32="","",F32*FX) | I32: S16
A33: Senior business analyst salary | B33: Philippines | C33: per month | D33: PHP 47,054 to 105,688 (average 70,519) | G33: =IF(E33="","",E33*FX) | H33: =IF(F33="","",F33*FX) | I33: S17 | J33: Employee cost, not vendor rate.
A34: Senior QA engineer salary | B34: Philippines | C34: per month | D34: PHP 54,000 to 100,000 (average 65,053) | G34: =IF(E34="","",E34*FX) | H34: =IF(F34="","",F34*FX) | I34: S18 | J34: Employee cost.
A35: IT project manager salary | B35: Philippines | C35: per month | D35: PHP 60,000 to 123,000 (average 64,826) | G35: =IF(E35="","",E35*FX) | H35: =IF(F35="","",F35*FX) | I35: S19 | J35: Employee cost.
A36: BrokerVerse blended day rate | B36: Philippines | C36: per day | D36: =TEXT(Blended,"#,##0")&" PHP" | G36: =IF(E36="","",E36*FX) | H36: =IF(F36="","",F36*FX) | J36: Recommended (Inputs).
A38: Philippine market facts used for tiers and affordability
A39: Licensed insurance brokers | B39: About 67 insurance brokers (IC key data, 2024 preliminary). A small, concentrated market: price for a few dozen realistic prospects. | I39: S1
A40: Largest brokers by commission earned, 2024 | B40: BDO Insurance and Reinsurance Brokers PHP 2,434 million; Marsh PHP 2,075 million; Aon PHP 2,047 million; Lockton PHP 712 million; PhilPacific PHP 598 million. | I40: S2
A41: Mid-market brokers, 2024 | B41: Rank 20 East West Insurance Brokerage PHP 98.0 million; rank 30 Moneyhero Insurance Brokerage PHP 55.2 million. | I41: S2
A42: Premiums produced by brokers, 2024 | B42: Aon was first at PHP 23.4 billion of premiums produced. | I42: S3
A43: Non-life insurers, 2025 | B43: Gross premiums written PHP 149.11 billion (excluding reinsurers); Pioneer PHP 20.70 billion (14%), Prudential Guarantee PHP 13.86 billion (9%), Malayan PHP 13.35 billion (9%). Pioneer first in net premiums written at PHP 6.90 billion. | I43: S4
A44: What the insurer ranking suggests | B44: The top 3 insurers hold about a third of gross premiums and the rest is spread over many mid-size insurers, so a broker places with many insurers: insurer set-up, remittance and reconciliation by insurer are core needs in every tier. | I44: S4
A45: IT budget norm | B45: Insurance IT spend 3.1% of revenue (Gartner, 2010); later benchmarks 4% to 7% for insurance. Used as the affordability band. | I45: S10, S11
A46: Broker licensing | B46: Minimum paid-up capital PHP 20 million for an insurance broker, PHP 50 million for insurance and reinsurance broker. | I46: S28

Sheet Sources
A1: Sources
A2: Accessed 03 October 2026. Some Insurance Commission and BusinessWorld pages could not be opened from the research network; their figures were read from search-engine extracts of the same documents and should be checked against the originals before external use.
A4: ID | B4: Title / publisher | C4: URL | D4: Accessed | E4: Used for
A5: S1 | B5: Insurance Commission: Key Data 2020-2024 (preliminary), Annex A | C5: https://www.insurance.gov.ph/wp-content/uploads/2026/02/Annex-A-Key-Data-2020-2024-Preliminary-Figures.pdf | D5: 03 Oct 2026 | E5: Number of licensed insurance brokers (about 67, 2024). Read from search extract.
A6: S2 | B6: Insurance Commission: Performance of Insurance Brokers, Commission Earned as of 31 December 2024 | C6: https://www.insurance.gov.ph/wp-content/uploads/2026/01/Performance-of-Insurance-Brokers-Commission-Earned-as-of-31-December-2024.pdf | D6: 03 Oct 2026 | E6: Broker ranking by commission earned. Read from search extract.
A7: S3 | B7: Insurance Commission: Performance of Insurance Brokers, Premiums Produced as of 31 December 2024 | C7: https://www.insurance.gov.ph/wp-content/uploads/2026/01/Performance-of-Insurance-Brokers-Premiums-Produced-as-of-31-December-2024.pdf | D7: 03 Oct 2026 | E7: Aon premiums produced. Read from search extract.
A8: S4 | B8: The Manila Times, "Growth on a sure footing", 31 August 2026; Insurance Commission non-life NPW and GPW rankings 2025 | C8: https://www.manilatimes.net/2026/08/31/supplements/growth-on-a-sure-footing/2414786 ; https://www.insurance.gov.ph/wp-content/uploads/2026/02/Performance-of-Non-Life-Insurance-Companies-NPW-as-of-31-December-2025-Based-on-Submitted-Unaudited-EQRSFS.pdf | D8: 03 Oct 2026 | E8: Non-life GPW 2025 and top insurers. Read from search extract.
A9: S5 | B9: Software Finder / All Insurance CRM: Applied Epic pricing | C9: https://softwarefinder.com/insurance-software/applied-epic ; https://allinsurancecrm.com/compare/applied-epic/ | D9: 03 Oct 2026 | E9: Applied Epic per-user estimate and set-up cost.
A10: S6 | B10: Unlocked CRM: How much does Vertafore AMS360 cost (2026) | C10: https://unlockedcrm.ai/blog/how-much-does-vertafore-ams360-really-cost | D10: 03 Oct 2026 | E10: AMS360 per-user estimate.
A11: S7 | B11: ITQlick / GetApp: Insly pricing | C11: https://www.itqlick.com/insly/pricing ; https://www.getapp.com/industries-software/a/insly-com/pricing/ | D11: 03 Oct 2026 | E11: Insly tiers.
A12: S8 | B12: Capterra: Open GI and Acturis pricing; Acturis FAQ | C12: https://www.capterra.com/p/79710/Transactor/ ; https://www.capterra.com/p/238790/Acturis/ ; https://www.acturis.com/faqs/how-much-does-it-cost/ | D12: 03 Oct 2026 | E12: Open GI starting price; Acturis monthly range and model.
A13: S9 | B13: WifiTalents / ZipDo: best insurance broking management software 2026 | C13: https://wifitalents.com/best/insurance-broking-management-software/ | D13: 03 Oct 2026 | E13: Sagitta and general price bands.
A14: S10 | B14: Gartner IT Key Metrics (2010) via Scribd | C14: https://www.scribd.com/document/670004267/Gartner-It-Spent | D14: 03 Oct 2026 | E14: Insurance IT spend 3.1% of revenue.
A15: S11 | B15: IT Budget Calculator: IT spending benchmarks by industry 2026 | C15: https://itbudgetcalculator.com/by-industry | D15: 03 Oct 2026 | E15: Insurance IT spend 4% to 7% (third-party benchmark).
... A34: S30 | B34: BrokerVerse documentation: Capacity and Performance; Go-live data set-up; docs/package/05_Delivery/Upload_Templates | C34: docs/architecture/06_BrokerVerse_Capacity_and_Performance.pdf ; docs/onboarding/GO_LIVE_DATA_SETUP.md | D34: 03 Oct 2026 | E34: Reference sizing and the standard upload templates.
