Workbook

Sheet Summary
A1: BrokerVerse OOTB: Test Execution Summary
A3: Product | B3: BrokerVerse OOTB (Philippine non-life insurance broking platform)
A4: Prepared by | B4: iorta TechNXT QA
A5: Execution dates | B5: 03 to 04 October 2026; new modules 04 October 2026; release verification on the merged release 04 October 2026
A6: Environment | B6: Production build on a fresh PostgreSQL database with the UAT data set (business date 04 October 2026, months May to October 2026)
A7: Evidence | B7: Backend regression run of 04 October 2026 (1035 tests in 97 files, all passed); IC and NPC compliance tests of the package B branch (36 tests, all passed); front-end unit tests (162 tests in 31 suites, all passed); end-to-end UAT cycle (371 steps); go-live rehearsal (51 checks); screen check of every menu screen for the administrator and six role users Release verification of 04 October 2026: UAT cycle of 433 steps, go-live rehearsal of 52 checks, data masking with verification on a copy of the UAT database, environment comparison.
A8: Status values | B8: Pass: result observed as expected. Fail: result differs; defect raised. Blocked: cannot be executed in this environment. Not Run: not executed in this cycle.
A10: Module | B10: Total | C10: Pass | D10: Fail | E10: Blocked | F10: Not Run | G10: Pass %
A11: Sign-in and security | B11: =COUNTIF('Test Cases'!$B$2:$B$630,A11) | C11: =COUNTIFS('Test Cases'!$B$2:$B$630,$A11,'Test Cases'!$M$2:$M$630,"Pass") | D11: =COUNTIFS('Test Cases'!$B$2:$B$630,$A11,'Test Cases'!$M$2:$M$630,"Fail") | E11: =COUNTIFS('Test Cases'!$B$2:$B$630,$A11,'Test Cases'!$M$2:$M$630,"Blocked") | F11: =COUNTIFS('Test Cases'!$B$2:$B$630,$A11,'Test Cases'!$M$2:$M$630,"Not Run") | G11: =IF(B11=0,0,C11/B11)
A12: User and role administration | B12: =COUNTIF('Test Cases'!$B$2:$B$630,A12) | C12: =COUNTIFS('Test Cases'!$B$2:$B$630,$A12,'Test Cases'!$M$2:$M$630,"Pass") | D12: =COUNTIFS('Test Cases'!$B$2:$B$630,$A12,'Test Cases'!$M$2:$M$630,"Fail") | E12: =COUNTIFS('Test Cases'!$B$2:$B$630,$A12,'Test Cases'!$M$2:$M$630,"Blocked") | F12: =COUNTIFS('Test Cases'!$B$2:$B$630,$A12,'Test Cases'!$M$2:$M$630,"Not Run") | G12: =IF(B12=0,0,C12/B12)
A13: Masters | B13: =COUNTIF('Test Cases'!$B$2:$B$630,A13) | C13: =COUNTIFS('Test Cases'!$B$2:$B$630,$A13,'Test Cases'!$M$2:$M$630,"Pass") | D13: =COUNTIFS('Test Cases'!$B$2:$B$630,$A13,'Test Cases'!$M$2:$M$630,"Fail") | E13: =COUNTIFS('Test Cases'!$B$2:$B$630,$A13,'Test Cases'!$M$2:$M$630,"Blocked") | F13: =COUNTIFS('Test Cases'!$B$2:$B$630,$A13,'Test Cases'!$M$2:$M$630,"Not Run") | G13: =IF(B13=0,0,C13/B13)
A14: Configuration and numbering | B14: =COUNTIF('Test Cases'!$B$2:$B$630,A14) | C14: =COUNTIFS('Test Cases'!$B$2:$B$630,$A14,'Test Cases'!$M$2:$M$630,"Pass") | D14: =COUNTIFS('Test Cases'!$B$2:$B$630,$A14,'Test Cases'!$M$2:$M$630,"Fail") | E14: =COUNTIFS('Test Cases'!$B$2:$B$630,$A14,'Test Cases'!$M$2:$M$630,"Blocked") | F14: =COUNTIFS('Test Cases'!$B$2:$B$630,$A14,'Test Cases'!$M$2:$M$630,"Not Run") | G14: =IF(B14=0,0,C14/B14)
A15: Product configurator | B15: =COUNTIF('Test Cases'!$B$2:$B$630,A15) | C15: =COUNTIFS('Test Cases'!$B$2:$B$630,$A15,'Test Cases'!$M$2:$M$630,"Pass") | D15: =COUNTIFS('Test Cases'!$B$2:$B$630,$A15,'Test Cases'!$M$2:$M$630,"Fail") | E15: =COUNTIFS('Test Cases'!$B$2:$B$630,$A15,'Test Cases'!$M$2:$M$630,"Blocked") | F15: =COUNTIFS('Test Cases'!$B$2:$B$630,$A15,'Test Cases'!$M$2:$M$630,"Not Run") | G15: =IF(B15=0,0,C15/B15)
A16: Go-live data load | B16: =COUNTIF('Test Cases'!$B$2:$B$630,A16) | C16: =COUNTIFS('Test Cases'!$B$2:$B$630,$A16,'Test Cases'!$M$2:$M$630,"Pass") | D16: =COUNTIFS('Test Cases'!$B$2:$B$630,$A16,'Test Cases'!$M$2:$M$630,"Fail") | E16: =COUNTIFS('Test Cases'!$B$2:$B$630,$A16,'Test Cases'!$M$2:$M$630,"Blocked") | F16: =COUNTIFS('Test Cases'!$B$2:$B$630,$A16,'Test Cases'!$M$2:$M$630,"Not Run") | G16: =IF(B16=0,0,C16/B16)
A17: Prospects and clients | B17: =COUNTIF('Test Cases'!$B$2:$B$630,A17) | C17: =COUNTIFS('Test Cases'!$B$2:$B$630,$A17,'Test Cases'!$M$2:$M$630,"Pass") | D17: =COUNTIFS('Test Cases'!$B$2:$B$630,$A17,'Test Cases'!$M$2:$M$630,"Fail") | E17: =COUNTIFS('Test Cases'!$B$2:$B$630,$A17,'Test Cases'!$M$2:$M$630,"Blocked") | F17: =COUNTIFS('Test Cases'!$B$2:$B$630,$A17,'Test Cases'!$M$2:$M$630,"Not Run") | G17: =IF(B17=0,0,C17/B17)
A18: Quick quote and compare insurers | B18: =COUNTIF('Test Cases'!$B$2:$B$630,A18) | C18: =COUNTIFS('Test Cases'!$B$2:$B$630,$A18,'Test Cases'!$M$2:$M$630,"Pass") | D18: =COUNTIFS('Test Cases'!$B$2:$B$630,$A18,'Test Cases'!$M$2:$M$630,"Fail") | E18: =COUNTIFS('Test Cases'!$B$2:$B$630,$A18,'Test Cases'!$M$2:$M$630,"Blocked") | F18: =COUNTIFS('Test Cases'!$B$2:$B$630,$A18,'Test Cases'!$M$2:$M$630,"Not Run") | G18: =IF(B18=0,0,C18/B18)
A19: Quotations and customer response | B19: =COUNTIF('Test Cases'!$B$2:$B$630,A19) | C19: =COUNTIFS('Test Cases'!$B$2:$B$630,$A19,'Test Cases'!$M$2:$M$630,"Pass") | D19: =COUNTIFS('Test Cases'!$B$2:$B$630,$A19,'Test Cases'!$M$2:$M$630,"Fail") | E19: =COUNTIFS('Test Cases'!$B$2:$B$630,$A19,'Test Cases'!$M$2:$M$630,"Blocked") | F19: =COUNTIFS('Test Cases'!$B$2:$B$630,$A19,'Test Cases'!$M$2:$M$630,"Not Run") | G19: =IF(B19=0,0,C19/B19)
A20: Request for quotation and placement | B20: =COUNTIF('Test Cases'!$B$2:$B$630,A20) | C20: =COUNTIFS('Test Cases'!$B$2:$B$630,$A20,'Test Cases'!$M$2:$M$630,"Pass") | D20: =COUNTIFS('Test Cases'!$B$2:$B$630,$A20,'Test Cases'!$M$2:$M$630,"Fail") | E20: =COUNTIFS('Test Cases'!$B$2:$B$630,$A20,'Test Cases'!$M$2:$M$630,"Blocked") | F20: =COUNTIFS('Test Cases'!$B$2:$B$630,$A20,'Test Cases'!$M$2:$M$630,"Not Run") | G20: =IF(B20=0,0,C20/B20)
A21: Policy issuance | B21: =COUNTIF('Test Cases'!$B$2:$B$630,A21) | C21: =COUNTIFS('Test Cases'!$B$2:$B$630,$A21,'Test Cases'!$M$2:$M$630,"Pass") | D21: =COUNTIFS('Test Cases'!$B$2:$B$630,$A21,'Test Cases'!$M$2:$M$630,"Fail") | E21: =COUNTIFS('Test Cases'!$B$2:$B$630,$A21,'Test Cases'!$M$2:$M$630,"Blocked") | F21: =COUNTIFS('Test Cases'!$B$2:$B$630,$A21,'Test Cases'!$M$2:$M$630,"Not Run") | G21: =IF(B21=0,0,C21/B21)
A22: Endorsements and cancellations | B22: =COUNTIF('Test Cases'!$B$2:$B$630,A22) | C22: =COUNTIFS('Test Cases'!$B$2:$B$630,$A22,'Test Cases'!$M$2:$M$630,"Pass") | D22: =COUNTIFS('Test Cases'!$B$2:$B$630,$A22,'Test Cases'!$M$2:$M$630,"Fail") | E22: =COUNTIFS('Test Cases'!$B$2:$B$630,$A22,'Test Cases'!$M$2:$M$630,"Blocked") | F22: =COUNTIFS('Test Cases'!$B$2:$B$630,$A22,'Test Cases'!$M$2:$M$630,"Not Run") | G22: =IF(B22=0,0,C22/B22)
... A61: Package G features | B61: =COUNTIF('Test Cases'!$B$2:$B$630,A61) | C61: =COUNTIFS('Test Cases'!$B$2:$B$630,$A61,'Test Cases'!$M$2:$M$630,"Pass") | D61: =COUNTIFS('Test Cases'!$B$2:$B$630,$A61,'Test Cases'!$M$2:$M$630,"Fail") | E61: =COUNTIFS('Test Cases'!$B$2:$B$630,$A61,'Test Cases'!$M$2:$M$630,"Blocked") | F61: =COUNTIFS('Test Cases'!$B$2:$B$630,$A61,'Test Cases'!$M$2:$M$630,"Not Run") | G61: =IF(B61=0,0,C61/B61)
A62: Total | B62: =SUM(B11:B61) | C62: =SUM(C11:C61) | D62: =SUM(D11:D61) | E62: =SUM(E11:E61) | F62: =SUM(F11:F61) | G62: =IF(B62=0,0,C62/B62)
A64: Test Type | B64: Total | C64: Pass | D64: Fail | E64: Blocked | F64: Not Run
A65: Functional | B65: =COUNTIF('Test Cases'!$F$2:$F$630,A65) | C65: =COUNTIFS('Test Cases'!$F$2:$F$630,$A65,'Test Cases'!$M$2:$M$630,"Pass") | D65: =COUNTIFS('Test Cases'!$F$2:$F$630,$A65,'Test Cases'!$M$2:$M$630,"Fail") | E65: =COUNTIFS('Test Cases'!$F$2:$F$630,$A65,'Test Cases'!$M$2:$M$630,"Blocked") | F65: =COUNTIFS('Test Cases'!$F$2:$F$630,$A65,'Test Cases'!$M$2:$M$630,"Not Run")
A66: Negative | B66: =COUNTIF('Test Cases'!$F$2:$F$630,A66) | C66: =COUNTIFS('Test Cases'!$F$2:$F$630,$A66,'Test Cases'!$M$2:$M$630,"Pass") | D66: =COUNTIFS('Test Cases'!$F$2:$F$630,$A66,'Test Cases'!$M$2:$M$630,"Fail") | E66: =COUNTIFS('Test Cases'!$F$2:$F$630,$A66,'Test Cases'!$M$2:$M$630,"Blocked") | F66: =COUNTIFS('Test Cases'!$F$2:$F$630,$A66,'Test Cases'!$M$2:$M$630,"Not Run")
A67: Validation | B67: =COUNTIF('Test Cases'!$F$2:$F$630,A67) | C67: =COUNTIFS('Test Cases'!$F$2:$F$630,$A67,'Test Cases'!$M$2:$M$630,"Pass") | D67: =COUNTIFS('Test Cases'!$F$2:$F$630,$A67,'Test Cases'!$M$2:$M$630,"Fail") | E67: =COUNTIFS('Test Cases'!$F$2:$F$630,$A67,'Test Cases'!$M$2:$M$630,"Blocked") | F67: =COUNTIFS('Test Cases'!$F$2:$F$630,$A67,'Test Cases'!$M$2:$M$630,"Not Run")
A68: Integration | B68: =COUNTIF('Test Cases'!$F$2:$F$630,A68) | C68: =COUNTIFS('Test Cases'!$F$2:$F$630,$A68,'Test Cases'!$M$2:$M$630,"Pass") | D68: =COUNTIFS('Test Cases'!$F$2:$F$630,$A68,'Test Cases'!$M$2:$M$630,"Fail") | E68: =COUNTIFS('Test Cases'!$F$2:$F$630,$A68,'Test Cases'!$M$2:$M$630,"Blocked") | F68: =COUNTIFS('Test Cases'!$F$2:$F$630,$A68,'Test Cases'!$M$2:$M$630,"Not Run")
A69: Role access | B69: =COUNTIF('Test Cases'!$F$2:$F$630,A69) | C69: =COUNTIFS('Test Cases'!$F$2:$F$630,$A69,'Test Cases'!$M$2:$M$630,"Pass") | D69: =COUNTIFS('Test Cases'!$F$2:$F$630,$A69,'Test Cases'!$M$2:$M$630,"Fail") | E69: =COUNTIFS('Test Cases'!$F$2:$F$630,$A69,'Test Cases'!$M$2:$M$630,"Blocked") | F69: =COUNTIFS('Test Cases'!$F$2:$F$630,$A69,'Test Cases'!$M$2:$M$630,"Not Run")
A70: Report | B70: =COUNTIF('Test Cases'!$F$2:$F$630,A70) | C70: =COUNTIFS('Test Cases'!$F$2:$F$630,$A70,'Test Cases'!$M$2:$M$630,"Pass") | D70: =COUNTIFS('Test Cases'!$F$2:$F$630,$A70,'Test Cases'!$M$2:$M$630,"Fail") | E70: =COUNTIFS('Test Cases'!$F$2:$F$630,$A70,'Test Cases'!$M$2:$M$630,"Blocked") | F70: =COUNTIFS('Test Cases'!$F$2:$F$630,$A70,'Test Cases'!$M$2:$M$630,"Not Run")
A71: Accounting | B71: =COUNTIF('Test Cases'!$F$2:$F$630,A71) | C71: =COUNTIFS('Test Cases'!$F$2:$F$630,$A71,'Test Cases'!$M$2:$M$630,"Pass") | D71: =COUNTIFS('Test Cases'!$F$2:$F$630,$A71,'Test Cases'!$M$2:$M$630,"Fail") | E71: =COUNTIFS('Test Cases'!$F$2:$F$630,$A71,'Test Cases'!$M$2:$M$630,"Blocked") | F71: =COUNTIFS('Test Cases'!$F$2:$F$630,$A71,'Test Cases'!$M$2:$M$630,"Not Run")
A73: Priority | B73: Total | C73: Pass | D73: Fail | E73: Blocked | F73: Not Run
A74: High | B74: =COUNTIF('Test Cases'!$G$2:$G$630,A74) | C74: =COUNTIFS('Test Cases'!$G$2:$G$630,$A74,'Test Cases'!$M$2:$M$630,"Pass") | D74: =COUNTIFS('Test Cases'!$G$2:$G$630,$A74,'Test Cases'!$M$2:$M$630,"Fail") | E74: =COUNTIFS('Test Cases'!$G$2:$G$630,$A74,'Test Cases'!$M$2:$M$630,"Blocked") | F74: =COUNTIFS('Test Cases'!$G$2:$G$630,$A74,'Test Cases'!$M$2:$M$630,"Not Run")
A75: Medium | B75: =COUNTIF('Test Cases'!$G$2:$G$630,A75) | C75: =COUNTIFS('Test Cases'!$G$2:$G$630,$A75,'Test Cases'!$M$2:$M$630,"Pass") | D75: =COUNTIFS('Test Cases'!$G$2:$G$630,$A75,'Test Cases'!$M$2:$M$630,"Fail") | E75: =COUNTIFS('Test Cases'!$G$2:$G$630,$A75,'Test Cases'!$M$2:$M$630,"Blocked") | F75: =COUNTIFS('Test Cases'!$G$2:$G$630,$A75,'Test Cases'!$M$2:$M$630,"Not Run")
A76: Low | B76: =COUNTIF('Test Cases'!$G$2:$G$630,A76) | C76: =COUNTIFS('Test Cases'!$G$2:$G$630,$A76,'Test Cases'!$M$2:$M$630,"Pass") | D76: =COUNTIFS('Test Cases'!$G$2:$G$630,$A76,'Test Cases'!$M$2:$M$630,"Fail") | E76: =COUNTIFS('Test Cases'!$G$2:$G$630,$A76,'Test Cases'!$M$2:$M$630,"Blocked") | F76: =COUNTIFS('Test Cases'!$G$2:$G$630,$A76,'Test Cases'!$M$2:$M$630,"Not Run")
A78: Defects and observations open | B78: =COUNTIF('Defects and Observations'!$E$2:$E$15,"Open")

Sheet Test Cases
A1: TC ID | B1: Module | C1: Sub-module / Screen | D1: Persona (role) | E1: Test Scenario | F1: Test Type | G1: Priority | H1: Pre-conditions | I1: Test Steps | J1: Test Data | K1: Expected Result | L1: Actual Result | M1: Status | N1: Defect ID | O1: Executed By | P1: Executed On | Q1: Remarks | R1: Evidence | S1: Regulatory reference
A2: BV-SEC-001 | B2: Sign-in and security | C2: Login | D2: System Administrator (BrokerVerse) | E2: Sign in with a valid user ID and password | F2: Functional | G2: High | H2: Application open at the Login page. User BrokerVerse is active. | I2: 1. Open the BrokerVerse URL in Chrome. 2. Enter the User ID and Password. 3. Click Login. | J2: User ID: BrokerVerse; Password: administrator password from the environment sheet | K2: Login succeeds and the Executive Dashboard opens. The user name shows in the header. The menu shows every top-level menu. | L2: As expected. | M2: Pass | O2: iorta TechNXT QA | P2: 03 October 2026 | R2: backend/test/core.test.js :: rejects a wrong password and accepts the admin [passed] Screen check /executive/dashboard: opened clean
A3: BV-SEC-002 | B3: Sign-in and security | C3: Login | D3: Any signed-in user | E3: Wrong password is refused with a generic message | F3: Negative | G3: High | H3: User maria.rivera is active. | I3: 1. Open the Login page. 2. Enter User ID maria.rivera and a wrong password. 3. Click Login. | J3: User ID: maria.rivera; Password: Wrong#Pass1 | K3: Message "Invalid username or password" is shown. The user stays on the Login page. The attempt is recorded in Sign-in history as "Wrong password". | L3: As expected. | M3: Pass | O3: iorta TechNXT QA | P3: 03 October 2026 | R3: backend/test/core.test.js :: rejects a wrong password and accepts the admin [passed] backend/test/security.test.js :: exposes sign-in history to administrators and to the user [passed]
A4: BV-SEC-003 | B4: Sign-in and security | C4: Login | D4: Any signed-in user | E4: Unknown user ID gets the same message as a wrong password | F4: Negative | G4: Medium | H4: None. | I4: 1. Open the Login page. 2. Enter a user ID that does not exist and any password. 3. Click Login. | J4: User ID: juan.notauser; Password: Any#Pass123 | K4: Message "Invalid username or password" (same wording as a wrong password, so the screen does not reveal whether the user exists). Sign-in history records "Unknown user ID". | L4: As expected. | M4: Pass | O4: iorta TechNXT QA | P4: 03 October 2026 | R4: backend/test/security.test.js :: rate limits sign-in per username and per IP (429 + Retry-After) and logs every attempt [passed] backend/test/security.test.js :: exposes sign-in history to administrators and to the user [passed]
A5: BV-SEC-004 | B5: Sign-in and security | C5: Login | D5: Any signed-in user | E5: Login with blank User ID and Password | F5: Validation | G5: Medium | H5: Login page open. | I5: 1. Leave User ID and Password empty. 2. Click Login. | J5: User ID: (blank); Password: (blank) | K5: Field messages "User ID is required" and "Password is required" are shown under the fields. No request is sent. | M5: Not Run | O5: iorta TechNXT QA | Q5: Sign-in screen render covered by the front-end test; field messages to be checked by hand in the next cycle. | R5: brokerverse/src/App.test.js :: renders the sign-in screen when signed out [passed]
A6: BV-SEC-005 | B6: Sign-in and security | C6: Lockout | D6: System Administrator (BrokerVerse) | E6: Account locks after the configured number of failed sign-ins | F6: Negative | G6: High | H6: Test user ana.buenaventura active. Master > Configuration > limits.max_login_attempts = 5. | I6: 1. Sign in as ana.buenaventura with a wrong password 5 times. 2. Sign in a 6th time with the correct password. 3. Sign in as BrokerVerse and open Master > Generals > User Management > User. 4. Find ana.buenaventura and check the status. | J6: User ID: ana.buenaventura; wrong password: Wrong#Pass1 (x5) | K6: Attempts 1 to 5 show "Invalid username or password". The 6th attempt shows "Account locked. Contact the administrator". The User list shows the user as Locked. | L6: As expected. | M6: Pass | O6: iorta TechNXT QA | P6: 03 October 2026 | Q6: Lock threshold read from limits.max_login_attempts (seeded 5). | R6: backend/test/security.test.js :: rate limits sign-in per username and per IP (429 + Retry-After) and logs every attempt [passed] backend/test/hardening.test.js :: unlocks a locked account and records it [passed]
A7: BV-SEC-006 | B7: Sign-in and security | C7: Lockout | D7: System Administrator (BrokerVerse) | E7: Administrator unlocks a locked user | F7: Functional | G7: High | H7: User ana.buenaventura is Locked (previous case). | I7: 1. Open Master > Generals > User Management > User. 2. Open the Account actions of ana.buenaventura. 3. Click Unlock and confirm. 4. Sign in as ana.buenaventura with the correct password. | J7: User: ana.buenaventura | K7: Confirmation "Unlock the account of ana.buenaventura? Failed sign-in attempts are cleared." Message "ana.buenaventura can sign in again." The user signs in. The unlock is in the Audit Trail. | L7: As expected. | M7: Pass | O7: iorta TechNXT QA | P7: 03 October 2026 | R7: backend/test/hardening.test.js :: unlocks a locked account and records it [passed] Screen check /master/generals/usermanagement/user: opened clean
A8: BV-SEC-007 | B8: Sign-in and security | C8: Lockout | D8: Any signed-in user | E8: Too many sign-in attempts from one address are throttled | F8: Negative | G8: Medium | H8: security.login_rate_limit = {"max":10,"windowSeconds":300}. | I8: 1. Submit 11 sign-in attempts for the same user ID within 5 minutes. 2. Read the message on the 11th attempt. | J8: User ID: paolo.dizon; Password: Wrong#Pass1 | K8: The 11th attempt is refused with "Too many attempts" (HTTP 429 with Retry-After). Every attempt is in Sign-in history. | L8: As expected. | M8: Pass | O8: iorta TechNXT QA | P8: 03 October 2026 | R8: backend/test/security.test.js :: rate limits sign-in per username and per IP (429 + Retry-After) and logs every attempt [passed]
A9: BV-SEC-008 | B9: Sign-in and security | C9: Password policy | D9: Any signed-in user | E9: Change password: rules shown and enforced | F9: Validation | G9: High | H9: Signed in as maria.rivera. Policy: 8 characters, upper, lower, digit, symbol, not one of last 5. | I9: 1. Open the user menu and click Change password. 2. Enter the current password. 3. Enter new password "brokerverse" in both new password fields. 4. Click Save and read the rules list. 5. Enter "Brokerverse#2026" in both fields and save. | J9: Weak: brokerverse; Strong: Brokerverse#2026 | K9: With the weak value the rules for upper-case, digit and symbol show "(not met yet)" and "The new password does not meet all the rules below." With the strong value: "Password changed. Your other sessions have been signed out." | L9: As expected. | M9: Pass | O9: iorta TechNXT QA | P9: 03 October 2026 | R9: backend/test/security.test.js :: enforces length, character classes and history on change-password [passed]
A10: BV-SEC-009 | B10: Sign-in and security | C10: Password policy | D10: Any signed-in user | E10: New password cannot repeat one of the last 5 passwords | F10: Negative | G10: Medium | H10: User has changed the password at least twice. | I10: 1. Open Change password. 2. Enter the current password. 3. Enter a password used two changes ago as the new password. 4. Click Save. | J10: Previous password: Brokerverse#2025 | K10: Change refused. Rule "Not one of your last 5 passwords" shows "(not met yet)". | L10: As expected. | M10: Pass | O10: iorta TechNXT QA | P10: 03 October 2026 | R10: backend/test/security.test.js :: enforces length, character classes and history on change-password [passed]
A11: BV-SEC-010 | B11: Sign-in and security | C11: Password policy | D11: Any signed-in user | E11: New password must differ from the current one and both entries must match | F11: Validation | G11: Low | H11: Signed in. | I11: 1. Open Change password. 2. Enter the current password as the new password and save. 3. Enter two different values in New password and Confirm new password and save. | J11: New: same as current; Confirm: Brokerverse#2027 vs Brokerverse#2028 | K11: Messages "The new password must differ from the current one." and "The two new passwords do not match." | L11: As expected. | M11: Pass | O11: iorta TechNXT QA | P11: 03 October 2026 | R11: backend/test/security.test.js :: enforces length, character classes and history on change-password [passed]
A12: BV-SEC-011 | B12: Sign-in and security | C12: Password policy | D12: System Administrator (BrokerVerse) | E12: New user created without a password gets a temporary password that must be changed | F12: Functional | G12: High | H12: Signed in as BrokerVerse. | I12: 1. Open Master > Generals > User Management > User and click Add User. 2. Fill the user details, role Claims, leave Password empty ("Leave empty for a temporary password"). 3. Click Save and copy the temporary password. 4. Sign in as the new user with the temporary password. | J12: Username: joy.macaraeg; Role: claims; Branch: HO | K12: The Temporary password dialog shows the password once. At first sign-in the user sees "You must choose a new password before you continue." and cannot open any screen until the password is changed. | L12: As expected. | M12: Pass | O12: iorta TechNXT QA | P12: 04 October 2026 | R12: backend/test/hardening.test.js :: generates a policy-compliant temporary password for a user created without one; it must be changed [passed] backend/test/core.test.js :: admin creates a persona user who can then sign in with that role [passed] UAT cycle 03-04 October 2026, phase Set-up (46 passed, 0 failed)
A13: BV-SEC-012 | B13: Sign-in and security | C13: Password policy | D13: Any signed-in user | E13: Expired password forces a change at sign-in | F13: Functional | G13: Medium | H13: security.password_max_age_days = 90. Test user whose password is older than 90 days. | I13: 1. Sign in with the user whose password is older than 90 days. | J13: User with password_changed_at older than 90 days | K13: Screen shows "Your password has expired. Choose a new one to continue." The user reaches the dashboard only after a compliant change. | L13: As expected. | M13: Pass | O13: iorta TechNXT QA | P13: 03 October 2026 | R13: backend/test/security.test.js :: flags mustChangePassword when the password is older than security.password_max_age_days [passed]
A14: BV-SEC-013 | B14: Sign-in and security | C14: Password reset | D14: Any signed-in user | E14: Forgot password with a verification code | F14: Functional | G14: Medium | H14: E-mail sending switched on and SMTP configured. | I14: 1. On the Login page click Forgot password?. 2. Enter the user ID and click Send code. 3. Open the e-mail and enter the verification code with a new password. 4. Click Reset password and sign in. | J14: User ID: liza.quiambao | K14: "If the account exists, a verification code has been sent." The code works once within 15 minutes; after the reset: "Your password has been reset. Sign in with the new password." | L14: Code handling confirmed in the backend run; delivery to a mailbox not possible: SMTP not configured in the test environment. | M14: Blocked | O14: iorta TechNXT QA | P14: 03 October 2026 | Q14: Re-test once the SMTP server is set. | R14: backend/test/configuration.test.js :: password reset e-mail and code lifetime follow security.reset_* settings [passed] backend/test/hardening.test.js :: stores reset codes hashed, keeps only the latest valid, withdraws a code after too many wrong entries [passed]
A15: BV-SEC-014 | B15: Sign-in and security | C15: Password reset | D15: Any signed-in user | E15: Reset code withdrawn after too many wrong entries | F15: Negative | G15: Medium | H15: A reset code has been requested. | I15: 1. Request a reset code. 2. Enter a wrong code 5 times. 3. Enter the correct code. | J15: security.reset_code_max_attempts = 5 | K15: After 5 wrong entries the code no longer works; a new code must be requested. Only the latest code is valid. | L15: As expected. | M15: Pass | O15: iorta TechNXT QA | P15: 03 October 2026 | R15: backend/test/hardening.test.js :: stores reset codes hashed, keeps only the latest valid, withdraws a code after too many wrong entries [passed]
A16: BV-SEC-015 | B16: Sign-in and security | C16: 2FA | D16: Any signed-in user | E16: Turn on two-step verification and sign in with the code | F16: Functional | G16: High | H16: Signed in as liza.quiambao. Authenticator app on a phone. | I16: 1. Open the user menu > Two-factor authentication and click Turn on. 2. Type the Setup key in the authenticator app. 3. Enter the 6-digit code and click Verify. 4. Sign out and sign in again with user ID and password. 5. Enter the code from the app. | J16: User: liza.quiambao; Issuer shown in app: BrokerVerse | K16: "Two-step verification is on." At the next sign-in the Two-step verification screen asks for the code; the dashboard opens after a valid code. | L16: As expected. | M16: Pass | O16: iorta TechNXT QA | P16: 03 October 2026 | R16: backend/test/security.test.js :: enrols, then requires the code at sign-in; disables with a code [passed] backend/test/security.test.js :: implements RFC 6238 / RFC 4226 correctly [passed]
A17: BV-SEC-016 | B17: Sign-in and security | C17: 2FA | D17: Any signed-in user | E17: Wrong two-step code is refused and checks are rate limited | F17: Negative | G17: High | H17: User with two-step verification on. | I17: 1. Sign in with user ID and password. 2. Enter 000000 as the code. 3. Repeat wrong codes several times. | J17: Code: 000000 | K17: "The code is not valid. Try the current code." Repeated wrong codes are throttled. Sign-in history records "Wrong authentication code". | L17: As expected. | M17: Pass | O17: iorta TechNXT QA | P17: 03 October 2026 | R17: backend/test/hardening.test.js :: rate limits two-factor code checks of a signed-in user [passed] backend/test/security.test.js :: exposes sign-in history to administrators and to the user [passed]
A18: BV-SEC-017 | B18: Sign-in and security | C18: 2FA | D18: System Administrator (BrokerVerse) | E18: Role that requires two-step verification must enrol before any screen | F18: Functional | G18: High | H18: Master > Configuration > Security: security.require_2fa_roles = ["accounting-manager"]. | I18: 1. Save the setting. 2. Sign in as teresa.villaroman (no two-step yet). | J18: Setting: security.require_2fa_roles = ["accounting-manager"] | K18: Screen "Set up two-step verification" with "Your role requires two-step verification. Set it up to continue." No menu screen opens until enrolment is done. "Turn off" is not offered to this user. | L18: As expected. | M18: Pass | O18: iorta TechNXT QA | P18: 03 October 2026 | R18: backend/test/security.test.js :: forces enrolment for roles in security.require_2fa_roles; administrators can reset a user's second factor [passed]
A19: BV-SEC-018 | B19: Sign-in and security | C19: 2FA | D19: System Administrator (BrokerVerse) | E19: Administrator turns off a user's two-step verification | F19: Functional | G19: Medium | H19: User liza.quiambao lost the phone. | I19: 1. Open Master > Generals > User Management > User. 2. Open Account actions of liza.quiambao. 3. Click Turn off two-step verification and confirm. | J19: User: liza.quiambao | K19: Message "Two-step verification turned off for liza.quiambao." The user signs in with password only. Action is in the Audit Trail. | L19: As expected. | M19: Pass | O19: iorta TechNXT QA | P19: 03 October 2026 | R19: backend/test/security.test.js :: forces enrolment for roles in security.require_2fa_roles; administrators can reset a user's second factor [passed]
A20: BV-SEC-019 | B20: Sign-in and security | C20: 2FA | D20: System Administrator (beatriz.lacson) | E20: A non-administrator user desk cannot reset 2FA or lock a System Administrator | F20: Negative | G20: High | H20: beatriz.lacson holds a user desk grant but is checked against the built-in administrator. | I20: 1. Open the User list. 2. Try to turn off two-step verification of BrokerVerse. 3. Try to lock BrokerVerse. 4. Try to change own roles. | J20: Target: BrokerVerse | K20: Each action is refused with a clear message. Nobody changes their own roles or status. | L20: As expected. | M20: Pass | O20: iorta TechNXT QA | P20: 03 October 2026 | R20: backend/test/hardening.test.js :: a non-administrator user desk cannot reset, lock or turn off 2FA of a System Administrator, nor change their own access [passed]
A21: BV-SEC-020 | B21: Sign-in and security | C21: Session | D21: Any signed-in user | E21: Idle session signs out after the configured minutes | F21: Functional | G21: Medium | H21: limits.session_idle_minutes = 30. | I21: 1. Sign in as maria.rivera. 2. Leave the browser idle for 29 minutes. 3. Read the warning. 4. Leave it idle 1 more minute. | J21: Idle time: 30 minutes | K21: At 29 minutes the banner "You will be signed out in one minute because of inactivity..." shows. At 30 minutes the user is returned to the Login page. | M21: Not Run | O21: iorta TechNXT QA | Q21: Timed test not run in this cycle; access token lifetime (30 minutes) confirmed in the backend run. | R21: backend/test/hardening.test.js :: defaults: 30-minute access tokens; development keeps its fallbacks [passed]
A22: BV-SEC-021 | B22: Sign-in and security | C22: Session | D22: System Administrator (BrokerVerse) | E22: Deactivating a user or changing the role ends access at once | F22: Functional | G22: High | H22: paolo.dizon signed in on another browser. | I22: 1. As BrokerVerse open the User list and deactivate paolo.dizon. 2. In the other browser click any menu. | J22: User: paolo.dizon | K22: The next request of paolo.dizon is refused and the browser returns to the Login page with the session ended. | L22: As expected. | M22: Pass | O22: iorta TechNXT QA | P22: 03 October 2026 | R22: backend/test/hardening.test.js :: ends access at once on deactivation and on role change; refresh issues a token with the new roles [passed]
A23: BV-SEC-022 | B23: Sign-in and security | C23: Session | D23: System Administrator (BrokerVerse) | E23: End every session of a user | F23: Functional | G23: Medium | H23: User signed in on two browsers. | I23: 1. Open Master > Generals > User Management > User Access Matrix. 2. Select the user and end all sessions. | J23: User: jose.bernardo | K23: Both browsers are signed out at the next request. | L23: As expected. | M23: Pass | O23: iorta TechNXT QA | P23: 03 October 2026 | R23: backend/test/access-control.test.js :: ends every session of a user [passed] Screen check /master/generals/usermanagement/access-matrix: opened clean
A24: BV-SEC-023 | B24: Sign-in and security | C24: Session | D24: Any signed-in user | E24: Reuse of an old refresh token revokes the sign-in | F24: Negative | G24: High | H24: Valid session. | I24: 1. Capture the refresh token after one renewal. 2. Present the old (rotated) refresh token again. | J24: Old refresh token | K24: The request is refused and the whole sign-in is revoked; Sign-in history shows "Session ended (token reuse)". | L24: As expected. | M24: Pass | O24: iorta TechNXT QA | P24: 03 October 2026 | R24: backend/test/hardening.test.js :: detects reuse of a rotated refresh token and revokes the whole sign-in [passed]
A25: BV-SEC-024 | B25: Sign-in and security | C25: Sign-in history | D25: System Administrator (BrokerVerse) | E25: Sign-in history visible to the administrator and the user | F25: Functional | G25: Low | H25: Some failed and successful sign-ins exist. | I25: 1. Open the User list and click Sign-in history for maria.rivera. 2. Sign in as maria.rivera and open own Sign-in history. | J25: User: maria.rivera | K25: Columns Date and time, Result, Detail, Method, IP address, Browser / device. Failed attempts show the reason. | L25: As expected. | M25: Pass | O25: iorta TechNXT QA | P25: 03 October 2026 | R25: backend/test/security.test.js :: exposes sign-in history to administrators and to the user [passed]
A26: BV-SEC-025 | B26: Sign-in and security | C26: API security | D26: System Administrator (BrokerVerse) | E26: Every non-public endpoint refuses a call without a token | F26: Negative | G26: High | H26: API reachable. | I26: 1. Call each non-public API route without the Authorization header. 2. Compare the public route list with the intended list. | J26: All registered routes | K26: Every non-public route answers 401. Only the intended public routes (sign-in, health, version, public settings, customer approval link, gateway callbacks) answer without a token. | L26: As expected. | M26: Pass | O26: iorta TechNXT QA | P26: 03 October 2026 | R26: backend/test/hardening.test.js :: every non-public route answers 401 without a token [passed] backend/test/hardening.test.js :: declares only the intended public routes [passed]
A27: BV-SEC-026 | B27: Sign-in and security | C27: API security | D27: System Administrator (BrokerVerse) | E27: Tokens other than HS256 and default secrets are refused | F27: Negative | G27: High | H27: Production configuration. | I27: 1. Present a token signed with another algorithm. 2. Start the API in production mode with a default secret, CORS * or a localhost base URL. | J27: alg=none token; JWT_SECRET=default | K27: Token refused. The API does not start in production with default secrets, CORS * or a localhost base URL. | L27: As expected. | M27: Pass | O27: iorta TechNXT QA | P27: 03 October 2026 | R27: backend/test/hardening.test.js :: accepts only HS256 tokens [passed] backend/test/hardening.test.js :: refuses missing or default secrets, CORS * and a localhost base URL in production only [passed]
A28: BV-SEC-027 | B28: Sign-in and security | C28: API security | D28: System Administrator (BrokerVerse) | E28: Injection probes in search and file fields | F28: Negative | G28: High | H28: Signed in. | I28: 1. Search a list with ' OR 1=1 -- and <script>alert(1)</script>. 2. Upload an .html file renamed .pdf as a document. 3. Export a list containing a cell starting with =HYPERLINK(. | J28: Search: ' OR 1=1 --; File: test.html renamed test.pdf; Cell: =HYPERLINK("x") | K28: Search returns no extra rows and no error page. The upload is refused (type read from the file signature). Exported CSV cells starting with = + - @ are guarded. | L28: As expected. | M28: Pass | O28: iorta TechNXT QA | P28: 03 October 2026 | R28: backend/test/hardening.test.js :: detects file types from their signature, not from the name or the browser [passed] backend/test/hardening.test.js :: refuses HTML, scripts and unknown binaries; stores the detected type [passed] backend/test/configuration.test.js :: CSV cells written by any module are guarded against spreadsheet formulas [passed]
A29: BV-SEC-028 | B29: Sign-in and security | C29: API security | D29: System Administrator (BrokerVerse) | E29: Security headers and request id on every response | F29: Functional | G29: Medium | H29: API reachable. | I29: 1. Open browser developer tools > Network. 2. Load any screen and inspect a response header set. | J29: Any API call | K29: Responses carry the standard security headers (X-Content-Type-Options, X-Frame-Options, Strict-Transport-Security, Content-Security-Policy) and x-request-id. Errors show a generic message with the request id. | L29: As expected. | M29: Pass | O29: iorta TechNXT QA | P29: 03 October 2026 | R29: backend/test/security.test.js :: adds x-request-id to every response, echoes a caller id and returns it in error bodies [passed] backend/test/hardening.test.js :: answers 500 with a generic message and the request id; client errors keep their message [passed]
A30: BV-SEC-029 | B30: Sign-in and security | C30: API security | D30: System Administrator (BrokerVerse) | E30: Upload size limit and global rate limit | F30: Negative | G30: Medium | H30: UPLOAD_MAX_MB set. | I30: 1. Upload a file larger than UPLOAD_MAX_MB. 2. Send API calls above the per-user rate limit. | J30: File: 30 MB PDF | K30: Large file refused with 413. Calls above the limit answer 429. | L30: As expected. | M30: Pass | O30: iorta TechNXT QA | P30: 03 October 2026 | R30: backend/test/hardening.test.js :: refuses uploads above UPLOAD_MAX_MB with 413 [passed] backend/test/hardening.test.js :: applies a configurable global API rate limit per user [passed]
A31: BV-SEC-030 | B31: Sign-in and security | C31: API security | D31: System Administrator (BrokerVerse) | E31: Tokens and cookies never written to the server log | F31: Functional | G31: Medium | H31: Server log available. | I31: 1. Sign in and use several screens. 2. Open the server log and search for "Bearer" and the refresh token value. | J31: Server log of the test session | K31: No bearer token, cookie or signed link token appears in the log. | L31: As expected. | M31: Pass | O31: iorta TechNXT QA | P31: 03 October 2026 | R31: backend/test/hardening.test.js :: never writes bearer tokens, cookies or link tokens to the log [passed]
A32: BV-SEC-031 | B32: Sign-in and security | C32: Documents | D32: Any signed-in user | E32: Document links open only with a session or a signed, unexpired link | F32: Negative | G32: High | H32: A policy document is stored. | I32: 1. Copy the document link from a policy. 2. Open it in a private window after the signature expiry. 3. Open a non-PDF attachment. | J32: Policy schedule PDF; claim photo | K32: Expired or unsigned link is refused. Non-image, non-PDF files download as attachments. | L32: As expected. | M32: Pass | O32: iorta TechNXT QA | P32: 03 October 2026 | R32: backend/test/hardening.test.js :: serves objects only with a bearer header or a signed, unexpired link, with safe headers [passed] backend/test/hardening.test.js :: sends non-image, non-PDF files as attachments; legacy unsafe types as octet-stream [passed]
A33: BV-SEC-032 | B33: Sign-in and security | C33: Dependency audit | D33: System Administrator (BrokerVerse) | E33: Dependency audit of the release build | F33: Functional | G33: High | H33: Release build of backend and front end. | I33: 1. Run npm audit --omit=dev in backend/. 2. Run npm audit --omit=dev in brokerverse/. | J33: Release lock files of 03 October 2026 | K33: No known vulnerability in runtime dependencies. | L33: Backend: 0 vulnerabilities. Front end runtime: 2 moderate findings in react-router (open redirect advisory); the fix needs a major upgrade. | M33: Fail | N33: BV-DEF-001 | O33: iorta TechNXT QA | P33: 03 October 2026
A34: BV-SEC-033 | B34: Sign-in and security | C34: Data protection | D34: System Administrator (BrokerVerse) | E34: Personal data encrypted at application level | F34: Functional | G34: Medium | H34: Database access for the tester. | I34: 1. Create a client with TIN, mobile and ID number. 2. Query the clients table directly. 3. Query the users table for TOTP secrets. | J34: Client: Rowena Bautista; TIN 214-558-902-000 | K34: Sensitive personal fields are stored encrypted. | L34: TIN, government ID numbers (clients, signatories, beneficial owners) and bank account numbers are stored as pii:1: cipher text (PII_ENCRYPTION_KEY); the masking run of 04 October 2026 read them in clear and found no original value left. | M34: Pass | O34: iorta TechNXT QA | P34: 04 October 2026 | Q34: BV-DEF-003 closed: package B merged into the release on 04 October 2026. | R34: backend/test/personal-data-protection.test.js :: stores TIN and government ID numbers encrypted with a blind index [passed]; masking run of 04 October 2026 (identifier check)
A35: BV-SEC-034 | B35: Sign-in and security | C35: Data privacy | D35: Operations / Client Service (ana.buenaventura) | E35: Record client consent under the Data Privacy Act | F35: Functional | G35: Medium | H35: Client record open. | I35: 1. Open Operations > Clients and open a client. 2. Look for a consent capture section and record consent with date and purpose. | J35: Client: any retail client | K35: Consent with date, purpose and channel can be recorded and is shown on the client. | L35: Client Data privacy tab and the privacy API record consent per purpose (processing, marketing, sharing) with channel, evidence and notice version; the consent is shown on the client with its history. Re-test: consent for marketing recorded on CL-2026-00068 (201) and read back. | M35: Pass | N35: BV-DEF-002 (closed) | O35: iorta TechNXT QA | P35: 03 October 2026 | Q35: Re-test of 03 October 2026 after the fix, fresh database with the UAT data set.
A36: BV-SEC-035 | B36: Sign-in and security | C36: Data privacy | D36: System Administrator (BrokerVerse) | E36: Log and answer a data subject access or erasure request | F36: Functional | G36: Medium | H36: Client asks for a copy of personal data. | I36: 1. Look for a data subject request register under Master. 2. Look for an anonymise action on a closed client. | J36: Client: any | K36: Request can be logged and tracked; an inactive client can be anonymised. | L36: Master > Data Privacy: request DSR-2026-00001 logged, due 15 days after receipt (18/10/2026); personal data export produced; anonymise dry run refuses a client with a policy in force and lists the reasons. | M36: Pass | N36: BV-DEF-002 (closed) | O36: iorta TechNXT QA | P36: 03 October 2026 | Q36: Re-test of 03 October 2026 after the fix, fresh database with the UAT data set.
A37: BV-USR-001 | B37: User and role administration | C37: User | D37: System Administrator (BrokerVerse) | E37: Create a user per broker role | F37: Functional | G37: High | H37: Signed in as BrokerVerse. | I37: 1. Open Master > Generals > User Management > User. 2. Click Add User. 3. Enter username, first and last name, e-mail, branch HO, designation and one role. 4. Click Save. 5. Repeat for each persona. | J37: maria.rivera (sales), jose.bernardo (processing), ana.buenaventura (operations), carlo.estrada (claims), liza.quiambao (accounting), teresa.villaroman (accounting-manager); e-mail <user>@example.ph | K37: Each user is saved with the role and listed. A temporary password is shown once for each. | L37: 12 persona users created in the cycle and signed in with their roles. | M37: Pass | O37: iorta TechNXT QA | P37: 04 October 2026 | R37: backend/test/user-access.test.js :: lists, creates and locks users, and reads the audit trail [passed] backend/test/core.test.js :: admin creates a persona user who can then sign in with that role [passed] UAT cycle 03-04 October 2026, phase Set-up (46 passed, 0 failed) Screen check /master/generals/usermanagement/user: opened clean
A38: BV-USR-002 | B38: User and role administration | C38: User | D38: System Administrator (BrokerVerse) | E38: Required fields and e-mail format on Add User | F38: Validation | G38: Medium | H38: Add User form open. | I38: 1. Click Save with all fields empty. 2. Enter e-mail "maria.rivera@" and save. | J38: E-mail: maria.rivera@ | K38: Each required field shows its message. Invalid e-mail is refused. Nothing is saved. | L38: As expected. | M38: Pass | O38: iorta TechNXT QA | P38: 03 October 2026 | R38: backend/test/role-access.test.js :: every create endpoint of the walk answers 400 "Validation failed" with one readable message per field [passed]
A39: BV-USR-003 | B39: User and role administration | C39: User | D39: System Administrator (BrokerVerse) | E39: Duplicate username refused | F39: Negative | G39: Medium | H39: User maria.rivera exists. | I39: 1. Click Add User. 2. Enter username maria.rivera with valid other details. 3. Click Save. | J39: Username: maria.rivera | K39: Save refused with a duplicate username message. | L39: As expected. | M39: Pass | O39: iorta TechNXT QA | P39: 03 October 2026 | Q39: Unique username enforced by the user store. | R39: backend/test/user-access.test.js :: lists, creates and locks users, and reads the audit trail [passed]
A40: BV-USR-004 | B40: User and role administration | C40: User | D40: System Administrator (beatriz.lacson) | E40: Only a System Administrator grants the administrator role | F40: Negative | G40: High | H40: Signed in as a user desk user without System Administrator role. | I40: 1. Open a user and add role system-admin. 2. Click Save. | J40: Target role: system-admin | K40: Save refused. The role list stays unchanged. | L40: As expected. | M40: Pass | O40: iorta TechNXT QA | P40: 03 October 2026 | R40: backend/test/user-access.test.js :: cannot grant the System Administrator role [passed] backend/test/hardening.test.js :: only a System Administrator grants the administrator role or edits it; nobody changes their own roles or status [passed]
A41: BV-USR-005 | B41: User and role administration | C41: User | D41: Any signed-in user | E41: A user cannot change own roles or status | F41: Negative | G41: High | H41: Signed in as beatriz.lacson. | I41: 1. Open own user record. 2. Change the role or status and save. | J41: Own record | K41: Change refused. | L41: As expected. | M41: Pass | O41: iorta TechNXT QA | P41: 03 October 2026 | R41: backend/test/user-access.test.js :: cannot change its own roles [passed]
A42: BV-USR-006 | B42: User and role administration | C42: User | D42: System Administrator (BrokerVerse) | E42: Administrator resets a user password | F42: Functional | G42: Medium | H42: User carlo.estrada active and signed in elsewhere. | I42: 1. Open the User list. 2. Open Account actions of carlo.estrada and reset the password leaving it empty. | J42: User: carlo.estrada | K42: Temporary password shown once. Existing sessions of the user end. User must change the password at the next sign-in. | L42: As expected. | M42: Pass | O42: iorta TechNXT QA | P42: 03 October 2026 | R42: backend/test/hardening.test.js :: administrator reset without a password returns a temporary one once and ends the user's sessions [passed]
A43: BV-USR-007 | B43: User and role administration | C43: Role | D43: System Administrator (BrokerVerse) | E43: Seeded roles are the broker roles plus System Administrator | F43: Functional | G43: Medium | H43: Fresh database. | I43: 1. Open Master > Generals > User Management > Role. | J43: None | K43: Roles listed: system-admin, sales, processing, operations, claims, accounting, accounting-manager. No legacy role codes. | L43: As expected. | M43: Pass | O43: iorta TechNXT QA | P43: 03 October 2026 | R43: backend/test/user-access.test.js :: the seeded roles are the broker roles and the System Administrator [passed] backend/test/broker-roles-migration.test.js :: leaves no old role code anywhere and is idempotent [passed] Screen check /master/generals/usermanagement/role: opened clean
A44: BV-USR-008 | B44: User and role administration | C44: Role permissions | D44: System Administrator (BrokerVerse) | E44: Change a role permission; the change waits for a second approver | F44: Functional | G44: High | H44: Two administrators. | I44: 1. Open Master > Generals > User Management > Role Permissions. 2. Add read:reports to role claims and save. 3. Check that the change is pending. 4. Sign in as the second administrator and approve it on Master > Finance > Configuration Approvals. | J44: Role: claims; permission read:reports | K44: Change shows as pending until a different user approves. After approval the users of the role receive renewed tokens with the new permission. | L44: As expected. | M44: Pass | O44: iorta TechNXT QA | P44: 03 October 2026 | R44: backend/test/configuration-controls.test.js :: a role change waits for a different approver [passed] backend/test/hardening.test.js :: role permission changes renew the tokens of the role's users [passed] Screen check /master/generals/usermanagement/role-permissions: opened clean Screen check /master/finance/configuration-approvals: opened clean
A45: BV-USR-009 | B45: User and role administration | C45: Authority matrix | D45: System Administrator (BrokerVerse) | E45: Approval limits per role and transaction type | F45: Functional | G45: High | H45: Seeded authority matrix. | I45: 1. Open Master > Generals > User Management > Authority Matrix. 2. Read the default limits. 3. Raise the journal voucher limit of accounting to PHP 1,000,000.00 and save. 4. Approve as the second administrator. | J45: Journal voucher limit: PHP 1,000,000.00 | K45: Matrix shows transaction types down and roles across. The new limit applies only after another administrator approves. | L45: As expected. | M45: Pass | O45: iorta TechNXT QA | P45: 03 October 2026 | R45: backend/test/access-control.test.js :: ships default limits per role and shows them types down, roles across [passed] backend/test/access-control.test.js :: a new limit applies only after another administrator approves it [passed] Screen check /master/generals/usermanagement/authority-matrix: opened clean
A46: BV-USR-010 | B46: User and role administration | C46: Authority matrix | D46: Accounting Manager (teresa.villaroman) | E46: Approval above the approver limit is refused | F46: Negative | G46: High | H46: Journal voucher of PHP 3,500,000.00 pending; accounting limit lower than that. | I46: 1. Sign in as liza.quiambao's colleague nestor.pangilinan (accounting). 2. Try to approve the voucher. 3. Sign in as teresa.villaroman and approve. | J46: JV: go-live opening balance of BDO-OPS, PHP 3,500,000.00 | K46: Accounting approver is refused (above limit). The Accounting Manager approves within limit. | L46: As expected. | M46: Pass | O46: iorta TechNXT QA | P46: 04 October 2026 | R46: backend/test/access-control.test.js :: refuses an approval above the approver's limit and allows it within [passed] UAT cycle 03-04 October 2026, phase Reconciliation: bank and insurer statements (10 passed, 0 failed)
A47: BV-USR-011 | B47: User and role administration | C47: Delegations | D47: System Administrator (BrokerVerse) | E47: Delegate approval authority for a date range | F47: Functional | G47: Medium | H47: teresa.villaroman on leave 05 to 09 October 2026. | I47: 1. Open Master > Generals > User Management > Delegations. 2. Add a delegation from teresa.villaroman to ramon.almario for journal vouchers, 05 to 09 October 2026. 3. Save. | J47: Delegator: teresa.villaroman; Delegate: ramon.almario | K47: Within the dates ramon.almario approves with the delegator's authority for the listed types only. | L47: As expected. | M47: Pass | O47: iorta TechNXT QA | P47: 03 October 2026 | R47: backend/test/access-control.test.js :: a delegation lends the delegator's authority for its types and dates [passed] Screen check /master/generals/usermanagement/delegations: opened clean
A48: BV-USR-012 | B48: User and role administration | C48: Segregation of duties | D48: System Administrator (BrokerVerse) | E48: Conflicting roles blocked on one user | F48: Negative | G48: High | H48: SoD rules seeded. | I48: 1. Open Master > Generals > User Management > Segregation of Duties and read the rules. 2. Open user liza.quiambao and add a role that conflicts with accounting (blocking rule). 3. Save. | J48: User: liza.quiambao | K48: Blocking conflicts refused; warning-level conflicts saved with a warning. | L48: As expected. | M48: Pass | O48: iorta TechNXT QA | P48: 03 October 2026 | R48: backend/test/access-control.test.js :: blocks roles one person may not hold together and warns on the others [passed] Screen check /master/generals/usermanagement/segregation-of-duties: opened clean
A49: BV-USR-013 | B49: User and role administration | C49: Access reviews | D49: System Administrator (BrokerVerse) | E49: Periodic access review closes when every user is decided | F49: Functional | G49: Medium | H49: Active users exist. | I49: 1. Open Master > Generals > User Management > Access Reviews. 2. Start a review. 3. Keep all users except one; revoke paolo.dizon. 4. Complete the review. | J49: Revoked: paolo.dizon | K49: Every active user is listed. The revoked user is deactivated. The review closes when all are decided. | L49: As expected. | M49: Pass | O49: iorta TechNXT QA | P49: 03 October 2026 | R49: backend/test/access-control.test.js :: reviews every active user; a revoked user is deactivated and the review closes when all are decided [passed] Screen check /master/generals/usermanagement/access-reviews: opened clean
A50: BV-USR-014 | B50: User and role administration | C50: User Access Matrix | D50: System Administrator (BrokerVerse) | E50: User access report downloads | F50: Report | G50: Low | H50: Users exist. | I50: 1. Open Master > Generals > User Management > User Access Matrix. 2. Click Download. | J50: None | K50: Every user listed with roles, last sign-in and status; file downloads. | L50: As expected. | M50: Pass | O50: iorta TechNXT QA | P50: 03 October 2026 | R50: backend/test/access-control.test.js :: lists every user with roles and sign-in facts, and downloads it [passed] Screen check /master/generals/usermanagement/access-matrix: opened clean
A51: BV-USR-015 | B51: User and role administration | C51: Dormant accounts | D51: System Administrator (BrokerVerse) | E51: Dormant accounts deactivated, administrator kept | F51: Functional | G51: Low | H51: A user with no sign-in for the dormant period. | I51: 1. Open Master > Schedules. 2. Run the dormant account job. | J51: User last signed in more than the dormant period ago | K51: The dormant user is deactivated; the built-in administrator is never deactivated. | L51: As expected. | M51: Pass | O51: iorta TechNXT QA | P51: 03 October 2026 | R51: backend/test/access-control.test.js :: deactivates accounts with no sign-in for the dormant period, never the built-in administrator [passed]
... A70: BV-MST-018 | B70: Masters | C70: Taxation | D70: Accounting Officer (liza.quiambao) | E70: Tax codes master holds the PH codes with ATCs | F70: Accounting | G70: High | H70: Seeded tax codes. | I70: 1. Open Master > Finance > Taxation. 2. Find VAT12-OUT and WC139. 3. Edit the description of one code and save. | J70: VAT12-OUT; WC139 | K70: 26 tax codes, all active, with ATC; edit saved and the linked configuration key stays in step. | L70: As expected. | M70: Pass | O70: iorta TechNXT QA | P70: 04 October 2026 | R70: backend/test/period-end.test.js :: tax codes master holds the PH codes with ATCs and is editable [passed] backend/test/masters.test.js :: taxation records linked to a setting keep the configuration key in step [passed] UAT cycle 03-04 October 2026, phase Set-up (46 passed, 0 failed) Screen check /master/finance/taxation: opened clean
A71: BV-MST-019 | B71: Masters | C71: Premium taxes | D71: Accounting Officer (liza.quiambao) | E71: Premium taxes and LGU rates maintained by Accounting | F71: Accounting | G71: High | H71: Seeded rules and Metro Manila LGU rates. | I71: 1. Open Master > Finance > Premium Taxes & LGU Rates. 2. Read VAT, DST, FST and LGT rules. 3. Change the Makati LGT rate and save. 4. As maria.rivera try the same change. | J71: Makati LGT 0.75% | K71: Accounting saves; Sales is refused. Charges calculator shows the effect for a premium at a location. | L71: Rules and LGU rates saved by Accounting; Sales refused. Signed in as Accounting, the screen loads with no refused request and the product list of the charges calculator is filled. | M71: Pass | N71: BV-DEF-006 (closed) | O71: iorta TechNXT QA | P71: 03 October 2026 | Q71: Re-test of 03 October 2026 after the fix, fresh database with the UAT data set. | R71: backend/test/premium-charges.test.js :: lets Accounting maintain rules and LGU rates; Sales cannot [passed] backend/test/premium-charges.test.js :: lists the seeded rules and Metro Manila LGU rates [passed] backend/test/premium-charges.test.js :: calculates the charges of a product premium at a location [passed] Screen check /master/finance/premium-taxes: opened clean
A72: BV-MST-020 | B72: Masters | C72: Premium taxes | D72: Processing Team (jose.bernardo) | E72: DST, VAT, FST and LGT computed on a fire premium | F72: Validation | G72: High | H72: Fire product; location Makati. | I72: 1. Create a fire quotation for net premium PHP 22,000.00 in Makati. 2. Read the premium breakdown. | J72: Net PHP 22,000.00 | K72: DST charged per PHP 4.00 or part (rounded up), VAT on non-property, FST on fire, LGT at the LGU rate; each line rounded to 2 decimals and totalled. | L72: As expected. | M72: Pass | O72: iorta TechNXT QA | P72: 03 October 2026 | R72: backend/test/premium-charges.test.js :: prices VAT, DST per P4.00, FST on fire and LGT for a fire premium [passed] backend/test/premium-charges.test.js :: charges DST on every P4.00 or fractional part (round up) or proportionally (prorate) [passed] backend/test/premium-charges.test.js :: rounds every amount to 2 decimals half away from zero and totals the rounded lines [passed]
A73: BV-MST-021 | B73: Masters | C73: Rounding | D73: Accounting Officer (liza.quiambao) | E73: Money rounding half away from zero | F73: Validation | G73: Medium | H73: Any premium screen. | I73: 1. Enter amounts that end in .005 and check the displayed totals. | J73: 1.005 -> 1.01; 2.675 -> 2.68; -1.005 -> -1.01; 1234567.895 -> 1,234,567.90 | K73: Amounts round half away from zero to 2 decimals; empty input is 0. | L73: As expected. | M73: Pass | O73: iorta TechNXT QA | P73: 03 October 2026 | R73: backend/test/configuration.test.js :: round2(1.005) = 1.01 [passed] backend/test/configuration.test.js :: round2(2.675) = 2.68 [passed] backend/test/configuration.test.js :: treats empty and invalid input as 0 (never -0 or NaN) [passed]
A74: BV-CFG-001 | B74: Configuration and numbering | C74: Configuration | D74: System Administrator (BrokerVerse) | E74: Every setting is listed with a label and group | F74: Functional | G74: Medium | H74: Fresh database. | I74: 1. Open Master > Configuration. 2. Browse each group (Security, Limits, Accounting, Sales, Notification). | J74: None | K74: Every key read by the application is present with a label and group; values match the seeded defaults. | L74: As expected. | M74: Pass | O74: iorta TechNXT QA | P74: 03 October 2026 | R74: backend/test/configuration.test.js :: every key read by the code is seeded, with a label and a group (so Master > Configuration shows it) [passed] backend/test/configuration.test.js :: scripts/check-settings.js: every key read in code exists and only documented keys are left unread [passed] Screen check /master/configuration/settings: opened clean
A75: BV-CFG-002 | B75: Configuration and numbering | C75: Configuration | D75: System Administrator (BrokerVerse) | E75: Change a setting; it is saved and audited | F75: Functional | G75: High | H75: Signed in as BrokerVerse. | I75: 1. Open Master > Configuration > Limits. 2. Change limits.session_idle_minutes from 30 to 20 and save. 3. Open Master > Audit Trail and filter on today. | J75: limits.session_idle_minutes: 30 -> 20 | K75: Setting saved. Audit Trail shows the change with before and after values and user. | L75: As expected. | M75: Pass | O75: iorta TechNXT QA | P75: 03 October 2026 | R75: backend/test/core.test.js :: settings are read from the database and editable by admins [passed] backend/test/core.test.js :: writes an audit trail [passed]
A76: BV-CFG-003 | B76: Configuration and numbering | C76: Configuration | D76: System Administrator (BrokerVerse) | E76: Invalid setting value refused | F76: Negative | G76: Medium | H76: Signed in as BrokerVerse. | I76: 1. Enter "abc" for a number setting and save. 2. As maria.rivera try to change a setting. | J76: limits.max_login_attempts = abc | K76: Invalid value refused; unauthorised user refused. | L76: As expected. | M76: Pass | O76: iorta TechNXT QA | P76: 03 October 2026 | R76: backend/test/system-settings.test.js :: rejects invalid values and unauthorised users [passed]
A77: BV-CFG-004 | B77: Configuration and numbering | C77: Configuration | D77: System Administrator (BrokerVerse) | E77: Settings change on one server is picked up by the others | F77: Integration | G77: Low | H77: Two API instances. | I77: 1. Change a setting on instance A. 2. Read it from instance B after the version check interval. | J77: Any setting | K77: Instance B uses the new value without a restart. | L77: As expected. | M77: Pass | O77: iorta TechNXT QA | P77: 03 October 2026 | R77: backend/test/operations.test.js :: picks up a setting changed by another instance at the next version check [passed]
A78: BV-CFG-005 | B78: Configuration and numbering | C78: Time zone | D78: System Administrator (BrokerVerse) | E78: Business date is Manila time, not UTC | F78: Validation | G78: High | H78: general.timezone = Asia/Manila. | I78: 1. Issue a policy at 00:30 Manila on 01 October 2026. 2. Open the Executive Dashboard "This Month". | J78: Issue time 00:30 Manila (16:30 UTC previous day) | K78: The policy counts in October. Business dates and numbering use the Manila date. | L78: As expected. | M78: Pass | O78: iorta TechNXT QA | P78: 03 October 2026 | R78: backend/test/configuration.test.js :: is Manila time near midnight UTC, not the UTC date [passed] backend/test/dashboard.test.js :: "This Month" runs from the 1st of the Manila month; a policy at 00:30 Manila on the 1st counts, 23:30 the day before does not [passed] backend/test/operations.test.js :: defaults business-date columns to the Manila date (numbering_business_date) [passed]
A79: BV-CFG-006 | B79: Configuration and numbering | C79: System Settings | D79: System Administrator (BrokerVerse) | E79: Company logo and favicon on System Settings | F79: Functional | G79: Low | H79: Signed in as BrokerVerse. | I79: 1. Open Master > System Settings. 2. Click Upload Logo and choose a PNG. 3. Click Upload Favicon and choose an .exe renamed .ico. | J79: logo.png; bad.ico | K79: Logo preset added and shown. Disallowed favicon type refused. | L79: As expected. | M79: Pass | O79: iorta TechNXT QA | P79: 03 October 2026 | R79: backend/test/system-settings.test.js :: adds a logo preset by URL and by file upload, then removes it [passed] backend/test/system-settings.test.js :: uploads a favicon and rejects a disallowed type [passed] Screen check /master/configuration/system-settings: opened clean
A80: BV-CFG-007 | B80: Configuration and numbering | C80: Document Numbering | D80: System Administrator (BrokerVerse) | E80: Numbering series listed with next-number preview | F80: Functional | G80: High | H80: Fresh database. | I80: 1. Open Master > Document Numbering. 2. Search "receipt". 3. Read the pattern, current counter and next number. | J80: Series: official receipt | K80: Every document code has an active series with a unique prefix; preview shows the next number. | L80: As expected. | M80: Pass | O80: iorta TechNXT QA | P80: 03 October 2026 | R80: backend/test/numbering.test.js :: seeds a series for every code the application uses, with unique active prefixes and the default pattern [passed] backend/test/numbering.test.js :: lists series with the current counter and next-number preview [passed] Screen check /master/configuration/document-numbering: opened clean
A81: BV-CFG-008 | B81: Configuration and numbering | C81: Document Numbering | D81: System Administrator (BrokerVerse) | E81: Set the next official receipt number forward | F81: Functional | G81: High | H81: Receipt series active. | I81: 1. Open the official receipt series. 2. Set the next number to 5001 and save. 3. Have Accounting issue a receipt. 4. Try to set the next number back to 4000. | J81: Next number 5001; then 4000 | K81: The receipt carries number 5001 in the series format. Setting a lower number is refused (forward only). | L81: As expected. | M81: Pass | O81: iorta TechNXT QA | P81: 03 October 2026 | R81: backend/test/numbering.test.js :: sets the next number forward only [passed] backend/test/numbering.test.js :: updates a series with validation, unique prefixes and an audit entry [passed]
A82: BV-CFG-009 | B82: Configuration and numbering | C82: Document Numbering | D82: System Administrator (BrokerVerse) | E82: Pattern errors shown in the preview | F82: Validation | G82: Medium | H82: Series edit open. | I82: 1. Change the pattern to {PREFIX}-{YYYY}-{SEQ:5}-{BRANCH}. 2. Then enter an unknown token {FOO}. | J82: Pattern tokens | K82: Valid pattern previews; optional {BRANCH} / {LOB} drop with their separator; unknown token reported as a pattern error. | L82: As expected. | M82: Pass | O82: iorta TechNXT QA | P82: 03 October 2026 | R82: backend/test/numbering.test.js :: previews unsaved changes and reports pattern errors [passed] backend/test/numbering.test.js :: formats every token; optional {BRANCH} / {LOB} drop with their separator [passed]
A83: BV-CFG-010 | B83: Configuration and numbering | C83: Document Numbering | D83: System Administrator (BrokerVerse) | E83: Counter resets yearly, monthly or by fiscal year | F83: Validation | G83: Medium | H83: Series with yearly reset. | I83: 1. Issue a number on 31 December 2026 and on 01 January 2027 (test clock). | J83: Yearly reset series | K83: The counter restarts at the configured boundary. | L83: As expected. | M83: Pass | O83: iorta TechNXT QA | P83: 03 October 2026 | R83: backend/test/numbering.test.js :: yearly, monthly, fiscal-year and never reset the counter at the right boundary [passed]
... A94: BV-PCF-004 | B94: Product configurator | C94: Rating Engine | D94: Processing Team (jose.bernardo) | E94: Rate tables and insurer panel give a premium illustration | F94: Functional | G94: High | H94: Template with insurer panel. | I94: 1. Open Product Configurator > Rating Engine. 2. Add Factor for a template and save. 3. Open the insurer panel and calculate an illustration. | J94: Factor: vehicle age 0-3 years 1.00 | K94: Factor saved; premium illustration calculated per insurer. | L94: As expected. | M94: Pass | O94: iorta TechNXT QA | P94: 03 October 2026 | R94: backend/test/product-configurator.test.js :: manages the insurer panel and calculates a premium illustration [passed] backend/test/product-configurator.test.js :: CRUD for every component kind used by the mock-only screens [passed] Screen check /product-configurator/rating: opened clean
A95: BV-PCF-005 | B95: Product configurator | C95: Rating Engine | D95: Processing Team (jose.bernardo) | E95: Rating factors list shows which template each factor belongs to | F95: Functional | G95: Low | H95: Several templates with their own factors. | I95: 1. Open Product Configurator > Rating Engine. 2. Read the factor list. | J95: Factors of motor and householder templates | K95: Each factor row shows its template so per-template factors are distinguishable. | L95: Rating Engine, Coverage Builder, Acceptance Rules and Document Manager lists show a Template column; the same factor code on two templates (VEH_AGE on MOT-003-2025 and MOTOR-COMP-2026) is now distinguishable. | M95: Pass | N95: BV-DEF-004 (closed) | O95: iorta TechNXT QA | P95: 03 October 2026 | Q95: Re-test of 03 October 2026 after the fix, fresh database with the UAT data set. | R95: Screen check /product-configurator/rating: opened clean
A96: BV-PCF-006 | B96: Product configurator | C96: Coverage Builder | D96: Processing Team (jose.bernardo) | E96: Coverage Builder, Acceptance Rules, Document Manager, Approval Workflows | F96: Functional | G96: Medium | H96: Signed in as jose.bernardo. | I96: 1. Open Coverage Builder and click Add Coverage; save. 2. Open Acceptance Rules and click Add Rule; save. 3. Open Document Manager and upload a template. 4. Open Approval Workflows and click Create Workflow; Add Stage; save. | J96: Coverage: Riot, strike and civil commotion; Rule: vehicle age > 15 years refer | K96: Each component saves and lists. | L96: As expected. | M96: Pass | O96: iorta TechNXT QA | P96: 03 October 2026 | R96: backend/test/product-configurator.test.js :: CRUD for every component kind used by the mock-only screens [passed] Screen check /product-configurator/coverages: opened clean Screen check /product-configurator/underwriting: opened clean Screen check /product-configurator/documents: opened clean Screen check /product-configurator/workflows: opened clean
A97: BV-PCF-007 | B97: Product configurator | C97: Risk Mapping | D97: Processing Team (jose.bernardo) | E97: IAR sections added, deactivated and re-added | F97: Functional | G97: Low | H97: IAR product. | I97: 1. Open Product Configurator > Risk Mapping. 2. Add section Machinery breakdown, save. 3. Deactivate it and re-add. | J97: Section: Machinery breakdown | K97: Section list updates each time. | L97: As expected. | M97: Pass | O97: iorta TechNXT QA | P97: 03 October 2026 | R97: backend/test/product-configurator.test.js :: adds, updates, deactivates and re-adds IAR sections [passed] Screen check /product-configurator/risk-mapping: opened clean
A98: BV-PCF-008 | B98: Product configurator | C98: Motor tariff | D98: Processing Team (jose.bernardo) | E98: CTPL tariff change in the configurator is used by quotations | F98: Integration | G98: High | H98: Motor template open. | I98: 1. Change the CTPL of private cars and save. 2. As maria.rivera create a quick quote for a private car with CTPL. | J98: Private car CTPL changed for the test then restored | K98: Quotation uses the new tariff. A new vehicle class or 3-year CTPL appears once configured. | L98: As expected. | M98: Pass | O98: iorta TechNXT QA | P98: 03 October 2026 | R98: backend/test/motor-tariff.test.js :: follows tariff changes made in the Product Configurator [passed] backend/test/motor-tariff.test.js :: offers a 3-year CTPL and a new vehicle class once they are configured [passed]
A99: BV-PCF-009 | B99: Product configurator | C99: Motor tariff | D99: Processing Team (jose.bernardo) | E99: Invalid tariff amounts, seats and duplicate class codes refused | F99: Validation | G99: Medium | H99: Motor template open. | I99: 1. Enter a negative CTPL amount. 2. Enter seats 0. 3. Add class code private_cars again. | J99: CTPL -100; seats 0 | K99: Each value refused with a message. | L99: As expected. | M99: Pass | O99: iorta TechNXT QA | P99: 03 October 2026 | R99: backend/test/motor-tariff.test.js :: refuses invalid amounts, seats and duplicate class codes [passed]
A100: BV-PCF-010 | B100: Product configurator | C100: Dashboard / Analytics | D100: Processing Team (jose.bernardo) | E100: Product configurator dashboard and analytics | F100: Report | G100: Low | H100: Templates exist. | I100: 1. Open Product Configurator > Dashboard. 2. Open Product Analytics. | J100: None | K100: Both screens load figures for the templates. | L100: As expected. | M100: Pass | O100: iorta TechNXT QA | P100: 04 October 2026 | R100: backend/test/product-configurator.test.js :: analytics and dashboard return the screen shapes [passed] UAT cycle 03-04 October 2026, phase Reports and dashboards (58 passed, 0 failed) Screen check /product-configurator/dashboard: opened clean Screen check /product-configurator/analytics: opened clean
A101: BV-GOL-001 | B101: Go-live data load | C101: Production seed | D101: System Administrator (BrokerVerse) | E101: Production install seeds reference data only | F101: Functional | G101: High | H101: Empty PostgreSQL database; NODE_ENV=production. | I101: 1. Start the API. 2. Open /api/health. 3. Sign in as BrokerVerse and open Policy, Clients and Receipts. | J101: Fresh database | K101: Reference data and the administrator only; no demo transactions. A second seed changes nothing. | L101: As expected. | M101: Pass | O101: iorta TechNXT QA | P101: 03 October 2026 | R101: backend/test/go-live.test.js :: the API starts with NODE_ENV=production, seeds reference data only and answers the health check [passed] backend/test/go-live.test.js :: the database holds reference data and the administrator, and no demo transactions [passed] backend/test/go-live.test.js :: a second production seed is idempotent [passed]
A102: BV-GOL-002 | B102: Go-live data load | C102: Purge | D102: System Administrator (BrokerVerse) | E102: Purge of demo data needs confirmation and is a dry run by default | F102: Negative | G102: High | H102: Database with demo data. | I102: 1. Run the purge without CONFIRM_PURGE. 2. Run it with CONFIRM_PURGE=yes and --keep-users=BrokerVerse. | J102: CONFIRM_PURGE=yes | K102: Without confirmation nothing is deleted. With confirmation only reference data and the kept users remain; error rolls back. | L102: As expected. | M102: Pass | O102: iorta TechNXT QA | P102: 03 October 2026 | R102: backend/test/go-live.test.js :: the purge command refuses to run without CONFIRM_PURGE=yes and is a dry run by default [passed] backend/test/go-live.test.js :: the purge keeps only the users chosen with --keep-users and rolls back on error [passed]
A103: BV-GOL-003 | B103: Go-live data load | C103: In-force policies | D103: Processing Team (jose.bernardo) | E103: Upload in-force policies of the old system in go-live mode | F103: Functional | G103: High | H103: Policies_Upload_Template filled with the old system book. | I103: 1. Open Operations > Policy and click Upload Policy. 2. Tick the go-live option. 3. Upload old-system-in-force.csv. | J103: 14 policies OLD-MC-2025-xxxxx / OLD-FI-2025-xxxxx; insurers Pacific Crest, Luzon Bay, Visayas Mutual, Mindanao Shield | K103: "14 created, 0 failed". Policies are in force with no bill, no journal and no commission line. | L103: 14 in-force policies migrated; none reported as policies without accounting. | M103: Pass | O103: iorta TechNXT QA | P103: 04 October 2026 | R103: backend/test/upload-templates.test.js :: go-live policy upload creates in-force policies without bill, journal or commission; open items load against them once [passed] UAT cycle 03-04 October 2026, phase Go-live migration (1 passed, 0 failed)
A104: BV-GOL-004 | B104: Go-live data load | C104: Open items | D104: Accounting Officer (liza.quiambao) | E104: Load open premium items against migrated policies and receipt them | F104: Accounting | G104: High | H104: Go-live policies loaded. | I104: 1. Upload the open items file once. 2. Upload the same file again. 3. Enter a receipt against one open item. | J104: Open item PHP 18,550.40 on OLD-MC-2025-xxxxx | K104: Items load once (second upload refused). Receipt credits the receivable without booking the bill again. | L104: As expected. | M104: Pass | O104: iorta TechNXT QA | P104: 03 October 2026 | R104: backend/test/upload-templates.test.js :: go-live policy upload creates in-force policies without bill, journal or commission; open items load against them once [passed] backend/test/upload-templates.test.js :: a receipt against an open item credits the receivable without booking the bill again [passed]
A105: BV-GOL-005 | B105: Go-live data load | C105: Opening trial balance | D105: Accounting Officer (liza.quiambao) | E105: Load a balanced opening trial balance | F105: Accounting | G105: High | H105: Go-live date chosen; no journals in the fiscal year. | I105: 1. Open the trial balance upload. 2. Upload an unbalanced file. 3. Upload the balanced file. 4. Upload again with another go-live date. | J105: Go-live 30 April 2026; total debits = credits PHP 48,250,000.00 | K105: Unbalanced file loads nothing. Balanced file lands in the fiscal year of the go-live date; same date replaces it; another date refused. | L105: As expected. | M105: Pass | O105: iorta TechNXT QA | P105: 03 October 2026 | R105: backend/test/upload-templates.test.js :: refuses an unbalanced or invalid trial balance and loads nothing [passed] backend/test/upload-templates.test.js :: loads a balanced trial balance into the fiscal year of the go-live date; the same date replaces it, another date is refused [passed] backend/test/upload-templates.test.js :: refuses a go-live date after journals already posted in its fiscal year [passed]
A106: BV-GOL-006 | B106: Go-live data load | C106: Upload templates | D106: System Administrator (BrokerVerse) | E106: Upload templates match the importers | F106: Validation | G106: Medium | H106: Template download available per upload. | I106: 1. Download each upload template (leads, quotations, policies, masters, bank statement). 2. Upload each sample unchanged. | J106: Sample rows of each template | K106: Each sample row is accepted by its importer; Data sheet first, no duplicate headers. | L106: As expected. | M106: Pass | O106: iorta TechNXT QA | P106: 03 October 2026 | R106: backend/test/upload-templates.test.js :: builds one workbook per upload, Data sheet first, with the importer headers and no duplicate header [passed] backend/test/upload-templates.test.js :: every sample value is read back by the importer's own parser and column list [passed]
A107: BV-GOL-007 | B107: Go-live data load | C107: Upload limits | D107: System Administrator (BrokerVerse) | E107: Workbook decompression and row limits | F107: Negative | G107: Low | H107: Large workbook. | I107: 1. Upload a workbook above the row limit. | J107: XLSX with 200,000 rows | K107: Upload refused with a message stating the limit. | L107: As expected. | M107: Pass | O107: iorta TechNXT QA | P107: 03 October 2026 | R107: backend/test/hardening.test.js :: caps workbook decompression and import rows [passed]
... A138: BV-QUO-009 | B138: Quotations and customer response | C138: Customer approval | D138: Sales / Account Executive (maria.rivera) | E138: Customer response evidence validation | F138: Validation | G138: Medium | H138: Record customer response dialog open. | I138: 1. Click Record response with nothing selected. | J138: Empty form | K138: "Select how the response was received", "Enter the response date", "Enter a reference or remarks". | L138: As expected. | M138: Pass | O138: iorta TechNXT QA | P138: 03 October 2026 | R138: backend/test/customer-response.test.js :: validates the evidence: channel, date, reference or remarks [passed]
A139: BV-QUO-010 | B139: Quotations and customer response | C139: Customer approval | D139: Sales / Account Executive (maria.rivera) | E139: Customer approves through the link | F139: Functional | G139: High | H139: E-mail sending on; customer e-mail valid. | I139: 1. Send for Customer Approval. 2. Open the link from the e-mail as the customer. 3. Accept. 4. Open the link with a wrong token. | J139: Customer e-mail kristine.villanueva@example.ph | K139: Preview shows the quotation; accept sets Customer accepted; invalid token refused. | L139: Link flow confirmed in the backend run; e-mail delivery to an inbox not possible because SMTP is not configured. | M139: Blocked | O139: iorta TechNXT QA | P139: 03 October 2026 | Q139: Re-test with SMTP configured. | R139: backend/test/quotations.test.js :: public approve-by-customer: preview, accept, invalid token [passed] backend/test/quotations.test.js :: sends for approval: e-mail with signed link, underwriting notified, PendingCustomer [passed]
A140: BV-QUO-011 | B140: Quotations and customer response | C140: Customer approval | D140: Sales / Account Executive (maria.rivera) | E140: Response refused on a quotation not pending | F140: Negative | G140: Low | H140: Draft quotation. | I140: 1. Try to record a customer response on a Draft quotation. | J140: Draft quotation | K140: Refused; the transition map is respected. | L140: As expected. | M140: Pass | O140: iorta TechNXT QA | P140: 03 October 2026 | R140: backend/test/customer-response.test.js :: issues a new link when the stored one is gone and refuses a quotation that is not pending [passed] backend/test/customer-response.test.js :: follows the configured outcome status and the transition map [passed]
A141: BV-QUO-012 | B141: Quotations and customer response | C141: Quotation approval | D141: Processing Team (jose.bernardo) | E141: Maker cannot approve own quotation slip | F141: Negative | G141: High | H141: Quotation submitted to the insurer by jose.bernardo. | I141: 1. As jose.bernardo open the quotation and click Approve Quotation Slip. 2. As rica.fernandez approve it. | J141: Quotation slip of Kalayaan Steel Fabricators Inc. | K141: Maker refused; second user approves. | L141: As expected. | M141: Pass | O141: iorta TechNXT QA | P141: 03 October 2026 | R141: backend/test/quotations.test.js :: submits to the insurer, enforces maker-checker on approval and the transition map [passed]
A142: BV-QUO-013 | B142: Quotations and customer response | C142: Quotation | D142: Sales / Account Executive (maria.rivera) | E142: Convert or delete in the wrong status refused | F142: Negative | G142: Medium | H142: Draft quotation; converted quotation. | I142: 1. Click Convert to Policy on a Draft quotation. 2. Delete a converted quotation. | J142: Draft and converted quotations | K142: Both refused with a status message. | L142: As expected. | M142: Pass | O142: iorta TechNXT QA | P142: 03 October 2026 | R142: backend/test/quotations.test.js :: refuses to convert or delete quotations in the wrong status [passed]
A143: BV-QUO-014 | B143: Quotations and customer response | C143: Quotation | D143: Sales / Account Executive (maria.rivera) | E143: Bulk upload quotations from CSV | F143: Functional | G143: Low | H143: Template downloaded. | I143: 1. Open Quotations, click upload and click Download Template. 2. Upload 2 rows. | J143: 2 motor quotations | K143: Both created; errors reported per row. | L143: As expected. | M143: Pass | O143: iorta TechNXT QA | P143: 03 October 2026 | R143: backend/test/quotations.test.js :: bulk uploads quotations from CSV [passed]
A144: BV-QUO-015 | B144: Quotations and customer response | C144: Quotation | D144: Sales / Account Executive (maria.rivera) | E144: Quotation by another user on own prospect appears in list and funnel | F144: Integration | G144: Low | H144: jose.bernardo creates a quotation on maria.rivera's prospect. | I144: 1. As maria.rivera open Quotations and the Sales Dashboard funnel. | J144: Prospect of maria.rivera | K144: Quotation listed and counted in the funnel. | L144: As expected. | M144: Pass | O144: iorta TechNXT QA | P144: 03 October 2026 | R144: backend/test/role-access.test.js :: a quotation another user creates on the agent's lead is in both the quotation list and the dashboard funnel [passed]
A145: BV-QUO-016 | B145: Quotations and customer response | C145: Quotation | D145: Sales / Account Executive (maria.rivera) | E145: Quotation statistics | F145: Report | G145: Low | H145: Quotations exist. | I145: 1. Open Quotations and read the totals. | J145: None | K145: Totals by status shown. | L145: As expected. | M145: Pass | O145: iorta TechNXT QA | P145: 04 October 2026 | R145: backend/test/quotations.test.js :: stats, compare, vehicle info, quote PDF and customer e-mail [passed] UAT cycle 03-04 October 2026, phase Reports and dashboards (58 passed, 0 failed)
A146: BV-RFQ-001 | B146: Request for quotation and placement | C146: Request for Quotation | D146: Sales / Account Executive (maria.rivera) | E146: Retail RFQ to two insurers (PA) | F146: Functional | G146: High | H146: Prospect for Personal Accident. | I146: 1. Open Operations > Sales & Marketing > Request for Quotation. 2. Click New Request for Quotation. 3. Select prospect, product PA, sum insured, requested covers, insurers Luzon Bay and Harbor Point. 4. Click Save and submit to market. | J146: PA AD&D PHP 500,000.00; medical PHP 50,000.00; occupation Teacher | K146: Slip numbered; one pending request per insurer. | L146: 10 PA, 6 Travel and 8 Home RFQs sent in the cycle. | M146: Pass | O146: iorta TechNXT QA | P146: 04 October 2026 | R146: backend/test/placement.test.js :: creates a broker slip with the market and submits it (one queued request per insurer) [passed] UAT cycle 03-04 October 2026, phase Retail package business (84 passed, 0 failed) Screen check /placement/broker-slips: opened clean
A147: BV-RFQ-002 | B147: Request for quotation and placement | C147: Request for Quotation | D147: Sales / Account Executive (maria.rivera) | E147: RFQ saves a new prospect in one step | F147: Functional | G147: Medium | H147: No prospect yet. | I147: 1. New Request for Quotation, choose New insured and type the name. 2. Save. | J147: Bagong Silangan Agri-Ventures Corp. | K147: Prospect created and slip saved against it; on failure nothing is saved. | L147: As expected. | M147: Pass | O147: iorta TechNXT QA | P147: 03 October 2026 | R147: backend/test/request-for-quotation.test.js :: saves the prospect as a lead and the slip against it in one step [passed] backend/test/request-for-quotation.test.js :: needs a lead, a client or a prospect with a name, and saves nothing on failure [passed]
A148: BV-RFQ-003 | B148: Request for quotation and placement | C148: Offers | D148: Processing Team (jose.bernardo) | E148: Record offers and declines, compare and prepare a quotation slip | F148: Functional | G148: High | H148: Corporate fire RFQ sent to 3 insurers. | I148: 1. Open the slip. 2. Record response for two insurers (premium, share, reference, deductibles, validity). 3. Record decline for the third with a reason. 4. Open Compare offers. 5. Select two lines and click Prepare Quotation Slip with shares 60 / 40. | J148: Kalayaan Steel Fabricators Inc.; fire PHP 120,000,000.00; Pacific Crest 60%, Visayas Mutual 40%; decline: Treaty capacity used for the zone | K148: Comparison shows premiums and the best offer; co-insurance quotation slip prepared with lead insurer. | L148: 102 offers and 16 declines recorded; 4 FIRE co-insurance slips prepared. | M148: Pass | O148: iorta TechNXT QA | P148: 04 October 2026 | R148: backend/test/placement.test.js :: records the offers and declines, compares them and prepares a co-insurance Quotation Slip from two lines [passed] UAT cycle 03-04 October 2026, phase Corporate non-package business (45 passed, 0 failed)
A149: BV-RFQ-004 | B149: Request for quotation and placement | C149: Offers | D149: Processing Team (jose.bernardo) | E149: Shares must total 100% with one lead | F149: Validation | G149: High | H149: Prepare Quotation Slip dialog. | I149: 1. Enter shares 60 / 30. 2. Mark two leads. 3. Add an unknown insurer. | J149: Shares 60 / 30 | K149: Each refused with a clear message. | L149: As expected. | M149: Pass | O149: iorta TechNXT QA | P149: 03 October 2026 | R149: backend/test/placement.test.js :: rejects shares that do not total 100%, two leads and unknown insurers with a clear message [passed]
A150: BV-RFQ-005 | B150: Request for quotation and placement | C150: Offers | D150: Processing Team (jose.bernardo) | E150: Participant amounts split with the remainder on the lead | F150: Accounting | G150: Medium | H150: Three-way co-insurance 50 / 30 / 20. | I150: 1. Issue the policy. 2. Read participant premiums. | J150: Gross PHP 1,000,000.01 | K150: Each share rounded to centavos; remainder centavo on the lead insurer. | L150: As expected. | M150: Pass | O150: iorta TechNXT QA | P150: 03 October 2026 | R150: backend/test/placement.test.js :: splits with round2 and puts the remainder on the lead (unit) [passed] backend/test/placement.test.js :: writes participants by insurer id, splits by share with the remainder on the lead and keeps the legacy participantDetails [passed]
A151: BV-RFQ-006 | B151: Request for quotation and placement | C151: Placement Slips | D151: Processing Team (jose.bernardo) | E151: Placement slip, firm order and insurer bindings | F151: Functional | G151: High | H151: Quotation slip accepted by the client. | I151: 1. Open Operations > Sales & Marketing > Placement Slips. 2. Click Create Placement Slip from the quotation. 3. Click Send to insurer(s). 4. Record each insurer's confirmation with its reference. 5. Click Issue Policy. | J151: PCIC-FIRE-2026-xxxxxx; VIS-FIRE-2026-xxxxxx | K151: Policy issued only after every insurer confirms; participants copied; lead insurer on the policy; quotation Converted. | L151: 22 placement slips; 36 bindings; 22 corporate policies issued from placements. | M151: Pass | O151: iorta TechNXT QA | P151: 04 October 2026 | R151: backend/test/placement.test.js :: creates the Placement Slip from the quotation, sends it and records each insurer's binding [passed] backend/test/placement.test.js :: sends the firm order per participant and binds when every insurer confirms [passed] backend/test/placement.test.js :: issues the policy from the bound placement: participants copied, lead insurer on the policy, quotation converted [passed] UAT cycle 03-04 October 2026, phase Corporate non-package business (45 passed, 0 failed) Screen check /placement/placement-slips: opened clean
... A172: BV-POL-014 | B172: Policy issuance | C172: Commission accrual | D172: Processing Team (jose.bernardo) | E172: No commission line for an administrator issuing a policy | F172: Validation | G172: Low | H172: Policy issued by BrokerVerse and one by an Account Executive. | I172: 1. Open Commission > Commission Dashboard. | J172: Two policies | K172: Only the Account Executive earns a commission line. | L172: As expected. | M172: Pass | O172: iorta TechNXT QA | P172: 03 October 2026 | R172: backend/test/policy-payments.test.js :: no commission line for an administrator who issues a policy; an Account Executive earns one [passed]
A173: BV-POL-015 | B173: Policy issuance | C173: Payment gateway | D173: Sales / Account Executive (maria.rivera) | E173: Online payment link issues the package policy | F173: Integration | G173: Medium | H173: Payment gateway in sandbox. | I173: 1. Create a payment link for an accepted package quotation. 2. Pay in the sandbox. | J173: PayMongo sandbox; amount in centavos | K173: Signed webhook applied once; policy issued; receipt created; policy PDF available. Bad signature rejected and logged. | L173: As expected. | M173: Pass | O173: iorta TechNXT QA | P173: 03 October 2026 | Q173: Sandbox only; live keys not configured. | R173: backend/test/payments.test.js :: pays a package quotation in the sandbox: policy issued, receipt created, policy PDF available [passed] backend/test/payments.test.js :: rejects a notification with a bad signature and logs it [passed]
A174: BV-END-001 | B174: Endorsements and cancellations | C174: Endorsement | D174: Operations / Client Service (ana.buenaventura) | E174: Additional premium endorsement on a motor policy | F174: Functional | G174: High | H174: Active broker-billed motor policy, OD PHP 1,200,000.00 at 2%. | I174: 1. Open the policy and start an endorsement. 2. Change own damage sum insured to PHP 1,400,000.00 and click Save & Next. 3. Send to Insurance Company. 4. Click Upload Endorsement with the insurer document and complete with issued date. | J174: OD 1,200,000.00 -> 1,400,000.00 at 2%; remarks: Accessories added: mags, dashcam and tint | K174: Premium delta priced by the system (net PHP 4,000.00 plus taxes); endorsement numbered; new bill raised with a balanced journal and a collection item; policy premium updated. | L174: 4 additional premium endorsements completed and paid. | M174: Pass | O174: iorta TechNXT QA | P174: 04 October 2026 | R174: backend/test/endorsements.test.js :: prices the screen payload of a motor policy with BI / PD / APPA (own damage 1,200,000 -> 1,400,000 at 2%) [passed] backend/test/endorsements.test.js :: bills a positive delta as a new receivable with a balanced journal and a collection item, and updates the policy premium [passed] UAT cycle 03-04 October 2026, phase Servicing: endorsements, renewals, claims (31 passed, 0 failed)
A175: BV-END-002 | B175: Endorsements and cancellations | C175: Endorsement | D175: Operations / Client Service (ana.buenaventura) | E175: Premium delta that does not match the coverage change refused | F175: Negative | G175: High | H175: Endorsement form. | I175: 1. Send a premium delta different from new gross minus current gross. | J175: Delta sent PHP 1,000.00 vs computed PHP 4,994.40 | K175: Refused. | L175: As expected. | M175: Pass | O175: iorta TechNXT QA | P175: 03 October 2026 | R175: backend/test/endorsements.test.js :: refuses a premiumDelta that does not match new gross - current gross [passed]
A176: BV-END-003 | B176: Endorsements and cancellations | C176: Endorsement | D176: Operations / Client Service (ana.buenaventura) | E176: Zero delta is not billed | F176: Validation | G176: Low | H176: Address change only. | I176: 1. Endorse a change of address. | J176: New address: 32nd St., Fort Bonifacio, Taguig | K176: Endorsement completed; no bill. | L176: As expected. | M176: Pass | O176: iorta TechNXT QA | P176: 03 October 2026 | R176: backend/test/endorsements.test.js :: does not bill a zero delta [passed]
A177: BV-END-004 | B177: Endorsements and cancellations | C177: Endorsement | D177: Operations / Client Service (ana.buenaventura) | E177: Return premium on a paid policy raises a client refund | F177: Accounting | G177: High | H177: Fully paid motor policy. | I177: 1. Reduce own damage to the appraised value. 2. Complete the endorsement. 3. Open Accounts > Disbursement invoice list. | J177: OD reduced by 15% | K177: Return premium credits the open bill; the paid part becomes a client refund payable; commission taxes reversed at booked rates. | L177: 2 return premium endorsements; 3 client refunds paid by cheque. | M177: Pass | O177: iorta TechNXT QA | P177: 04 October 2026 | R177: backend/test/posting-rules.test.js :: return premium credits the open bill and makes the paid part a client refund payable [passed] backend/test/commission-taxes.test.js :: a return premium reverses the commission taxes at the rates booked; bills booked without them return none [passed] backend/test/endorsements.test.js :: records a negative delta (return premium) without billing it [passed] UAT cycle 03-04 October 2026, phase Servicing: endorsements, renewals, claims (31 passed, 0 failed)
A178: BV-END-005 | B178: Endorsements and cancellations | C178: Endorsement | D178: Operations / Client Service (ana.buenaventura) | E178: Return premium claws back sub-agent commission | F178: Accounting | G178: Medium | H178: Policy with paid sub-agent commission line. | I178: 1. Endorse a 25% return. 2. Cancel the rest later. | J178: Return 25% | K178: 25% of the paid line clawed back and 25% of the accrual reversed; later cancellation claws back only what is left. | L178: As expected. | M178: Pass | O178: iorta TechNXT QA | P178: 03 October 2026 | R178: backend/test/accounting-followups.test.js :: a 25% return claws back 25% of the paid line and reverses 25% of the approved accrual through the posting rules [passed] backend/test/accounting-followups.test.js :: a later cancellation of the rest claws back only what is left and reverses the lines [passed]
...

Sheet Traceability
A1: TC ID | B1: Module | C1: Test Scenario | D1: Status | E1: Backend / front-end test file | F1: Test name | G1: UAT phase | H1: UAT phase result | I1: Screen check (path) | J1: Screen check result
A2: BV-SEC-001 | B2: Sign-in and security | C2: Sign in with a valid user ID and password | D2: Pass | E2: backend/test/core.test.js | F2: rejects a wrong password and accepts the admin | I2: /executive/dashboard | J2: opened clean
A3: BV-SEC-002 | B3: Sign-in and security | C3: Wrong password is refused with a generic message | D3: Pass | E3: backend/test/core.test.js backend/test/security.test.js | F3: rejects a wrong password and accepts the admin exposes sign-in history to administrators and to the user
A4: BV-SEC-003 | B4: Sign-in and security | C4: Unknown user ID gets the same message as a wrong password | D4: Pass | E4: backend/test/security.test.js backend/test/security.test.js | F4: rate limits sign-in per username and per IP (429 + Retry-After) and logs every attempt exposes sign-in history to administrators and to the user
A5: BV-SEC-004 | B5: Sign-in and security | C5: Login with blank User ID and Password | D5: Not Run | E5: brokerverse/src/App.test.js | F5: renders the sign-in screen when signed out
A6: BV-SEC-005 | B6: Sign-in and security | C6: Account locks after the configured number of failed sign-ins | D6: Pass | E6: backend/test/security.test.js backend/test/hardening.test.js | F6: rate limits sign-in per username and per IP (429 + Retry-After) and logs every attempt unlocks a locked account and records it
A7: BV-SEC-006 | B7: Sign-in and security | C7: Administrator unlocks a locked user | D7: Pass | E7: backend/test/hardening.test.js | F7: unlocks a locked account and records it | I7: /master/generals/usermanagement/user | J7: opened clean
A8: BV-SEC-007 | B8: Sign-in and security | C8: Too many sign-in attempts from one address are throttled | D8: Pass | E8: backend/test/security.test.js | F8: rate limits sign-in per username and per IP (429 + Retry-After) and logs every attempt
A9: BV-SEC-008 | B9: Sign-in and security | C9: Change password: rules shown and enforced | D9: Pass | E9: backend/test/security.test.js | F9: enforces length, character classes and history on change-password
A10: BV-SEC-009 | B10: Sign-in and security | C10: New password cannot repeat one of the last 5 passwords | D10: Pass | E10: backend/test/security.test.js | F10: enforces length, character classes and history on change-password
A11: BV-SEC-010 | B11: Sign-in and security | C11: New password must differ from the current one and both entries must match | D11: Pass | E11: backend/test/security.test.js | F11: enforces length, character classes and history on change-password
A12: BV-SEC-011 | B12: Sign-in and security | C12: New user created without a password gets a temporary password that must be changed | D12: Pass | E12: backend/test/hardening.test.js backend/test/core.test.js | F12: generates a policy-compliant temporary password for a user created without one; it must be changed admin creates a persona user who can then sign in with that role | G12: Set-up | H12: 46 passed, 0 failed
A13: BV-SEC-012 | B13: Sign-in and security | C13: Expired password forces a change at sign-in | D13: Pass | E13: backend/test/security.test.js | F13: flags mustChangePassword when the password is older than security.password_max_age_days
A14: BV-SEC-013 | B14: Sign-in and security | C14: Forgot password with a verification code | D14: Blocked | E14: backend/test/configuration.test.js backend/test/hardening.test.js | F14: password reset e-mail and code lifetime follow security.reset_* settings stores reset codes hashed, keeps only the latest valid, withdraws a code after too many wrong entries
A15: BV-SEC-014 | B15: Sign-in and security | C15: Reset code withdrawn after too many wrong entries | D15: Pass | E15: backend/test/hardening.test.js | F15: stores reset codes hashed, keeps only the latest valid, withdraws a code after too many wrong entries
A16: BV-SEC-015 | B16: Sign-in and security | C16: Turn on two-step verification and sign in with the code | D16: Pass | E16: backend/test/security.test.js backend/test/security.test.js | F16: enrols, then requires the code at sign-in; disables with a code implements RFC 6238 / RFC 4226 correctly
A17: BV-SEC-016 | B17: Sign-in and security | C17: Wrong two-step code is refused and checks are rate limited | D17: Pass | E17: backend/test/hardening.test.js backend/test/security.test.js | F17: rate limits two-factor code checks of a signed-in user exposes sign-in history to administrators and to the user
A18: BV-SEC-017 | B18: Sign-in and security | C18: Role that requires two-step verification must enrol before any screen | D18: Pass | E18: backend/test/security.test.js | F18: forces enrolment for roles in security.require_2fa_roles; administrators can reset a user's second factor
A19: BV-SEC-018 | B19: Sign-in and security | C19: Administrator turns off a user's two-step verification | D19: Pass | E19: backend/test/security.test.js | F19: forces enrolment for roles in security.require_2fa_roles; administrators can reset a user's second factor
A20: BV-SEC-019 | B20: Sign-in and security | C20: A non-administrator user desk cannot reset 2FA or lock a System Administrator | D20: Pass | E20: backend/test/hardening.test.js | F20: a non-administrator user desk cannot reset, lock or turn off 2FA of a System Administrator, nor change their own access
A21: BV-SEC-020 | B21: Sign-in and security | C21: Idle session signs out after the configured minutes | D21: Not Run | E21: backend/test/hardening.test.js | F21: defaults: 30-minute access tokens; development keeps its fallbacks
A22: BV-SEC-021 | B22: Sign-in and security | C22: Deactivating a user or changing the role ends access at once | D22: Pass | E22: backend/test/hardening.test.js | F22: ends access at once on deactivation and on role change; refresh issues a token with the new roles
A23: BV-SEC-022 | B23: Sign-in and security | C23: End every session of a user | D23: Pass | E23: backend/test/access-control.test.js | F23: ends every session of a user | I23: /master/generals/usermanagement/access-matrix | J23: opened clean
A24: BV-SEC-023 | B24: Sign-in and security | C24: Reuse of an old refresh token revokes the sign-in | D24: Pass | E24: backend/test/hardening.test.js | F24: detects reuse of a rotated refresh token and revokes the whole sign-in
A25: BV-SEC-024 | B25: Sign-in and security | C25: Sign-in history visible to the administrator and the user | D25: Pass | E25: backend/test/security.test.js | F25: exposes sign-in history to administrators and to the user
A26: BV-SEC-025 | B26: Sign-in and security | C26: Every non-public endpoint refuses a call without a token | D26: Pass | E26: backend/test/hardening.test.js backend/test/hardening.test.js | F26: every non-public route answers 401 without a token declares only the intended public routes
A27: BV-SEC-026 | B27: Sign-in and security | C27: Tokens other than HS256 and default secrets are refused | D27: Pass | E27: backend/test/hardening.test.js backend/test/hardening.test.js | F27: accepts only HS256 tokens refuses missing or default secrets, CORS * and a localhost base URL in production only
A28: BV-SEC-027 | B28: Sign-in and security | C28: Injection probes in search and file fields | D28: Pass | E28: backend/test/hardening.test.js backend/test/hardening.test.js backend/test/configuration.test.js | F28: detects file types from their signature, not from the name or the browser refuses HTML, scripts and unknown binaries; stores the detected type CSV cells written by any module are guarded against spreadsheet formulas
A29: BV-SEC-028 | B29: Sign-in and security | C29: Security headers and request id on every response | D29: Pass | E29: backend/test/security.test.js backend/test/hardening.test.js | F29: adds x-request-id to every response, echoes a caller id and returns it in error bodies answers 500 with a generic message and the request id; client errors keep their message
A30: BV-SEC-029 | B30: Sign-in and security | C30: Upload size limit and global rate limit | D30: Pass | E30: backend/test/hardening.test.js backend/test/hardening.test.js | F30: refuses uploads above UPLOAD_MAX_MB with 413 applies a configurable global API rate limit per user
A31: BV-SEC-030 | B31: Sign-in and security | C31: Tokens and cookies never written to the server log | D31: Pass | E31: backend/test/hardening.test.js | F31: never writes bearer tokens, cookies or link tokens to the log
A32: BV-SEC-031 | B32: Sign-in and security | C32: Document links open only with a session or a signed, unexpired link | D32: Pass | E32: backend/test/hardening.test.js backend/test/hardening.test.js | F32: serves objects only with a bearer header or a signed, unexpired link, with safe headers sends non-image, non-PDF files as attachments; legacy unsafe types as octet-stream
A33: BV-SEC-032 | B33: Sign-in and security | C33: Dependency audit of the release build | D33: Fail
A34: BV-SEC-033 | B34: Sign-in and security | C34: Personal data encrypted at application level | D34: Pass | E34: backend/test/personal-data-protection.test.js | F34: stores TIN and government ID numbers encrypted with a blind index
A35: BV-SEC-034 | B35: Sign-in and security | C35: Record client consent under the Data Privacy Act | D35: Pass
A36: BV-SEC-035 | B36: Sign-in and security | C36: Log and answer a data subject access or erasure request | D36: Pass
A37: BV-USR-001 | B37: User and role administration | C37: Create a user per broker role | D37: Pass | E37: backend/test/user-access.test.js backend/test/core.test.js | F37: lists, creates and locks users, and reads the audit trail admin creates a persona user who can then sign in with that role | G37: Set-up | H37: 46 passed, 0 failed | I37: /master/generals/usermanagement/user | J37: opened clean
A38: BV-USR-002 | B38: User and role administration | C38: Required fields and e-mail format on Add User | D38: Pass | E38: backend/test/role-access.test.js | F38: every create endpoint of the walk answers 400 "Validation failed" with one readable message per field
A39: BV-USR-003 | B39: User and role administration | C39: Duplicate username refused | D39: Pass | E39: backend/test/user-access.test.js | F39: lists, creates and locks users, and reads the audit trail
A40: BV-USR-004 | B40: User and role administration | C40: Only a System Administrator grants the administrator role | D40: Pass | E40: backend/test/user-access.test.js backend/test/hardening.test.js | F40: cannot grant the System Administrator role only a System Administrator grants the administrator role or edits it; nobody changes their own roles or status
A41: BV-USR-005 | B41: User and role administration | C41: A user cannot change own roles or status | D41: Pass | E41: backend/test/user-access.test.js | F41: cannot change its own roles
A42: BV-USR-006 | B42: User and role administration | C42: Administrator resets a user password | D42: Pass | E42: backend/test/hardening.test.js | F42: administrator reset without a password returns a temporary one once and ends the user's sessions
A43: BV-USR-007 | B43: User and role administration | C43: Seeded roles are the broker roles plus System Administrator | D43: Pass | E43: backend/test/user-access.test.js backend/test/broker-roles-migration.test.js | F43: the seeded roles are the broker roles and the System Administrator leaves no old role code anywhere and is idempotent | I43: /master/generals/usermanagement/role | J43: opened clean
A44: BV-USR-008 | B44: User and role administration | C44: Change a role permission; the change waits for a second approver | D44: Pass | E44: backend/test/configuration-controls.test.js backend/test/hardening.test.js | F44: a role change waits for a different approver role permission changes renew the tokens of the role's users | I44: /master/generals/usermanagement/role-permissions /master/finance/configuration-approvals | J44: opened clean opened clean
A45: BV-USR-009 | B45: User and role administration | C45: Approval limits per role and transaction type | D45: Pass | E45: backend/test/access-control.test.js backend/test/access-control.test.js | F45: ships default limits per role and shows them types down, roles across a new limit applies only after another administrator approves it | I45: /master/generals/usermanagement/authority-matrix | J45: opened clean
A46: BV-USR-010 | B46: User and role administration | C46: Approval above the approver limit is refused | D46: Pass | E46: backend/test/access-control.test.js | F46: refuses an approval above the approver's limit and allows it within | G46: Reconciliation: bank and insurer statements | H46: 10 passed, 0 failed
A47: BV-USR-011 | B47: User and role administration | C47: Delegate approval authority for a date range | D47: Pass | E47: backend/test/access-control.test.js | F47: a delegation lends the delegator's authority for its types and dates | I47: /master/generals/usermanagement/delegations | J47: opened clean
A48: BV-USR-012 | B48: User and role administration | C48: Conflicting roles blocked on one user | D48: Pass | E48: backend/test/access-control.test.js | F48: blocks roles one person may not hold together and warns on the others | I48: /master/generals/usermanagement/segregation-of-duties | J48: opened clean
A49: BV-USR-013 | B49: User and role administration | C49: Periodic access review closes when every user is decided | D49: Pass | E49: backend/test/access-control.test.js | F49: reviews every active user; a revoked user is deactivated and the review closes when all are decided | I49: /master/generals/usermanagement/access-reviews | J49: opened clean
A50: BV-USR-014 | B50: User and role administration | C50: User access report downloads | D50: Pass | E50: backend/test/access-control.test.js | F50: lists every user with roles and sign-in facts, and downloads it | I50: /master/generals/usermanagement/access-matrix | J50: opened clean
A51: BV-USR-015 | B51: User and role administration | C51: Dormant accounts deactivated, administrator kept | D51: Pass | E51: backend/test/access-control.test.js | F51: deactivates accounts with no sign-in for the dormant period, never the built-in administrator
A52: BV-USR-016 | B52: User and role administration | C52: Account Executive in a scoped role sees only own book | D52: Pass | E52: backend/test/scope.test.js backend/test/scope.test.js backend/test/scope.test.js backend/test/scope.test.js | F52: leads: each agent lists, reads and updates only their own; admin sees all quotations: own list and stats; someone else's quote (or lead) answers 404 policies and clients: own book only; admin sees both agents' policies scoped roles come from security.scoped_roles
A53: BV-MST-001 | B53: Masters | C53: Add an insurer with credit terms | D53: Pass | E53: backend/test/masters.test.js backend/test/numbering.test.js | F53: creates, reads, searches, updates and deactivates are edited on the insurer master and fall back to the settings | G53: Set-up | H53: 46 passed, 0 failed | I53: /master/generals/insurancemanagement/insurancecompany | J53: opened clean
A54: BV-MST-002 | B54: Masters | C54: Required fields and duplicate code on a master | D54: Pass | E54: backend/test/masters.test.js | F54: validates required fields, types and duplicate codes
A55: BV-MST-003 | B55: Masters | C55: Product master shows package / non-package classification | D55: Pass | E55: backend/test/product-classification.test.js backend/test/product-classification.test.js | F55: seeds package and non-package products with their customer segment shows and filters the classification on the placement options and the product master | I55: /master/generals/insurancemanagement/productmaster | J55: opened clean
A56: BV-MST-004 | B56: Masters | C56: Reclassifying a product changes its placement journey | D56: Pass | E56: backend/test/product-classification.test.js | F56: reclassifying a product on the Product master changes its journey without a code change
A57: BV-MST-005 | B57: Masters | C57: Cover master: code issued, several covers per line | D57: Pass | E57: backend/test/masters.test.js backend/test/masters.test.js | F57: issues the code, leaves Effective To open, keeps several covers and matches every sales person when none is set offers the covers of a line and those without a line | I57: /master/generals/insurancemanagement/cover | J57: opened clean
A58: BV-MST-006 | B58: Masters | C58: Signatory added is offered on quotations; inactive is not | D58: Pass | E58: backend/test/masters.test.js backend/test/quote-to-policy.test.js | F58: a signatory added under Master is offered; an inactive one is not the quotation PDF prints the chosen signatory with the designation | I58: /master/generals/insurancemanagement/signatories | J58: opened clean
A59: BV-MST-007 | B59: Masters | C59: Country, province and city drop-downs follow the hierarchy | D59: Pass | E59: backend/test/addresses.test.js backend/test/addresses.test.js | F59: serves the Philippine hierarchy used by the claim screens: Metro Manila (NCR) -> Makati looks up postal codes for auto-fill | I59: /master/generals/location/country /master/generals/location/state /master/generals/location/city | J59: opened clean opened clean opened clean
A60: BV-MST-008 | B60: Masters | C60: Upload cities from the master template | D60: Pass | E60: backend/test/upload-templates.test.js | F60: downloads a master template and creates the uploaded records, reporting the rows that fail
A61: BV-MST-009 | B61: Masters | C61: Primary company prints on documents | D61: Pass | E61: backend/test/printing.test.js backend/test/printing.test.js | F61: reads the primary company of the Company master (iorta TechNXT Corp. out of the box) with its logo allows one primary company only, and prints follow the primary company | I61: /master/generals/organization/companymaster | J61: opened clean
A62: BV-MST-010 | B62: Masters | C62: Branch, designation and employee masters open and save | D62: Pass | E62: backend/test/masters.test.js | F62: creates, reads, searches, updates and deactivates | I62: /master/generals/organization/branchmaster /master/generals/employeemanagement/designation /master/generals/employeemanagement/employee | J62: opened clean opened clean opened clean
A63: BV-MST-011 | B63: Masters | C63: Sales reads masters but cannot change them | D63: Pass | E63: backend/test/masters.test.js | F63: enforces permissions: sales may read but not write
A64: BV-MST-012 | B64: Masters | C64: Administrator adds a new master type without code change | D64: Pass | E64: backend/test/masters.test.js | F64: administrators add a new master type and edit field definitions without code changes
A65: BV-MST-013 | B65: Masters | C65: Currency, exchange rate and bank masters | D65: Pass | E65: backend/test/masters.test.js brokerverse/src/module/FinanceMastersModule/BankMaster/AccountDataView/bankAccountErrors.test.js | F65: currency and seeded insurance companies expose front-end field names checks the formats of number, e-mail, phone and SWIFT code | G65: Set-up | H65: 46 passed, 0 failed | I65: /master/finance/currency /master/finance/exchangerate /master/finance/bank | J65: opened clean opened clean opened clean
A66: BV-MST-014 | B66: Masters | C66: Chart of accounts is a complete Philippine broker chart | D66: Pass | E66: backend/test/chart-of-accounts.test.js backend/test/chart-of-accounts.test.js backend/test/chart-of-accounts.test.js | F66: every GL account the system posts to (settings, payee and payment-mode maps) exists and is active is a complete Philippine broker chart, grouped for the statements is maintained from the chart of accounts screen (type grouping, statement group, system accounts protected) | I66: /master/finance/mainaccount /master/finance/subaccount /master/finance/accountcategory | J66: opened clean opened clean opened clean
A67: BV-MST-015 | B67: Masters | C67: Upload chart of accounts adds and updates accounts | D67: Pass | E67: backend/test/upload-templates.test.js | F67: chart of accounts upload adds new accounts and updates existing ones
A68: BV-MST-016 | B68: Masters | C68: Commission rate per insurer and product with renewal row | D68: Pass | E68: backend/test/numbering.test.js backend/test/numbering.test.js | F68: picks the most specific active row effective on the date falls back to the insurer rate, then commission.default_rate | G68: Set-up | H68: 46 passed, 0 failed | I68: /master/finance/commission-rate-matrix | J68: opened clean
A69: BV-MST-017 | B69: Masters | C69: Overlapping active commission rows refused | D69: Pass | E69: backend/test/numbering.test.js | F69: rejects overlapping active rows with the same keys; inactive rows do not count
A70: BV-MST-018 | B70: Masters | C70: Tax codes master holds the PH codes with ATCs | D70: Pass | E70: backend/test/period-end.test.js backend/test/masters.test.js | F70: tax codes master holds the PH codes with ATCs and is editable taxation records linked to a setting keep the configuration key in step | G70: Set-up | H70: 46 passed, 0 failed | I70: /master/finance/taxation | J70: opened clean
A71: BV-MST-019 | B71: Masters | C71: Premium taxes and LGU rates maintained by Accounting | D71: Pass | E71: backend/test/premium-charges.test.js backend/test/premium-charges.test.js backend/test/premium-charges.test.js | F71: lets Accounting maintain rules and LGU rates; Sales cannot lists the seeded rules and Metro Manila LGU rates calculates the charges of a product premium at a location | I71: /master/finance/premium-taxes | J71: opened clean
A72: BV-MST-020 | B72: Masters | C72: DST, VAT, FST and LGT computed on a fire premium | D72: Pass | E72: backend/test/premium-charges.test.js backend/test/premium-charges.test.js backend/test/premium-charges.test.js | F72: prices VAT, DST per P4.00, FST on fire and LGT for a fire premium charges DST on every P4.00 or fractional part (round up) or proportionally (prorate) rounds every amount to 2 decimals half away from zero and totals the rounded lines
A73: BV-MST-021 | B73: Masters | C73: Money rounding half away from zero | D73: Pass | E73: backend/test/configuration.test.js backend/test/configuration.test.js backend/test/configuration.test.js | F73: round2(1.005) = 1.01 round2(2.675) = 2.68 treats empty and invalid input as 0 (never -0 or NaN)
A74: BV-CFG-001 | B74: Configuration and numbering | C74: Every setting is listed with a label and group | D74: Pass | E74: backend/test/configuration.test.js backend/test/configuration.test.js | F74: every key read by the code is seeded, with a label and a group (so Master > Configuration shows it) scripts/check-settings.js: every key read in code exists and only documented keys are left unread | I74: /master/configuration/settings | J74: opened clean
A75: BV-CFG-002 | B75: Configuration and numbering | C75: Change a setting; it is saved and audited | D75: Pass | E75: backend/test/core.test.js backend/test/core.test.js | F75: settings are read from the database and editable by admins writes an audit trail
A76: BV-CFG-003 | B76: Configuration and numbering | C76: Invalid setting value refused | D76: Pass | E76: backend/test/system-settings.test.js | F76: rejects invalid values and unauthorised users
A77: BV-CFG-004 | B77: Configuration and numbering | C77: Settings change on one server is picked up by the others | D77: Pass | E77: backend/test/operations.test.js | F77: picks up a setting changed by another instance at the next version check
A78: BV-CFG-005 | B78: Configuration and numbering | C78: Business date is Manila time, not UTC | D78: Pass | E78: backend/test/configuration.test.js backend/test/dashboard.test.js backend/test/operations.test.js | F78: is Manila time near midnight UTC, not the UTC date "This Month" runs from the 1st of the Manila month; a policy at 00:30 Manila on the 1st counts, 23:30 the day before does not defaults business-date columns to the Manila date (numbering_business_date)
A79: BV-CFG-006 | B79: Configuration and numbering | C79: Company logo and favicon on System Settings | D79: Pass | E79: backend/test/system-settings.test.js backend/test/system-settings.test.js | F79: adds a logo preset by URL and by file upload, then removes it uploads a favicon and rejects a disallowed type | I79: /master/configuration/system-settings | J79: opened clean
A80: BV-CFG-007 | B80: Configuration and numbering | C80: Numbering series listed with next-number preview | D80: Pass | E80: backend/test/numbering.test.js backend/test/numbering.test.js | F80: seeds a series for every code the application uses, with unique active prefixes and the default pattern lists series with the current counter and next-number preview | I80: /master/configuration/document-numbering | J80: opened clean
A81: BV-CFG-008 | B81: Configuration and numbering | C81: Set the next official receipt number forward | D81: Pass | E81: backend/test/numbering.test.js backend/test/numbering.test.js | F81: sets the next number forward only updates a series with validation, unique prefixes and an audit entry
A82: BV-CFG-009 | B82: Configuration and numbering | C82: Pattern errors shown in the preview | D82: Pass | E82: backend/test/numbering.test.js backend/test/numbering.test.js | F82: previews unsaved changes and reports pattern errors formats every token; optional {BRANCH} / {LOB} drop with their separator
A83: BV-CFG-010 | B83: Configuration and numbering | C83: Counter resets yearly, monthly or by fiscal year | D83: Pass | E83: backend/test/numbering.test.js | F83: yearly, monthly, fiscal-year and never reset the counter at the right boundary
A84: BV-CFG-011 | B84: Configuration and numbering | C84: No duplicate numbers under concurrent saves | D84: Pass | E84: backend/test/numbering.test.js backend/test/numbering.test.js | F84: parallel callers (pool and transactions) never receive the same number a rolled-back transaction gives its number back; a number already in the target table is skipped
A85: BV-CFG-012 | B85: Configuration and numbering | C85: Inactive series refuses to issue | D85: Pass | E85: backend/test/numbering.test.js | F85: an inactive or unknown series refuses to issue numbers
A86: BV-CFG-013 | B86: Configuration and numbering | C86: Numbering is restricted to system configuration | D86: Pass | E86: backend/test/numbering.test.js | F86: is restricted to system configuration
A87: BV-CFG-014 | B87: Configuration and numbering | C87: Scheduled jobs list and run now | D87: Pass | E87: backend/test/core.test.js backend/test/operations.test.js backend/test/dependencies.test.js | F87: runs a scheduled job and records the run schedules every job in general.timezone (06:00 Manila, not 06:00 UTC) and shows the zone node-cron 4 validates every seeded job schedule and schedules / stops tasks | I87: /master/configuration/schedules | J87: opened clean
A88: BV-CFG-015 | B88: Configuration and numbering | C88: A job runs once when several servers fire it | D88: Pass | E88: backend/test/go-live.test.js backend/test/go-live.test.js | F88: skips a run while another instance holds the job advisory lock runs a scheduled slot once when several instances fire it at the same time
A89: BV-CFG-016 | B89: Configuration and numbering | C89: Data retention purge keeps audit trail at least 7 years | D89: Pass | E89: backend/test/operations.test.js backend/test/operations.test.js | F89: purges rows past their retention and keeps recent, unresolved and audit rows keeps a table forever at 0 days and never purges the audit trail below 7 years
A90: BV-CFG-017 | B90: Configuration and numbering | C90: Health check and version endpoints | D90: Pass | E90: backend/test/go-live.test.js backend/test/security.test.js | F90: GET /api/health reports database connectivity and readiness; 503 while starting or when the database is down GET /api/version reports build and runtime information without sign-in
A91: BV-PCF-001 | B91: Product configurator | C91: Templates listed and opened | D91: Pass | E91: backend/test/product-configurator.test.js backend/test/motor-tariff.test.js | F91: lists seeded templates in the captured shape lists the Insurance Commission vehicle classes with the CTPL tariff and the APPA limits | I91: /product-configurator/templates | J91: opened clean
A92: BV-PCF-002 | B92: Product configurator | C92: Create, version, retire and reactivate a template | D92: Pass | E92: backend/test/product-configurator.test.js | F92: creates, updates, versions, retires and reactivates a template
A93: BV-PCF-003 | B93: Product configurator | C93: Users without products permission cannot change templates | D93: Pass | E93: backend/test/product-configurator.test.js | F93: denies writes without products permission
A94: BV-PCF-004 | B94: Product configurator | C94: Rate tables and insurer panel give a premium illustration | D94: Pass | E94: backend/test/product-configurator.test.js backend/test/product-configurator.test.js | F94: manages the insurer panel and calculates a premium illustration CRUD for every component kind used by the mock-only screens | I94: /product-configurator/rating | J94: opened clean
A95: BV-PCF-005 | B95: Product configurator | C95: Rating factors list shows which template each factor belongs to | D95: Pass | I95: /product-configurator/rating | J95: opened clean
A96: BV-PCF-006 | B96: Product configurator | C96: Coverage Builder, Acceptance Rules, Document Manager, Approval Workflows | D96: Pass | E96: backend/test/product-configurator.test.js | F96: CRUD for every component kind used by the mock-only screens | I96: /product-configurator/coverages /product-configurator/underwriting /product-configurator/documents /product-configurator/workflows | J96: opened clean opened clean opened clean opened clean
A97: BV-PCF-007 | B97: Product configurator | C97: IAR sections added, deactivated and re-added | D97: Pass | E97: backend/test/product-configurator.test.js | F97: adds, updates, deactivates and re-adds IAR sections | I97: /product-configurator/risk-mapping | J97: opened clean
A98: BV-PCF-008 | B98: Product configurator | C98: CTPL tariff change in the configurator is used by quotations | D98: Pass | E98: backend/test/motor-tariff.test.js backend/test/motor-tariff.test.js | F98: follows tariff changes made in the Product Configurator offers a 3-year CTPL and a new vehicle class once they are configured
A99: BV-PCF-009 | B99: Product configurator | C99: Invalid tariff amounts, seats and duplicate class codes refused | D99: Pass | E99: backend/test/motor-tariff.test.js | F99: refuses invalid amounts, seats and duplicate class codes
A100: BV-PCF-010 | B100: Product configurator | C100: Product configurator dashboard and analytics | D100: Pass | E100: backend/test/product-configurator.test.js | F100: analytics and dashboard return the screen shapes | G100: Reports and dashboards | H100: 58 passed, 0 failed | I100: /product-configurator/dashboard /product-configurator/analytics | J100: opened clean opened clean
...

Sheet Requirements Traceability
A1: Process ID | B1: Process area | C1: Process | D1: Type | E1: Fit score | F1: Test cases | G1: Cases | H1: Pass | I1: Not passed | J1: Backend test files | K1: Front-end test files | L1: Coverage
A2: 1.01 | B2: Client onboarding, KYC and AML | C2: Individual client record with Philippine address, mobile and TIN | D2: Ops | E2: 1 | F2: BV-PRS-001; BV-PHM-002, BV-PHM-003, BV-PHM-005; BV-AML-001 | G2: 5 | H2: 5 | I2: 0 | J2: backend/test/leads.test.js backend/test/dashboard.test.js backend/test/addresses.test.js backend/test/aml.test.js backend/test/clients.test.js | K2: brokerverse/src/agentModule/component/PhAddressFields/PhAddressFields.test.jsx brokerverse/src/module/Compliance/Compliance.test.jsx | L2: Covered: test cases and automated tests passed
A3: 1.02 | B3: Client onboarding, KYC and AML | C3: Corporate client with TIN, registered name and authorised signatories | D3: AMLC | E3: 1 | F3: BV-AML-002 | G3: 1 | H3: 1 | I3: 0 | J3: backend/test/aml.test.js backend/test/leads.test.js | K3: brokerverse/src/module/Compliance/Compliance.test.jsx | L3: Covered: test cases and automated tests passed
A4: 1.03 | B4: Client onboarding, KYC and AML | C4: Customer identification: government ID type, number and image | D4: AMLC | E4: 2 | F4: BV-POL-002, BV-POL-003; BV-AML-001; BV-PHM-007 | G4: 4 | H4: 3 | I4: 1 | J4: backend/test/quotations.test.js backend/test/quote-to-policy.test.js backend/test/aml.test.js backend/test/policies.test.js | K4: brokerverse/src/module/Compliance/Compliance.test.jsx | L4: Covered: some cases not passed (see Test Cases)
A5: 1.04 | B5: Client onboarding, KYC and AML | C5: Risk-based customer due diligence rating and enhanced due diligence | D5: AMLC | E5: 0 | F5: BV-AML-003, BV-AML-004 | G5: 2 | H5: 2 | I5: 0 | J5: backend/test/aml.test.js | L5: Covered: test cases and automated tests passed
A6: 1.05 | B6: Client onboarding, KYC and AML | C6: Beneficial ownership of juridical clients | D6: AMLC | E6: 0 | F6: BV-AML-002 | G6: 1 | H6: 1 | I6: 0 | J6: backend/test/aml.test.js | K6: brokerverse/src/module/Compliance/Compliance.test.jsx | L6: Covered: test cases and automated tests passed
A7: 1.06 | B7: Client onboarding, KYC and AML | C7: Sanctions, PEP and negative list screening | D7: AMLC | E7: 0 | F7: BV-AML-005, BV-AML-006, BV-AML-007 | G7: 3 | H7: 3 | I7: 0 | J7: backend/test/aml.test.js | L7: Covered: test cases and automated tests passed
A8: 1.07 | B8: Client onboarding, KYC and AML | C8: Covered and suspicious transaction monitoring and AMLC reporting | D8: AMLC | E8: 0 | F8: BV-AML-008, BV-AML-009, BV-AML-010, BV-AML-011 | G8: 4 | H8: 4 | I8: 0 | J8: backend/test/aml.test.js | L8: Covered: test cases and automated tests passed
A9: 1.08 | B9: Client onboarding, KYC and AML | C9: KYC and transaction record retention (5 years or more) | D9: AMLC | E9: 2 | F9: BV-AML-012; BV-NPC-010 | G9: 2 | H9: 2 | I9: 0 | J9: backend/test/aml.test.js backend/test/privacy.test.js | K9: brokerverse/src/module/Compliance/Compliance.test.jsx | L9: Covered: test cases and automated tests passed
A10: 1.09 | B10: Client onboarding, KYC and AML | C10: Single client view across policies, claims, renewals and endorsements | D10: Ops | E10: 2 | F10: BV-PRS-001 to BV-PRS-012 (all 12); BV-E2E-001 | G10: 13 | H10: 13 | I10: 0 | J10: backend/test/leads.test.js backend/test/dashboard.test.js backend/test/clients.test.js backend/test/hardening.test.js backend/test/scope.test.js backend/test/core.test.js | K10: brokerverse/src/services/__tests__/leadService.test.js | L10: Covered: test cases and automated tests passed
A11: 1.10 | B11: Client onboarding, KYC and AML | C11: Privacy notice and consent per purpose at onboarding | D11: NPC | E11: 2 | F11: BV-SEC-034; BV-NPC-009 | G11: 2 | H11: 2 | I11: 0 | J11: backend/test/privacy.test.js | L11: Covered: test cases and automated tests passed
A12: 2.01 | B12: Prospecting and sales pipeline | C12: Lead capture by line (motor, fire, IAR, employee benefits), retail or corporate, with bulk upload | D12: Ops | E12: 2 | F12: BV-PRS-001, BV-PRS-002, BV-PRS-005 | G12: 3 | H12: 3 | I12: 0 | J12: backend/test/leads.test.js backend/test/dashboard.test.js | K12: brokerverse/src/services/__tests__/leadService.test.js | L12: Covered: test cases and automated tests passed
A13: 2.03 | B13: Prospecting and sales pipeline | C13: Lead status pipeline and conversion funnel | D13: Ops | E13: 2 | F13: BV-PRS-001 to BV-PRS-012 (all 12) | G13: 12 | H13: 12 | I13: 0 | J13: backend/test/leads.test.js backend/test/dashboard.test.js backend/test/clients.test.js backend/test/hardening.test.js backend/test/scope.test.js backend/test/reports.test.js | K13: brokerverse/src/services/__tests__/leadService.test.js | L13: Covered: test cases and automated tests passed
A14: 2.04 | B14: Prospecting and sales pipeline | C14: Sales activities: calls, meetings, follow-up tasks and reminders | D14: Ops | E14: 0 | F14: BV-PKG-001; BV-MYW-005 | G14: 2 | H14: 1 | I14: 1 | J14: backend/test/my-work.test.js | K14: brokerverse/src/module/MyWork/logic.test.js | L14: Covered: some cases not passed (see Test Cases)
A15: 2.05 | B15: Prospecting and sales pipeline | C15: Lead assignment to account executives and team visibility | D15: Ops | E15: 1 | F15: BV-DST-001, BV-DST-002 | G15: 2 | H15: 2 | I15: 0 | J15: backend/test/lead-assignment.test.js backend/test/scope.test.js | L15: Covered: test cases and automated tests passed
A16: 2.06 | B16: Prospecting and sales pipeline | C16: Sales targets and sales dashboard | D16: Ops | E16: 2 | F16: BV-DSH-001 to BV-DSH-008 (all 8) | G16: 8 | H16: 8 | I16: 0 | J16: backend/test/dashboard.test.js backend/test/role-access.test.js backend/test/reports.test.js | L16: Covered: test cases and automated tests passed
A17: 2.07 | B17: Prospecting and sales pipeline | C17: Dealer, bank and affinity channel referrals (captive agency, motor dealer branches) | D17: Ops | E17: 1 | F17: BV-DST-003, BV-DST-004, BV-DST-005 | G17: 3 | H17: 3 | I17: 0 | J17: backend/test/distribution-channels.test.js backend/test/motor-programmes.test.js backend/test/commission.test.js | L17: Covered: test cases and automated tests passed
A18: 2.08 | B18: Prospecting and sales pipeline | C18: Marketing campaigns to consenting clients | D18: Ops | E18: 1 | F18: BV-DST-010 | G18: 1 | H18: 1 | I18: 0 | J18: backend/test/campaigns.test.js | K18: brokerverse/src/module/Distribution/Distribution.test.jsx | L18: Covered: test cases and automated tests passed
A19: 3.01 | B19: Quotation and insurer comparison | C19: Quick quote of packaged products from insurer rate tables | D19: Ops | E19: 2 | F19: BV-QQT-001 | G19: 1 | H19: 1 | I19: 0 | J19: backend/test/motor-tariff.test.js backend/test/packages.test.js | L19: Covered: test cases and automated tests passed
A20: 3.02 | B20: Quotation and insurer comparison | C20: Side-by-side comparison of insurers on screen | D20: Ops | E20: 2 | F20: BV-QQT-007 | G20: 1 | H20: 1 | I20: 0 | J20: backend/test/packages.test.js | L20: Covered: test cases and automated tests passed
A21: 3.03 | B21: Quotation and insurer comparison | C21: Client-facing comparison and recommendation report | D21: Ops | E21: 1 | F21: BV-DST-009 | G21: 1 | H21: 1 | I21: 0 | J21: backend/test/comparison-reports.test.js | L21: Covered: test cases and automated tests passed
A22: 3.04 | B22: Quotation and insurer comparison | C22: Motor quotation: own damage, acts of nature, VTPL BI/PD, APPA, accessories | D22: Ops | E22: 2 | F22: BV-QUO-001, BV-QUO-003; BV-QQT-001 | G22: 3 | H22: 3 | I22: 0 | J22: backend/test/quotations.test.js backend/test/motor-tariff.test.js | K22: brokerverse/src/agentModule/quoteModule/coverageDetails/coverageDetailsCard/coverageInputErrors.test.js | L22: Covered: test cases and automated tests passed
A23: 3.05 | B23: Quotation and insurer comparison | C23: Server-side pricing with premium taxes (VAT, DST, LGT, FST) | D23: BIR | E23: 2 | F23: BV-MST-020; BV-TAX-007, BV-TAX-008 | G23: 3 | H23: 3 | I23: 0 | J23: backend/test/premium-charges.test.js backend/test/money-single-source.test.js | L23: Covered: test cases and automated tests passed
A24: 3.06 | B24: Quotation and insurer comparison | C24: Quotation for non-motor lines from insurer terms | D24: Ops | E24: 2 | F24: BV-RFQ-001, BV-RFQ-003 | G24: 2 | H24: 2 | I24: 0 | J24: backend/test/placement.test.js backend/test/request-for-quotation.test.js | L24: Covered: test cases and automated tests passed
A25: 3.07 | B25: Quotation and insurer comparison | C25: Discount control taken from broker commission | D25: Ops | E25: 2 | F25: BV-QQT-005 | G25: 1 | H25: 1 | I25: 0 | J25: backend/test/uat-disconnects.test.js backend/test/quotations.test.js | L25: Covered: test cases and automated tests passed
A26: 3.08 | B26: Quotation and insurer comparison | C26: Online client approval of the quotation | D26: Ops | E26: 2 | F26: BV-QUO-006, BV-QUO-010 | G26: 2 | H26: 1 | I26: 1 | J26: backend/test/customer-response.test.js backend/test/quotations.test.js | L26: Covered: some cases not passed (see Test Cases)
A27: 3.09 | B27: Quotation and insurer comparison | C27: Quotation validity, expiry and maker-checker | D27: Ops | E27: 2 | F27: BV-QUO-012 | G27: 1 | H27: 1 | I27: 0 | J27: backend/test/quotations.test.js | L27: Covered: test cases and automated tests passed
A28: 3.10 | B28: Quotation and insurer comparison | C28: Electronic signature of proposal and acceptance | D28: Ops | E28: 1 | F28: BV-BRD-004 | G28: 1 | H28: 1 | I28: 0 | J28: backend/test/branding.test.js | L28: Covered: test cases and automated tests passed
A29: 3.11 | B29: Quotation and insurer comparison | C29: Product rules from the Product Configurator drive the quotation | D29: Ops | E29: 1 | F29: BV-PCF-001 to BV-PCF-010 (all 10); BV-PCR-001, BV-PCR-002, BV-PCR-003, BV-PCR-004; BV-PKG-002 | G29: 15 | H29: 14 | I29: 1 | J29: backend/test/product-configurator.test.js backend/test/motor-tariff.test.js backend/test/product-rules-in-flow.test.js | L29: Covered: some cases not passed (see Test Cases)
A30: 4.01 | B30: RFQ, placement, co-insurance and reinsurance | C30: Request for Quotation (broker slip) to several insurers by e-mail | D30: Ops | E30: 2 | F30: BV-RFQ-001, BV-RFQ-002 | G30: 2 | H30: 2 | I30: 0 | J30: backend/test/placement.test.js backend/test/request-for-quotation.test.js | L30: Covered: test cases and automated tests passed
A31: 4.02 | B31: RFQ, placement, co-insurance and reinsurance | C31: Record insurer offers and declines with terms | D31: Ops | E31: 2 | F31: BV-RFQ-003 | G31: 1 | H31: 1 | I31: 0 | J31: backend/test/placement.test.js backend/test/request-for-quotation.test.js | L31: Covered: test cases and automated tests passed
A32: 4.03 | B32: RFQ, placement, co-insurance and reinsurance | C32: Compare offers, best offer, market capacity and hit ratio per insurer | D32: Ops | E32: 2 | F32: BV-RFQ-003, BV-RFQ-013 | G32: 2 | H32: 2 | I32: 0 | J32: backend/test/placement.test.js backend/test/request-for-quotation.test.js backend/test/reports.test.js | L32: Covered: test cases and automated tests passed
A33: 4.04 | B33: RFQ, placement, co-insurance and reinsurance | C33: Placement slip to lead and co-insurers with confirmation per insurer | D33: Ops | E33: 2 | F33: BV-RFQ-006 | G33: 1 | H33: 1 | I33: 0 | J33: backend/test/placement.test.js | L33: Covered: test cases and automated tests passed
A34: 4.05 | B34: RFQ, placement, co-insurance and reinsurance | C34: Co-insurance shares, payables and taxes split per participant | D34: Ops | E34: 2 | F34: BV-RFQ-004, BV-RFQ-005; BV-POL-007; BV-REM-006 | G34: 4 | H34: 4 | I34: 0 | J34: backend/test/placement.test.js backend/test/posting-rules.test.js backend/test/remittance.test.js | L34: Covered: test cases and automated tests passed
... A39: 4.11 | B39: RFQ, placement, co-insurance and reinsurance | C39: Reinsurance recoveries and reinsurer statement reconciliation | D39: Ops | E39: 2 | F39: BV-RIN-005 | G39: 1 | H39: 1 | I39: 0 | J39: backend/test/reinsurance.test.js | L39: Covered: test cases and automated tests passed
A40: 5.01 | B40: Policy issuance, documents and motor (CTPL, LTO) | C40: Issue policy from bound placement or accepted quotation, create client, bill premium; policy statuses | D40: Ops | E40: 2 | F40: BV-POL-001; BV-E2E-001 to BV-E2E-023 (all 23) | G40: 24 | H40: 24 | I40: 0 | J40: backend/test/quotations.test.js backend/test/core.test.js backend/test/masters.test.js backend/test/leads.test.js backend/test/dashboard.test.js backend/test/customer-response.test.js backend/test/posting-rules.test.js backend/test/receipts.test.js and 10 more (sheet Traceability) | K40: brokerverse/src/utils/menuPermissions.test.js | L40: Covered: test cases and automated tests passed
A41: 5.02 | B41: Policy issuance, documents and motor (CTPL, LTO) | C41: Record a policy already issued by the insurer | D41: Ops | E41: 2 | F41: BV-RFQ-011 | G41: 1 | H41: 1 | I41: 0 | J41: backend/test/placement.test.js | L41: Covered: test cases and automated tests passed
A42: 5.03 | B42: Policy issuance, documents and motor (CTPL, LTO) | C42: Policy schedule and documents generated and e-mailed to the client | D42: Ops | E42: 2 | F42: BV-POL-009; BV-PCR-008; BV-BRD-003 | G42: 3 | H42: 3 | I42: 0 | J42: backend/test/policies.test.js backend/test/printing.test.js backend/test/receipts.test.js backend/test/product-rules-in-flow.test.js backend/test/branding.test.js backend/test/email-documents.test.js | K42: brokerverse/src/module/ProductConfigurator/shared/ruleLogic.test.js | L42: Covered: test cases and automated tests passed
A43: 5.04 | B43: Policy issuance, documents and motor (CTPL, LTO) | C43: Upload of the insurer policy document and attachments | D43: Ops | E43: 2 | F43: BV-POL-001 to BV-POL-015 (all 15) | G43: 15 | H43: 15 | I43: 0 | J43: backend/test/quotations.test.js backend/test/quote-to-policy.test.js backend/test/packages.test.js backend/test/uat-disconnects.test.js backend/test/product-classification.test.js backend/test/posting-rules.test.js backend/test/commission-taxes.test.js backend/test/policies.test.js and 7 more (sheet Traceability) | K43: brokerverse/src/utils/canOpen.test.js | L43: Covered: test cases and automated tests passed
A44: 5.05 | B44: Policy issuance, documents and motor (CTPL, LTO) | C44: Motor details: chassis, motor, plate or MV file number, mortgagee, photos | D44: Ops | E44: 2 | F44: BV-POL-001, BV-POL-002 | G44: 2 | H44: 2 | I44: 0 | J44: backend/test/quotations.test.js backend/test/policies.test.js | L44: Covered: test cases and automated tests passed
A45: 5.06 | B45: Policy issuance, documents and motor (CTPL, LTO) | C45: CTPL tariff per vehicle class, 1-year and 3-year, never discounted | D45: IC | E45: 2 | F45: BV-QQT-002, BV-QQT-003, BV-QQT-005; BV-PCF-008, BV-PCF-009 | G45: 5 | H45: 5 | I45: 0 | J45: backend/test/motor-tariff.test.js backend/test/uat-disconnects.test.js | L45: Covered: test cases and automated tests passed
A46: 5.07 | B46: Policy issuance, documents and motor (CTPL, LTO) | C46: CTPL certificate of cover authentication with the IC-accredited system and LTO | D46: IC | E46: 1 | F46: BV-INT-004, BV-INT-005 | G46: 2 | H46: 2 | I46: 0 | J46: backend/test/integrations.test.js | K46: brokerverse/src/module/Integrations/IntegrationScreens.test.jsx | L46: Covered: test cases and automated tests passed
A47: 5.08 | B47: Policy issuance, documents and motor (CTPL, LTO) | C47: Brand-new vehicle programme: dealer sale, financing bank mortgagee clause, free first-year cover | D47: Ops | E47: 1 | F47: BV-DST-004, BV-DST-005; BV-QQT-003 | G47: 3 | H47: 3 | I47: 0 | J47: backend/test/motor-programmes.test.js backend/test/motor-tariff.test.js | L47: Covered: test cases and automated tests passed
A48: 5.09 | B48: Policy issuance, documents and motor (CTPL, LTO) | C48: Bulk issuance: fleet schedules and group policies | D48: Ops | E48: 1 | F48: BV-DST-006; BV-POL-010 | G48: 2 | H48: 2 | I48: 0 | J48: backend/test/fleet-schedules.test.js backend/test/policies.test.js backend/test/placement.test.js backend/test/upload-templates.test.js | L48: Covered: test cases and automated tests passed
A49: 5.11 | B49: Policy issuance, documents and motor (CTPL, LTO) | C49: Lines placed: motor, fire, IAR, CAR, EAR, marine, CGL, money, PA, travel, EB, surety | D49: Ops | E49: 2 | F49: BV-POL-005; BV-E2E-001 to BV-E2E-023 (all 23) | G49: 24 | H49: 24 | I49: 0 | J49: backend/test/uat-disconnects.test.js backend/test/product-classification.test.js backend/test/core.test.js backend/test/masters.test.js backend/test/leads.test.js backend/test/quotations.test.js backend/test/dashboard.test.js backend/test/customer-response.test.js and 10 more (sheet Traceability) | K49: brokerverse/src/utils/menuPermissions.test.js | L49: Covered: test cases and automated tests passed
A50: 5.12 | B50: Policy issuance, documents and motor (CTPL, LTO) | C50: Marine open cover with certificates and declarations | D50: Ops | E50: 0 | F50: BV-DST-007 | G50: 1 | H50: 1 | I50: 0 | J50: backend/test/marine-open-cover.test.js | L50: Covered: test cases and automated tests passed
A51: 6.01 | B51: Endorsements and cancellations | C51: Motor endorsements: personal details, motor details, coverage change, extension | D51: Ops | E51: 2 | F51: BV-END-001 | G51: 1 | H51: 1 | I51: 0 | J51: backend/test/endorsements.test.js | L51: Covered: test cases and automated tests passed
A52: 6.02 | B52: Endorsements and cancellations | C52: Non-motor endorsements: premium change | D52: Ops | E52: 2 | F52: BV-END-001 to BV-END-013 (all 13) | G52: 13 | H52: 13 | I52: 0 | J52: backend/test/endorsements.test.js backend/test/posting-rules.test.js backend/test/commission-taxes.test.js backend/test/accounting-followups.test.js backend/test/packages.test.js backend/test/direct-bill.test.js backend/test/numbering.test.js backend/test/uat-disconnects.test.js and 2 more (sheet Traceability) | L52: Covered: test cases and automated tests passed
A53: 6.03 | B53: Endorsements and cancellations | C53: Re-pricing of coverage change with taxes on the server | D53: Ops | E53: 2 | F53: BV-END-001 | G53: 1 | H53: 1 | I53: 0 | J53: backend/test/endorsements.test.js | L53: Covered: test cases and automated tests passed
A54: 6.04 | B54: Endorsements and cancellations | C54: Cancellation full, partial or pro-rata with return premium computed | D54: Ops | E54: 1 | F54: BV-END-011, BV-END-012; BV-OPX-003, BV-OPX-004 | G54: 4 | H54: 4 | I54: 0 | J54: backend/test/endorsements.test.js backend/test/posting-rules.test.js backend/test/ops-accounting.test.js | L54: Covered: test cases and automated tests passed
A55: 6.05 | B55: Endorsements and cancellations | C55: Short-period rate scale when the insured cancels | D55: Ops | E55: 0 | F55: BV-OPX-003 | G55: 1 | H55: 1 | I55: 0 | J55: backend/test/ops-accounting.test.js | L55: Covered: test cases and automated tests passed
A56: 6.06 | B56: Endorsements and cancellations | C56: Return premium: refund to client, netting on insurer remittance, commission clawback | D56: Ops | E56: 2 | F56: BV-END-004; BV-OPX-004 | G56: 2 | H56: 2 | I56: 0 | J56: backend/test/posting-rules.test.js backend/test/commission-taxes.test.js backend/test/endorsements.test.js backend/test/ops-accounting.test.js backend/test/remittance.test.js backend/test/commission.test.js | L56: Covered: test cases and automated tests passed
A57: 6.07 | B57: Endorsements and cancellations | C57: Completion with insurer endorsement document and client notice | D57: Ops | E57: 2 | F57: BV-END-008 | G57: 1 | H57: 1 | I57: 0 | J57: backend/test/endorsements.test.js backend/test/numbering.test.js | L57: Covered: test cases and automated tests passed
A58: 6.08 | B58: Endorsements and cancellations | C58: Cancellation for non-payment from the premium warranty monitor | D58: IC | E58: 2 | F58: BV-END-013; BV-COL-007 | G58: 2 | H58: 2 | I58: 0 | J58: backend/test/credit-control.test.js | L58: Covered: test cases and automated tests passed
A59: 7.01 | B59: Renewals and retention | C59: Renewal pipeline 90 days before expiry, notices at 60, 30 and 15 days | D59: Ops | E59: 2 | F59: BV-REN-002, BV-REN-016 | G59: 2 | H59: 2 | I59: 0 | J59: backend/test/renewals.test.js backend/test/configuration.test.js backend/test/operations.test.js | L59: Covered: test cases and automated tests passed
A60: 7.02 | B60: Renewals and retention | C60: Renewal re-rating, negotiation with the insurer and renewal quotation | D60: Ops | E60: 2 | F60: BV-REN-006 | G60: 1 | H60: 1 | I60: 0 | J60: backend/test/renewals.test.js backend/test/money-single-source.test.js | L60: Covered: test cases and automated tests passed
A61: 7.03 | B61: Renewals and retention | C61: Renewal batch (up to 500 policies) | D61: Ops | E61: 2 | F61: BV-REN-001 to BV-REN-016 (all 16) | G61: 16 | H61: 16 | I61: 0 | J61: backend/test/renewals.test.js backend/test/uat-disconnects.test.js backend/test/packages.test.js backend/test/role-access.test.js backend/test/configuration.test.js backend/test/operations.test.js | K61: brokerverse/src/utils/menuPermissions.test.js | L61: Covered: test cases and automated tests passed
A62: 7.04 | B62: Renewals and retention | C62: At-risk scoring, retention analytics, lapse management and win-back | D62: Ops | E62: 2 | F62: BV-REN-009, BV-REN-012 | G62: 2 | H62: 2 | I62: 0 | J62: backend/test/renewals.test.js | L62: Covered: test cases and automated tests passed
A63: 7.06 | B63: Renewals and retention | C63: Renewal of placed and co-insured risks through the placement journey | D63: Ops | E63: 2 | F63: BV-RFQ-012 | G63: 1 | H63: 1 | I63: 0 | J63: backend/test/placement.test.js backend/test/product-classification.test.js | L63: Covered: test cases and automated tests passed
A64: 7.07 | B64: Renewals and retention | C64: Renewal notices by SMS or messaging app | D64: Ops | E64: 0 | F64: BV-INT-003 | G64: 1 | H64: 1 | I64: 0 | J64: backend/test/integrations.test.js | L64: Covered: test cases and automated tests passed
A65: 8.01 | B65: Billing, collection, credit control and receipts | C65: Premium bill on issue, endorsement and renewal; invoice e-mailed | D65: Ops | E65: 2 | F65: BV-RCT-001 to BV-RCT-013 (all 13); BV-BRD-003 | G65: 14 | H65: 14 | I65: 0 | J65: backend/test/receipts.test.js backend/test/uat-disconnects.test.js backend/test/printing.test.js backend/test/hardening.test.js backend/test/bank-reconciliation.test.js backend/test/posting-rules.test.js backend/test/credit-control.test.js backend/test/accounting.test.js and 2 more (sheet Traceability) | L65: Covered: test cases and automated tests passed
A66: 8.02 | B66: Billing, collection, credit control and receipts | C66: Payment capture (cash, cheque, transfer, online) with proof for verification | D66: Ops | E66: 2 | F66: BV-PAY-001 to BV-PAY-010 (all 10) | G66: 10 | H66: 10 | I66: 0 | J66: backend/test/policy-payments.test.js backend/test/payment-segregation.test.js backend/test/payments.test.js | L66: Covered: test cases and automated tests passed
A67: 8.03 | B67: Billing, collection, credit control and receipts | C67: Official receipt posting by Accounting, partial payments, bulk upload and bulk print | D67: Ops | E67: 2 | F67: BV-RCT-007 | G67: 1 | H67: 1 | I67: 0 | J67: backend/test/receipts.test.js | L67: Covered: test cases and automated tests passed
A68: 8.04 | B68: Billing, collection, credit control and receipts | C68: Receipt numbering continuity and printing on letterhead with TIN | D68: BIR | E68: 2 | F68: BV-CFG-007; BV-POL-009 | G68: 2 | H68: 2 | I68: 0 | J68: backend/test/numbering.test.js backend/test/policies.test.js backend/test/printing.test.js backend/test/receipts.test.js | L68: Covered: test cases and automated tests passed
A69: 8.05 | B69: Billing, collection, credit control and receipts | C69: Returned cheques (DAIF, DAUD) cancel the receipt and reopen the bill | D69: Ops | E69: 2 | F69: BV-RCT-008; BV-ACX-002 | G69: 2 | H69: 2 | I69: 0 | J69: backend/test/bank-reconciliation.test.js backend/test/ops-accounting.test.js backend/test/receipts.test.js | L69: Covered: test cases and automated tests passed
A70: 8.06 | B70: Billing, collection, credit control and receipts | C70: Online payment links with automatic receipt | D70: Ops | E70: 2 | F70: BV-POL-015; BV-PAY-008 | G70: 2 | H70: 2 | I70: 0 | J70: backend/test/payments.test.js | L70: Covered: test cases and automated tests passed
A71: 8.07 | B71: Billing, collection, credit control and receipts | C71: Receivables ageing and automatic collection reminders | D71: Ops | E71: 2 | F71: BV-COL-002, BV-COL-003 | G71: 2 | H71: 2 | I71: 0 | J71: backend/test/collections.test.js | L71: Covered: test cases and automated tests passed
A72: 8.08 | B72: Billing, collection, credit control and receipts | C72: Premium payment warranty and credit terms per insurer (Insurance Code, IC rules) | D72: IC | E72: 2 | F72: BV-COL-005, BV-COL-006, BV-COL-010; BV-CLM-003 | G72: 4 | H72: 4 | I72: 0 | J72: backend/test/credit-control.test.js backend/test/numbering.test.js backend/test/uat-disconnects.test.js backend/test/claims.test.js | L72: Covered: test cases and automated tests passed
A73: 8.09 | B73: Billing, collection, credit control and receipts | C73: Instalment billing with separate instalment invoices | D73: Ops | E73: 1 | F73: BV-RCT-011, BV-RCT-012; BV-ACX-003 | G73: 3 | H73: 3 | I73: 0 | J73: backend/test/credit-control.test.js backend/test/ops-accounting.test.js | L73: Covered: test cases and automated tests passed
... A79: 9.03 | B79: Remittance, direct bill and insurer reconciliation | C79: Remittance approval within Authority Matrix limits and settlement by payment voucher | D79: Ops | E79: 2 | F79: BV-REM-001 to BV-REM-015 (all 15); BV-DSB-002 | G79: 16 | H79: 15 | I79: 1 | J79: backend/test/remittance.test.js backend/test/role-access.test.js backend/test/uat-disconnects.test.js backend/test/direct-bill.test.js backend/test/posting-rules.test.js backend/test/bank-reconciliation.test.js backend/test/credit-control.test.js backend/test/disbursements.test.js and 1 more (sheet Traceability) | L79: Covered: some cases not passed (see Test Cases)
A80: 9.05 | B80: Remittance, direct bill and insurer reconciliation | C80: Bank payment file (InstaPay, PESONet, bulk credit) for insurers and referrers | D80: Ops | E80: 0 | F80: BV-INT-007 | G80: 1 | H80: 1 | I80: 0 | J80: backend/test/integrations.test.js | K80: brokerverse/src/module/Integrations/IntegrationScreens.test.jsx | L80: Covered: test cases and automated tests passed
A81: 9.06 | B81: Remittance, direct bill and insurer reconciliation | C81: Direct bill commission debit notes with VAT and EWT | D81: BIR | E81: 2 | F81: BV-DBL-001 to BV-DBL-010 (all 10) | G81: 10 | H81: 10 | I81: 0 | J81: backend/test/direct-bill.test.js backend/test/uat-disconnects.test.js backend/test/direct-bill-client-payments.test.js backend/test/posting-rules.test.js | L81: Covered: test cases and automated tests passed
A82: 9.07 | B82: Remittance, direct bill and insurer reconciliation | C82: Agency bill processing | D82: Ops | E82: 2 | F82: BV-REM-009 | G82: 1 | H82: 1 | I82: 0 | J82: backend/test/remittance.test.js | L82: Covered: test cases and automated tests passed
A83: 9.08 | B83: Remittance, direct bill and insurer reconciliation | C83: Insurer statement of account import, matching and differences | D83: Ops | E83: 2 | F83: BV-INR-001 to BV-INR-006 (all 6) | G83: 6 | H83: 6 | I83: 0 | J83: backend/test/insurer-reconciliation.test.js backend/test/role-access.test.js | L83: Covered: test cases and automated tests passed
A84: 9.09 | B84: Remittance, direct bill and insurer reconciliation | C84: Insurer system integration (policy, premium, claims data by API) | D84: Ops | E84: 0 | F84: BV-INT-006 | G84: 1 | H84: 1 | I84: 0 | J84: backend/test/integrations.test.js | L84: Covered: test cases and automated tests passed
A85: 10.01 | B85: Commission, referrers and incentives | C85: Commission rate matrix by insurer, product, line and policy type with dates | D85: Ops | E85: 2 | F85: BV-COM-001 to BV-COM-010 (all 10) | G85: 10 | H85: 10 | I85: 0 | J85: backend/test/commission.test.js backend/test/policy-payments.test.js backend/test/accounting-followups.test.js backend/test/commission-taxes.test.js backend/test/configuration-controls.test.js backend/test/motor-tariff.test.js | L85: Covered: test cases and automated tests passed
A86: 10.02 | B86: Commission, referrers and incentives | C86: Brokerage or agency commission income per insurer per policy | D86: Ops | E86: 2 | F86: BV-COM-001 to BV-COM-010 (all 10); BV-JNL-001 to BV-JNL-016 (all 16) | G86: 26 | H86: 26 | I86: 0 | J86: backend/test/commission.test.js backend/test/policy-payments.test.js backend/test/accounting-followups.test.js backend/test/commission-taxes.test.js backend/test/configuration-controls.test.js backend/test/motor-tariff.test.js backend/test/journal.test.js backend/test/accounting.test.js and 2 more (sheet Traceability) | L86: Covered: test cases and automated tests passed
A87: 10.03 | B87: Commission, referrers and incentives | C87: Referrer and sub-agent commission chain, payable on full collection | D87: Ops | E87: 2 | F87: BV-COM-001 to BV-COM-010 (all 10) | G87: 10 | H87: 10 | I87: 0 | J87: backend/test/commission.test.js backend/test/policy-payments.test.js backend/test/accounting-followups.test.js backend/test/commission-taxes.test.js backend/test/configuration-controls.test.js backend/test/motor-tariff.test.js | L87: Covered: test cases and automated tests passed
A88: 10.04 | B88: Commission, referrers and incentives | C88: Withholding tax on commission paid, by payee type and ATC | D88: BIR | E88: 2 | F88: BV-COM-007, BV-COM-008; BV-TAX-001 | G88: 3 | H88: 3 | I88: 0 | J88: backend/test/commission-taxes.test.js backend/test/configuration-controls.test.js backend/test/period-end.test.js | L88: Covered: test cases and automated tests passed
A89: 10.05 | B89: Commission, referrers and incentives | C89: Commission payout by voucher and bulk disbursement | D89: Ops | E89: 2 | F89: BV-COM-004; BV-INT-007 | G89: 2 | H89: 2 | I89: 0 | J89: backend/test/commission.test.js backend/test/accounting-followups.test.js backend/test/integrations.test.js backend/test/disbursements.test.js | K89: brokerverse/src/module/Integrations/IntegrationScreens.test.jsx | L89: Covered: test cases and automated tests passed
A90: 10.07 | B90: Commission, referrers and incentives | C90: Commission statements for referrers and the broker | D90: Ops | E90: 2 | F90: BV-RPT-001 to BV-RPT-045 (all 45) | G90: 45 | H90: 44 | I90: 1 | J90: backend/test/reports.test.js backend/test/printing.test.js backend/test/role-access.test.js backend/test/scope.test.js backend/test/uat-disconnects.test.js backend/test/placement.test.js backend/test/posting-rules.test.js backend/test/direct-bill.test.js and 2 more (sheet Traceability) | K90: brokerverse/src/utils/menuPermissions.test.js | L90: Covered: some cases not passed (see Test Cases)
A91: 10.08 | B91: Commission, referrers and incentives | C91: Incentive programmes for account executives | D91: Ops | E91: 2 | F91: BV-INC-001 to BV-INC-006 (all 6) | G91: 6 | H91: 6 | I91: 0 | J91: backend/test/incentive.test.js backend/test/role-access.test.js | L91: Covered: test cases and automated tests passed
A92: 10.09 | B92: Commission, referrers and incentives | C92: Licence check of agents and sub-agents before paying commission | D92: IC | E92: 0 | F92: BV-ICC-003 | G92: 1 | H92: 1 | I92: 0 | J92: backend/test/ic-compliance.test.js (package B branch) | L92: Covered: test cases and automated tests passed
A93: 10.10 | B93: Commission, referrers and incentives | C93: Overriding, profit and contingent commission from insurers | D93: Ops | E93: 1 | F93: BV-BIR-010, BV-BIR-011 | G93: 2 | H93: 2 | I93: 0 | J93: backend/test/insurer-overrides.test.js | L93: Covered: test cases and automated tests passed
A94: 11.01 | B94: Claims assistance | C94: Claim registration with incident, driver, third party and documents | D94: Ops | E94: 2 | F94: BV-CLM-001 | G94: 1 | H94: 1 | I94: 0 | J94: backend/test/claims.test.js | L94: Covered: test cases and automated tests passed
A95: 11.02 | B95: Claims assistance | C95: Preliminary loss advice to the insurer by e-mail | D95: Ops | E95: 2 | F95: BV-CLM-001 to BV-CLM-015 (all 15) | G95: 15 | H95: 14 | I95: 1 | J95: backend/test/claims.test.js backend/test/role-access.test.js backend/test/accounting-followups.test.js backend/test/uat-disconnects.test.js backend/test/scope.test.js backend/test/posting-rules.test.js | L95: Covered: some cases not passed (see Test Cases)
A96: 11.03 | B96: Claims assistance | C96: Claim document checklist per line and missing document follow-up | D96: Ops | E96: 1 | F96: BV-OPX-005 | G96: 1 | H96: 1 | I96: 0 | J96: backend/test/ops-accounting.test.js | L96: Covered: test cases and automated tests passed
A97: 11.04 | B97: Claims assistance | C97: Adjuster, insurer claim number, status tracking, handling time and claims reports | D97: Ops | E97: 2 | F97: BV-CLM-005; BV-RPT-014 | G97: 2 | H97: 2 | I97: 0 | J97: backend/test/claims.test.js backend/test/reports.test.js | L97: Covered: test cases and automated tests passed
A98: 11.05 | B98: Claims assistance | C98: Settlement approval by a second user and claim letters (discharge voucher) | D98: Ops | E98: 2 | F98: BV-CLM-001 to BV-CLM-015 (all 15) | G98: 15 | H98: 14 | I98: 1 | J98: backend/test/claims.test.js backend/test/role-access.test.js backend/test/accounting-followups.test.js backend/test/uat-disconnects.test.js backend/test/scope.test.js backend/test/posting-rules.test.js | L98: Covered: some cases not passed (see Test Cases)
A99: 11.06 | B99: Claims assistance | C99: Claims paid through the broker: funds received and paid to claimant | D99: Ops | E99: 1 | F99: BV-CLM-009; BV-ACX-004 | G99: 2 | H99: 2 | I99: 0 | J99: backend/test/accounting-followups.test.js backend/test/uat-disconnects.test.js backend/test/ops-accounting.test.js backend/test/claims.test.js | L99: Covered: test cases and automated tests passed
A100: 11.07 | B100: Claims assistance | C100: Co-insurer shares of claims and settlements | D100: Ops | E100: 2 | F100: BV-CLM-001 to BV-CLM-015 (all 15) | G100: 15 | H100: 14 | I100: 1 | J100: backend/test/claims.test.js backend/test/role-access.test.js backend/test/accounting-followups.test.js backend/test/uat-disconnects.test.js backend/test/scope.test.js backend/test/posting-rules.test.js | L100: Covered: some cases not passed (see Test Cases)
A101: 11.08 | B101: Claims assistance | C101: Motor claims: repair shop, estimate and letter of authority | D101: Ops | E101: 1 | F101: BV-OPX-006 | G101: 1 | H101: 1 | I101: 0 | J101: backend/test/ops-accounting.test.js | L101: Covered: test cases and automated tests passed
A102: 12.01 | B102: Accounting, general ledger, period end and audit | C102: Double-entry general ledger fed by posting rules, each journal traced to its source | D102: Ops | E102: 2 | F102: BV-JNL-001 to BV-JNL-016 (all 16) | G102: 16 | H102: 16 | I102: 0 | J102: backend/test/journal.test.js backend/test/accounting.test.js backend/test/posting-rules.test.js backend/test/configuration-controls.test.js backend/test/accounting-flow.test.js | L102: Covered: test cases and automated tests passed
... A108: 12.07 | B108: Accounting, general ledger, period end and audit | C108: Year-end close and opening balances | D108: Ops | E108: 2 | F108: BV-PER-013; BV-GOL-008 | G108: 2 | H108: 2 | I108: 0 | J108: backend/test/period-end.test.js backend/test/upload-templates.test.js | L108: Covered: test cases and automated tests passed
A109: 12.08 | B109: Accounting, general ledger, period end and audit | C109: Financial statements: income statement, balance sheet, trial balance | D109: Ops | E109: 2 | F109: BV-PER-001 to BV-PER-016 (all 16); BV-RPT-001 to BV-RPT-045 (all 45) | G109: 61 | H109: 60 | I109: 1 | J109: backend/test/period-end.test.js backend/test/period-end-calendar.test.js backend/test/accounting.test.js backend/test/role-inheritance.test.js backend/test/bank-reconciliation.test.js backend/test/reports.test.js backend/test/printing.test.js backend/test/role-access.test.js and 5 more (sheet Traceability) | K109: brokerverse/src/utils/menuPermissions.test.js | L109: Covered: some cases not passed (see Test Cases)
A110: 12.09 | B110: Accounting, general ledger, period end and audit | C110: Multi-currency transactions and FX revaluation | D110: Ops | E110: 2 | F110: BV-JNL-003; BV-PER-011; BV-MST-013 | G110: 3 | H110: 3 | I110: 0 | J110: backend/test/journal.test.js backend/test/period-end.test.js backend/test/masters.test.js | K110: brokerverse/src/module/FinanceMastersModule/BankMaster/AccountDataView/bankAccountErrors.test.js | L110: Covered: test cases and automated tests passed
A111: 12.10 | B111: Accounting, general ledger, period end and audit | C111: Supplier invoices, input VAT, fixed assets and depreciation | D111: Ops | E111: 1 | F111: BV-ACX-005, BV-ACX-006; BV-PCH-003; BV-PKG-004 | G111: 4 | H111: 3 | I111: 1 | J111: backend/test/ops-accounting.test.js | L111: Covered: some cases not passed (see Test Cases)
A112: 13.01 | B112: Taxes and BIR compliance | C112: Premium taxes: DST (NIRC s.184), VAT 12% or premium tax per product regime, LGT by LGU, FST 2% | D112: BIR | E112: 2 | F112: BV-MST-019, BV-MST-020; BV-TAX-007 | G112: 3 | H112: 3 | I112: 0 | J112: backend/test/premium-charges.test.js | L112: Covered: test cases and automated tests passed
A113: 13.03 | B113: Taxes and BIR compliance | C113: Output VAT on commission and VAT Summary (2550Q working paper) | D113: BIR | E113: 2 | F113: BV-TAX-002; BV-RPT-036 | G113: 2 | H113: 2 | I113: 0 | J113: backend/test/commission-taxes.test.js | L113: Covered: test cases and automated tests passed
A114: 13.04 | B114: Taxes and BIR compliance | C114: Percentage tax for a non-VAT broker or agent (2551Q) | D114: BIR | E114: 1 | F114: BV-BIR-006; BV-DBL-008 | G114: 2 | H114: 2 | I114: 0 | J114: backend/test/bir-forms.test.js backend/test/direct-bill.test.js | L114: Covered: test cases and automated tests passed
...

Sheet Defects and Observations
A1: Defect ID | B1: Title | C1: Module | D1: Severity | E1: Status | F1: Type | G1: Description | H1: Workaround | I1: Target | J1: Linked test cases
A2: BV-DEF-001 | B2: Front-end library react-router has a moderate security advisory (open redirect) | C2: Sign-in and security | D2: Medium | E2: Open | F2: Defect | G2: npm audit of the front-end runtime dependencies reports 2 moderate findings, both in react-router (open redirect). The fixed version is a new major release. Backend runtime dependencies report 0 vulnerabilities. | H2: The application builds its navigation targets from its own menu and routes and does not redirect to addresses taken from the URL. Keep the web server allowing only the application origin. | I2: Next minor release: upgrade react-router to the fixed major version and re-test navigation | J2: BV-SEC-032
A3: BV-DEF-002 | B3: Data privacy features not built: consent capture, data subject request register, anonymisation | C3: Sign-in and security | D3: Medium | E3: Closed | F3: Gap | G3: No screen records client consent (date, purpose, channel), no register tracks data subject access or erasure requests, and there is no function to anonymise an inactive client. Needed for Data Privacy Act compliance processes. | H3: Keep consent forms and the request log outside the system (signed forms filed against the client code; request register kept by the Data Protection Officer). | I3: Closed: fixed on 03 October 2026 (Master > Data Privacy, client Data privacy tab); re-tested BV-SEC-034 and BV-SEC-035 | J3: BV-SEC-034, BV-SEC-035
A4: BV-DEF-003 | B4: Application-level encryption covers only two-step verification secrets | C4: Sign-in and security | D4: Medium | E4: Closed | F4: Gap | G4: Only TOTP secrets are encrypted with DATA_ENCRYPTION_KEY. Client personal data (TIN, ID numbers, contact details) is stored in plain database columns. | H4: Use encrypted storage for the database server and backups, restrict database access to the support team, and keep backups encrypted. | I4: Closed: package B merged into the release on 04 October 2026. TIN, government ID numbers and bank account numbers are encrypted with PII_ENCRYPTION_KEY (blind index for the exact TIN search, key rotation); re-tested BV-SEC-033, BV-NPC-007 and BV-NPC-008 on the release, and the masking run of 04 October 2026 read the encrypted columns in clear. | J4: BV-SEC-033, BV-NPC-007, BV-NPC-008
A5: BV-DEF-004 | B5: Product configurator component list does not show the template; per-template rating factors look duplicated | C5: Product configurator | D5: Low | E5: Closed | F5: Defect | G5: On Product Configurator > Rating Engine (and the other component lists) the rows do not show which template they belong to. Factors with the same name on different templates appear as duplicates. | H5: Open the factor to see its template, or filter by template where the screen offers it. | I5: Closed: fixed on 03 October 2026 (Template column on the component lists); re-tested BV-PCF-005 | J5: BV-PCF-005
A6: BV-OBS-005 | B6: Renewal of a policy expired beyond the grace plus lapsed-renewal window is refused | C6: Renewals | D6: Low | E6: Closed | F6: Observation | G6: A renewal requested for a policy that expired more than grace days plus lapsed-renewal days ago is refused (HTTP 422). This is by design: such a risk is quoted as new business. In the UAT cycle 3 migrated policies were refused this way. | H6: Quote the client as new business from the prospect or client record. | I6: Closed: by design; window settings confirmed with the client at configuration | J6: BV-REN-010
A7: BV-DEF-006 | B7: Premium Taxes & LGU Rates: product list of the charges calculator does not load for Accounting | C7: Masters | D7: Low | E7: Closed | F7: Defect | G7: Screen check of 03 October 2026: signed in as liza.quiambao (accounting) or teresa.villaroman (accounting-manager), Master > Finance > Premium Taxes & LGU Rates opens, but its request GET /placements/options is refused with 403 (the role has no placement read permission). The product drop-down of the charges calculator stays empty. Rules and LGU rates can still be maintained. | H7: Run the charges calculation as the System Administrator, or check the charges on a test quotation. | I7: Closed: fixed on 03 October 2026 (screen reads the product list with a permission Accounting holds); re-tested BV-MST-019, BV-RBA-016, BV-RBA-019 | J7: BV-MST-019, BV-RBA-016, BV-RBA-019
A8: BV-OBS-007 | B8: Menu group Master > Generals > Organization has an address that opens "Page not found" | C8: Screen checks (all menus) | D8: Low | E8: Closed | F8: Observation | G8: The menu group Organization carries its own address (/master/generals/organization) with no screen behind it. Typing the address shows "Page not found" for every user, including the administrator. Company and Branch under it open normally. No data is shown. | H8: Open Company or Branch from the menu. | I8: Closed: fixed on 03 October 2026 (menu groups carry no address) | J8: BV-SCR-018
A9: BV-OBS-008 | B9: Accounts > Incentive > My Programs: Achievement Overview card extends past the right edge at 1440 px | C9: Incentives | D9: Low | E9: Closed | F9: Observation | G9: Screen check at 1440 x 900: the Achievement Overview card on My Programs is wider than the content area and is cut off on the right (administrator and accounting users). | H9: Collapse the side menu or zoom the browser to 90%. | I9: Closed: fixed on 03 October 2026 (card fits at 1440 px); re-tested BV-RBA-016 and BV-RBA-019 | J9: BV-SCR-013, BV-RBA-016, BV-RBA-019
A10: BV-DEF-009 | B10: A policy whose premium is only the CTPL tariff cannot be cancelled (no net premium to compute a return on) | C10: Endorsements and cancellations | D10: Medium | E10: Closed | F10: Defect | G10: The computed cancellation return (merged with the operations and accounting extensions) refused every policy with a net premium of 0 with HTTP 409. A CTPL-only policy carries the Insurance Commission tariff as its gross premium, taxes included, and no net premium, so the premium warranty cancellation for non-payment of such a policy was impossible (UAT cycle, POL-2026-00027). | H10: None in the application; the policy could only be cancelled by hand in the old system. | I10: Fixed in the release: the return of a tariff-only policy is computed on the tariff amount with no premium tax of its own (tariffOnly in the calculation); test in backend/test/ops-accounting.test.js. Re-tested in the UAT cycle (cancellation for non-payment). | J10: BV-END-013, BV-COL-007, BV-OPX-004
A11: BV-DEF-010 | B11: No Compliance Officer designation in the Designation master | C11: Masters | D11: Low | E11: Closed | F11: Defect | G11: The compliance officer role is delivered, but a user with that role could not be given the designation "Compliance Officer": the Designation master (and the Department master) had no entry for it, so the staff record was refused. | H11: Add the designation by hand on Master > Generals > Employee Management > Designation. | I11: Fixed in the release: department CMP (Compliance) and designation DSG-CPO (Compliance Officer) delivered in the masters seed; test in backend/test/masters.test.js. | J11: BV-USR-002, BV-MST-010
A12: BV-DEF-011 | B12: Data masking: the mobile number an SMS or Viber message was sent to stays in the integration outbox | C12: Go-live workbench and environments | D12: High | E12: Closed | F12: Defect | G12: The recipient ("to") of a queued SMS or Viber message is a mobile number, but the masking rule for recipient fields handled e-mail addresses only. On a masked copy of the UAT database the verification found 18 client mobile numbers left in integration_outbox.payload (exit code 4). | H12: Empty the integration outbox of the copy by hand before handing it over. | I12: Fixed in the release: a recipient field masks mobile numbers as well as e-mail addresses; test in backend/test/mask-data.test.js. Re-run of the masking on a copy of the UAT database: verification clean. | J12: BV-GLW-010, BV-GLW-011
... A15: BV-DEF-014 | B15: Incentive statement refused (400) for an agent with a semi-annual result | C15: Incentives | D15: Medium | E15: Closed | F15: Defect | G15: The agent incentive statement labels the periods of the last payment and of the approved results. A result of a semi-annual or quarterly program is keyed by its half or quarter (2026-H1, 2026-Q3); the period reader knew months and month labels only, so the statement of such an agent answered HTTP 400 "period must be YYYY-MM" whenever that result was in the last payment group (seen on a database server in Manila time, where the monthly and the half-year payments share the same timestamp). Found by the regression run of the release verification. | H15: Open the statement of a month with no semi-annual result in the last payment. | I15: Fixed in the release: the period reader understands quarter and half-year keys (label "January to June 2026"); test in backend/test/incentive.test.js. Re-run of the regression suite: all passed. | J15: BV-INC-004, BV-INC-005
